Workbook

Sheet Mon DS
A1: Scan ID | B1: Name | C1: Company Name | D1: Time In | E1: Time Out | G1: Scan Out | I1: Timestamp | J1: SAP Number | L1: Not Scanned Yet | M1: DS | N1: Reverse Name
A2: NC90112534 | B2: =_xlfn.IFNA(VLOOKUP(A2,'Personnel List'!A$1:E$1284,5,FALSE),"") -> Sonia Bott | C2: =_xlfn.IFNA(VLOOKUP(A2,'Personnel List'!A$1:E$1284,4,FALSE),"") -> Coates Pty Ltd | D2: =IF(A2<>"",IF(D2<>"",D2,NOW()),"") -> 45530.215 | E2: =IFERROR(VLOOKUP(A2,G:I,3,FALSE),"Onsite") -> 45530.723 | G2: nc90136043 | I2: =IF(G2<>"",IF(I2<>"",I2,NOW()),"") -> 45530.704 | J2: =SUBSTITUTE(A2,"NC","") -> 90112534 | L2: {=_xlfn._xlws.FILTER(M2:M1000,(ISNA(MATCH(M2:M1000,N2:N1000,0))),"")} -> Ashby Kaukau, Bula | M2: {=_xlfn._xlws.FILTER('Mon Data'!E13:E361,ISNUMBER(_xlfn.XMATCH('Mon Data'!D13:D361,M1)))} -> Alcuizar, Edson | N2: =_xlfn.IFNA(VLOOKUP(A2,'Personnel List'!A$1:F$1284,6,FALSE),"") -> Bott, Sonia
A3: NC90070857 | B3: =_xlfn.IFNA(VLOOKUP(A3,'Personnel List'!A$1:E$1284,5,FALSE),"") -> Brodie Eaton | C3: =_xlfn.IFNA(VLOOKUP(A3,'Personnel List'!A$1:E$1284,4,FALSE),"") -> APMS | D3: =IF(A3<>"",IF(D3<>"",D3,NOW()),"") -> 45530.233 | E3: =IFERROR(VLOOKUP(A3,G:I,3,FALSE),"Onsite") -> Onsite | G3: NC90117684 | I3: =IF(G3<>"",IF(I3<>"",I3,NOW()),"") -> 45530.721 | J3: =SUBSTITUTE(A3,"NC","") -> 90070857 | L3: Bacal, Raser | M3: Altamura, Anthony | N3: =_xlfn.IFNA(VLOOKUP(A3,'Personnel List'!A$1:F$1284,6,FALSE),"") -> Eaton, Brodie
A4: NC90069096 | B4: =_xlfn.IFNA(VLOOKUP(A4,'Personnel List'!A$1:E$1284,5,FALSE),"") | C4: =_xlfn.IFNA(VLOOKUP(A4,'Personnel List'!A$1:E$1284,4,FALSE),"") | D4: =IF(A4<>"",IF(D4<>"",D4,NOW()),"") -> 45530.233 | E4: =IFERROR(VLOOKUP(A4,G:I,3,FALSE),"Onsite") -> Onsite | G4: NC90112534 | I4: =IF(G4<>"",IF(I4<>"",I4,NOW()),"") -> 45530.723 | J4: =SUBSTITUTE(A4,"NC","") -> 90069096 | L4: Baldock, Grant | M4: Ashby Kaukau, Bula | N4: =_xlfn.IFNA(VLOOKUP(A4,'Personnel List'!A$1:F$1284,6,FALSE),"")
A5: NC90117684 | B5: =_xlfn.IFNA(VLOOKUP(A5,'Personnel List'!A$1:E$1284,5,FALSE),"") -> Isobel Newman | C5: =_xlfn.IFNA(VLOOKUP(A5,'Personnel List'!A$1:E$1284,4,FALSE),"") -> Hays Personnel Services | D5: =IF(A5<>"",IF(D5<>"",D5,NOW()),"") -> 45530.234 | E5: =IFERROR(VLOOKUP(A5,G:I,3,FALSE),"Onsite") -> 45530.721 | G5: NC6324 | I5: =IF(G5<>"",IF(I5<>"",I5,NOW()),"") -> 45530.734 | J5: =SUBSTITUTE(A5,"NC","") -> 90117684 | L5: Benamati, Federico | M5: Bacal, Raser | N5: =_xlfn.IFNA(VLOOKUP(A5,'Personnel List'!A$1:F$1284,6,FALSE),"") -> Newman, Isobel
A6: NC90122588 | B6: =_xlfn.IFNA(VLOOKUP(A6,'Personnel List'!A$1:E$1284,5,FALSE),"") -> Dion Pene-Gavin | C6: =_xlfn.IFNA(VLOOKUP(A6,'Personnel List'!A$1:E$1284,4,FALSE),"") -> Global Mill Relines | D6: =IF(A6<>"",IF(D6<>"",D6,NOW()),"") -> 45530.237 | E6: =IFERROR(VLOOKUP(A6,G:I,3,FALSE),"Onsite") -> Onsite | G6: NC22249 | I6: =IF(G6<>"",IF(I6<>"",I6,NOW()),"") -> 45530.734 | J6: =SUBSTITUTE(A6,"NC","") -> 90122588 | L6: Bickham, Lincoln | M6: Baker, Alistair | N6: =_xlfn.IFNA(VLOOKUP(A6,'Personnel List'!A$1:F$1284,6,FALSE),"") -> Pene-Gavin, Dion
A7: NC90133607 | B7: =_xlfn.IFNA(VLOOKUP(A7,'Personnel List'!A$1:E$1284,5,FALSE),"") -> Paul Anderton | C7: =_xlfn.IFNA(VLOOKUP(A7,'Personnel List'!A$1:E$1284,4,FALSE),"") -> Technical Maintenance Support (TMS) | D7: =IF(A7<>"",IF(D7<>"",D7,NOW()),"") -> 45530.238 | E7: =IFERROR(VLOOKUP(A7,G:I,3,FALSE),"Onsite") -> Onsite | G7: NC18645 | I7: =IF(G7<>"",IF(I7<>"",I7,NOW()),"") -> 45530.734 | J7: =SUBSTITUTE(A7,"NC","") -> 90133607 | L7: Brewer, Corry | M7: Baldock, Grant | N7: =_xlfn.IFNA(VLOOKUP(A7,'Personnel List'!A$1:F$1284,6,FALSE),"") -> Anderton, Paul
A8: NC90109011 | B8: =_xlfn.IFNA(VLOOKUP(A8,'Personnel List'!A$1:E$1284,5,FALSE),"") | C8: =_xlfn.IFNA(VLOOKUP(A8,'Personnel List'!A$1:E$1284,4,FALSE),"") | D8: =IF(A8<>"",IF(D8<>"",D8,NOW()),"") -> 45530.239 | E8: =IFERROR(VLOOKUP(A8,G:I,3,FALSE),"Onsite") -> Onsite | G8: NC4870 | I8: =IF(G8<>"",IF(I8<>"",I8,NOW()),"") -> 45530.734 | J8: =SUBSTITUTE(A8,"NC","") -> 90109011 | L8: Brooking, Desmond | M8: Batty, Noah | N8: =_xlfn.IFNA(VLOOKUP(A8,'Personnel List'!A$1:F$1284,6,FALSE),"")
A9: NC90136780 | B9: =_xlfn.IFNA(VLOOKUP(A9,'Personnel List'!A$1:E$1284,5,FALSE),"") | C9: =_xlfn.IFNA(VLOOKUP(A9,'Personnel List'!A$1:E$1284,4,FALSE),"") | D9: =IF(A9<>"",IF(D9<>"",D9,NOW()),"") -> 45530.239 | E9: =IFERROR(VLOOKUP(A9,G:I,3,FALSE),"Onsite") -> Onsite | G9: NC19989 | I9: =IF(G9<>"",IF(I9<>"",I9,NOW()),"") -> 45530.734 | J9: =SUBSTITUTE(A9,"NC","") -> 90136780 | L9: Brown, Archie | M9: Benamati, Federico | N9: =_xlfn.IFNA(VLOOKUP(A9,'Personnel List'!A$1:F$1284,6,FALSE),"")
A10: NC90135965 | B10: =_xlfn.IFNA(VLOOKUP(A10,'Personnel List'!A$1:E$1284,5,FALSE),"") | C10: =_xlfn.IFNA(VLOOKUP(A10,'Personnel List'!A$1:E$1284,4,FALSE),"") | D10: =IF(A10<>"",IF(D10<>"",D10,NOW()),"") -> 45530.241 | E10: =IFERROR(VLOOKUP(A10,G:I,3,FALSE),"Onsite") -> Onsite | G10: NC18952 | I10: =IF(G10<>"",IF(I10<>"",I10,NOW()),"") -> 45530.734 | J10: =SUBSTITUTE(A10,"NC","") -> 90135965 | L10: Brown, Dominic | M10: Bendjebbour, Nihad | N10: =_xlfn.IFNA(VLOOKUP(A10,'Personnel List'!A$1:F$1284,6,FALSE),"")
A11: NC90136947 | B11: =_xlfn.IFNA(VLOOKUP(A11,'Personnel List'!A$1:E$1284,5,FALSE),"") | C11: =_xlfn.IFNA(VLOOKUP(A11,'Personnel List'!A$1:E$1284,4,FALSE),"") | D11: =IF(A11<>"",IF(D11<>"",D11,NOW()),"") -> 45530.249 | E11: =IFERROR(VLOOKUP(A11,G:I,3,FALSE),"Onsite") -> Onsite | I11: =IF(G11<>"",IF(I11<>"",I11,NOW()),"") | J11: =SUBSTITUTE(A11,"NC","") -> 90136947 | L11: Bullock, John | M11: Bickham, Lincoln | N11: =_xlfn.IFNA(VLOOKUP(A11,'Personnel List'!A$1:F$1284,6,FALSE),"")
A12: nc90136392 | B12: =_xlfn.IFNA(VLOOKUP(A12,'Personnel List'!A$1:E$1284,5,FALSE),"") -> Rodelio Lanite | C12: =_xlfn.IFNA(VLOOKUP(A12,'Personnel List'!A$1:E$1284,4,FALSE),"") -> APMS | D12: =IF(A12<>"",IF(D12<>"",D12,NOW()),"") -> 45530.257 | E12: =IFERROR(VLOOKUP(A12,G:I,3,FALSE),"Onsite") -> Onsite | I12: =IF(G12<>"",IF(I12<>"",I12,NOW()),"") | J12: =SUBSTITUTE(A12,"NC","") -> nc90136392 | L12: Cahill, Mark | M12: Bott, Sonia | N12: =_xlfn.IFNA(VLOOKUP(A12,'Personnel List'!A$1:F$1284,6,FALSE),"") -> Lanite, Rodelio
A13: nc90136823 | B13: =_xlfn.IFNA(VLOOKUP(A13,'Personnel List'!A$1:E$1284,5,FALSE),"") | C13: =_xlfn.IFNA(VLOOKUP(A13,'Personnel List'!A$1:E$1284,4,FALSE),"") | D13: =IF(A13<>"",IF(D13<>"",D13,NOW()),"") -> 45530.258 | E13: =IFERROR(VLOOKUP(A13,G:I,3,FALSE),"Onsite") -> Onsite | I13: =IF(G13<>"",IF(I13<>"",I13,NOW()),"") | J13: =SUBSTITUTE(A13,"NC","") -> nc90136823 | L13: Chase, Nicholas | M13: Boyd, Graham | N13: =_xlfn.IFNA(VLOOKUP(A13,'Personnel List'!A$1:F$1284,6,FALSE),"")
A14: nc90135150 | B14: =_xlfn.IFNA(VLOOKUP(A14,'Personnel List'!A$1:E$1284,5,FALSE),"") -> Ranie Lanete | C14: =_xlfn.IFNA(VLOOKUP(A14,'Personnel List'!A$1:E$1284,4,FALSE),"") -> APMS | D14: =IF(A14<>"",IF(D14<>"",D14,NOW()),"") -> 45530.258 | E14: =IFERROR(VLOOKUP(A14,G:I,3,FALSE),"Onsite") -> Onsite | I14: =IF(G14<>"",IF(I14<>"",I14,NOW()),"") | J14: =SUBSTITUTE(A14,"NC","") -> nc90135150 | L14: Courtney, Peter | M14: Brewer, Corry | N14: =_xlfn.IFNA(VLOOKUP(A14,'Personnel List'!A$1:F$1284,6,FALSE),"") -> Lanete, Ranie
A15: nc90003219 | B15: =_xlfn.IFNA(VLOOKUP(A15,'Personnel List'!A$1:E$1284,5,FALSE),"") -> Joel Tarchini | C15: =_xlfn.IFNA(VLOOKUP(A15,'Personnel List'!A$1:E$1284,4,FALSE),"") -> Global Mill Relines | D15: =IF(A15<>"",IF(D15<>"",D15,NOW()),"") -> 45530.258 | E15: =IFERROR(VLOOKUP(A15,G:I,3,FALSE),"Onsite") -> Onsite | I15: =IF(G15<>"",IF(I15<>"",I15,NOW()),"") | J15: =SUBSTITUTE(A15,"NC","") -> nc90003219 | L15: Dalton, Ricky | M15: Brooking, Desmond | N15: =_xlfn.IFNA(VLOOKUP(A15,'Personnel List'!A$1:F$1284,6,FALSE),"") -> Tarchini, Joel
A16: nc90134023 | B16: =_xlfn.IFNA(VLOOKUP(A16,'Personnel List'!A$1:E$1284,5,FALSE),"") | C16: =_xlfn.IFNA(VLOOKUP(A16,'Personnel List'!A$1:E$1284,4,FALSE),"") | D16: =IF(A16<>"",IF(D16<>"",D16,NOW()),"") -> 45530.258 | E16: =IFERROR(VLOOKUP(A16,G:I,3,FALSE),"Onsite") -> Onsite | I16: =IF(G16<>"",IF(I16<>"",I16,NOW()),"") | J16: =SUBSTITUTE(A16,"NC","") -> nc90134023 | L16: Edwards, Lachlan | M16: Brown, Archie | N16: =_xlfn.IFNA(VLOOKUP(A16,'Personnel List'!A$1:F$1284,6,FALSE),"")
A17: nc90123711 | B17: =_xlfn.IFNA(VLOOKUP(A17,'Personnel List'!A$1:E$1284,5,FALSE),"") -> Germar Pfeuffer | C17: =_xlfn.IFNA(VLOOKUP(A17,'Personnel List'!A$1:E$1284,4,FALSE),"") -> Technical Maintenance Support (TMS) | D17: =IF(A17<>"",IF(D17<>"",D17,NOW()),"") -> 45530.259 | E17: =IFERROR(VLOOKUP(A17,G:I,3,FALSE),"Onsite") -> Onsite | I17: =IF(G17<>"",IF(I17<>"",I17,NOW()),"") | J17: =SUBSTITUTE(A17,"NC","") -> nc90123711 | L17: Egg, Christoph | M17: Brown, Dominic | N17: =_xlfn.IFNA(VLOOKUP(A17,'Personnel List'!A$1:F$1284,6,FALSE),"") -> Pfeuffer, Germar
A18: nc90137520 | B18: =_xlfn.IFNA(VLOOKUP(A18,'Personnel List'!A$1:E$1284,5,FALSE),"") | C18: =_xlfn.IFNA(VLOOKUP(A18,'Personnel List'!A$1:E$1284,4,FALSE),"") | D18: =IF(A18<>"",IF(D18<>"",D18,NOW()),"") -> 45530.259 | E18: =IFERROR(VLOOKUP(A18,G:I,3,FALSE),"Onsite") -> Onsite | I18: =IF(G18<>"",IF(I18<>"",I18,NOW()),"") | J18: =SUBSTITUTE(A18,"NC","") -> nc90137520 | L18: Eylward, Rhett | M18: Bullock, John | N18: =_xlfn.IFNA(VLOOKUP(A18,'Personnel List'!A$1:F$1284,6,FALSE),"")
A19: nc90050488 | B19: =_xlfn.IFNA(VLOOKUP(A19,'Personnel List'!A$1:E$1284,5,FALSE),"") -> Tyler Harris | C19: =_xlfn.IFNA(VLOOKUP(A19,'Personnel List'!A$1:E$1284,4,FALSE),"") -> Geraldton Hydraulics | D19: =IF(A19<>"",IF(D19<>"",D19,NOW()),"") -> 45530.259 | E19: =IFERROR(VLOOKUP(A19,G:I,3,FALSE),"Onsite") -> Onsite | I19: =IF(G19<>"",IF(I19<>"",I19,NOW()),"") | J19: =SUBSTITUTE(A19,"NC","") -> nc90050488 | L19: Foley, Megan | M19: Cahill, Mark | N19: =_xlfn.IFNA(VLOOKUP(A19,'Personnel List'!A$1:F$1284,6,FALSE),"") -> Harris, Tyler
A20: NC6324 | B20: =_xlfn.IFNA(VLOOKUP(A20,'Personnel List'!A$1:E$1284,5,FALSE),"") -> Davin Lord | C20: =_xlfn.IFNA(VLOOKUP(A20,'Personnel List'!A$1:E$1284,4,FALSE),"") -> Newmont | D20: =IF(A20<>"",IF(D20<>"",D20,NOW()),"") -> 45530.262 | E20: =IFERROR(VLOOKUP(A20,G:I,3,FALSE),"Onsite") -> 45530.734 | I20: =IF(G20<>"",IF(I20<>"",I20,NOW()),"") | J20: =SUBSTITUTE(A20,"NC","") -> 6324 | L20: Gates, Darren | M20: Chase, Nicholas | N20: =_xlfn.IFNA(VLOOKUP(A20,'Personnel List'!A$1:F$1284,6,FALSE),"") -> Lord, Davin
A21: NC22249 | B21: =_xlfn.IFNA(VLOOKUP(A21,'Personnel List'!A$1:E$1284,5,FALSE),"") -> Renatta Leofo | C21: =_xlfn.IFNA(VLOOKUP(A21,'Personnel List'!A$1:E$1284,4,FALSE),"") -> Newmont | D21: =IF(A21<>"",IF(D21<>"",D21,NOW()),"") -> 45530.262 | E21: =IFERROR(VLOOKUP(A21,G:I,3,FALSE),"Onsite") -> 45530.734 | I21: =IF(G21<>"",IF(I21<>"",I21,NOW()),"") | J21: =SUBSTITUTE(A21,"NC","") -> 22249 | L21: Geary, William | M21: Cooper, Travis | N21: =_xlfn.IFNA(VLOOKUP(A21,'Personnel List'!A$1:F$1284,6,FALSE),"") -> Leofo, Renatta
A22: NC18645 | B22: =_xlfn.IFNA(VLOOKUP(A22,'Personnel List'!A$1:E$1284,5,FALSE),"") -> Glenn Lavery | C22: =_xlfn.IFNA(VLOOKUP(A22,'Personnel List'!A$1:E$1284,4,FALSE),"") -> Newmont | D22: =IF(A22<>"",IF(D22<>"",D22,NOW()),"") -> 45530.262 | E22: =IFERROR(VLOOKUP(A22,G:I,3,FALSE),"Onsite") -> 45530.734 | I22: =IF(G22<>"",IF(I22<>"",I22,NOW()),"") | J22: =SUBSTITUTE(A22,"NC","") -> 18645 | L22: Gravner, Stuart | M22: Coupe, Lee | N22: =_xlfn.IFNA(VLOOKUP(A22,'Personnel List'!A$1:F$1284,6,FALSE),"") -> Lavery, Glenn
... A24: NC19989 | B24: =_xlfn.IFNA(VLOOKUP(A24,'Personnel List'!A$1:E$1284,5,FALSE),"") -> Jason Pendreigh | C24: =_xlfn.IFNA(VLOOKUP(A24,'Personnel List'!A$1:E$1284,4,FALSE),"") -> Newmont | D24: =IF(A24<>"",IF(D24<>"",D24,NOW()),"") -> 45530.262 | E24: =IFERROR(VLOOKUP(A24,G:I,3,FALSE),"Onsite") -> 45530.734 | I24: =IF(G24<>"",IF(I24<>"",I24,NOW()),"") | J24: =SUBSTITUTE(A24,"NC","") -> 19989 | L24: Hari, Dinnesh | M24: Dalton, Ricky | N24: =_xlfn.IFNA(VLOOKUP(A24,'Personnel List'!A$1:F$1284,6,FALSE),"") -> Pendreigh, Jason
B25: =_xlfn.IFNA(VLOOKUP(A25,'Personnel List'!A$1:E$1284,5,FALSE),"") | C25: =_xlfn.IFNA(VLOOKUP(A25,'Personnel List'!A$1:E$1284,4,FALSE),"") | D25: =IF(A25<>"",IF(D25<>"",D25,NOW()),"") | E25: =IFERROR(VLOOKUP(A25,G:I,3,FALSE),"Onsite") -> Onsite | I25: =IF(G25<>"",IF(I25<>"",I25,NOW()),"") | J25: =SUBSTITUTE(A25,"NC","") | L25: Harmsworth, Benjamin | M25: Donges, Trent | N25: =_xlfn.IFNA(VLOOKUP(A25,'Personnel List'!A$1:F$1284,6,FALSE),"")
A26: nc90134808 | B26: =_xlfn.IFNA(VLOOKUP(A26,'Personnel List'!A$1:E$1284,5,FALSE),"") -> Graham Boyd | C26: =_xlfn.IFNA(VLOOKUP(A26,'Personnel List'!A$1:E$1284,4,FALSE),"") -> Boom Cranes | D26: =IF(A26<>"",IF(D26<>"",D26,NOW()),"") -> 45530.262 | E26: =IFERROR(VLOOKUP(A26,G:I,3,FALSE),"Onsite") -> Onsite | I26: =IF(G26<>"",IF(I26<>"",I26,NOW()),"") | J26: =SUBSTITUTE(A26,"NC","") -> nc90134808 | L26: Hay, Shaquille | M26: Eaton, Brodie | N26: =_xlfn.IFNA(VLOOKUP(A26,'Personnel List'!A$1:F$1284,6,FALSE),"") -> Boyd, Graham
A27: nc22794 | B27: =_xlfn.IFNA(VLOOKUP(A27,'Personnel List'!A$1:E$1284,5,FALSE),"") -> Trent Donges | C27: =_xlfn.IFNA(VLOOKUP(A27,'Personnel List'!A$1:E$1284,4,FALSE),"") -> Newmont | D27: =IF(A27<>"",IF(D27<>"",D27,NOW()),"") -> 45530.263 | E27: =IFERROR(VLOOKUP(A27,G:I,3,FALSE),"Onsite") -> Onsite | I27: =IF(G27<>"",IF(I27<>"",I27,NOW()),"") | J27: =SUBSTITUTE(A27,"NC","") -> nc22794 | L27: Hitchens, Caleb | M27: Eclarino, Jesus | N27: =_xlfn.IFNA(VLOOKUP(A27,'Personnel List'!A$1:F$1284,6,FALSE),"") -> Donges, Trent
A28: nc23672 | B28: =_xlfn.IFNA(VLOOKUP(A28,'Personnel List'!A$1:E$1284,5,FALSE),"") -> Lyndon Kattler | C28: =_xlfn.IFNA(VLOOKUP(A28,'Personnel List'!A$1:E$1284,4,FALSE),"") -> Newmont | D28: =IF(A28<>"",IF(D28<>"",D28,NOW()),"") -> 45530.263 | E28: =IFERROR(VLOOKUP(A28,G:I,3,FALSE),"Onsite") -> Onsite | I28: =IF(G28<>"",IF(I28<>"",I28,NOW()),"") | J28: =SUBSTITUTE(A28,"NC","") -> nc23672 | L28: Hunt, Simonski | M28: Edwards, Lachlan | N28: =_xlfn.IFNA(VLOOKUP(A28,'Personnel List'!A$1:F$1284,6,FALSE),"") -> Kattler, Lyndon
A29: nc90134414 | B29: =_xlfn.IFNA(VLOOKUP(A29,'Personnel List'!A$1:E$1284,5,FALSE),"") -> Noah Batty | C29: =_xlfn.IFNA(VLOOKUP(A29,'Personnel List'!A$1:E$1284,4,FALSE),"") -> SCOTFORD & FENNESSY | D29: =IF(A29<>"",IF(D29<>"",D29,NOW()),"") -> 45530.263 | E29: =IFERROR(VLOOKUP(A29,G:I,3,FALSE),"Onsite") -> Onsite | I29: =IF(G29<>"",IF(I29<>"",I29,NOW()),"") | J29: =SUBSTITUTE(A29,"NC","") -> nc90134414 | L29: Kho, Janelle | M29: Egg, Christoph | N29: =_xlfn.IFNA(VLOOKUP(A29,'Personnel List'!A$1:F$1284,6,FALSE),"") -> Batty, Noah
A30: nc90094237 | B30: =_xlfn.IFNA(VLOOKUP(A30,'Personnel List'!A$1:E$1284,5,FALSE),"") -> Edward Santhanam | C30: =_xlfn.IFNA(VLOOKUP(A30,'Personnel List'!A$1:E$1284,4,FALSE),"") -> Losugen | D30: =IF(A30<>"",IF(D30<>"",D30,NOW()),"") -> 45530.263 | E30: =IFERROR(VLOOKUP(A30,G:I,3,FALSE),"Onsite") -> Onsite | I30: =IF(G30<>"",IF(I30<>"",I30,NOW()),"") | J30: =SUBSTITUTE(A30,"NC","") -> nc90094237 | L30: Kim, Jee Yeun | M30: Eylward, Rhett | N30: =_xlfn.IFNA(VLOOKUP(A30,'Personnel List'!A$1:F$1284,6,FALSE),"") -> Santhanam, Edward
A31: nc20304 | B31: =_xlfn.IFNA(VLOOKUP(A31,'Personnel List'!A$1:E$1284,5,FALSE),"") -> Alistair Baker | C31: =_xlfn.IFNA(VLOOKUP(A31,'Personnel List'!A$1:E$1284,4,FALSE),"") -> Newmont | D31: =IF(A31<>"",IF(D31<>"",D31,NOW()),"") -> 45530.263 | E31: =IFERROR(VLOOKUP(A31,G:I,3,FALSE),"Onsite") -> Onsite | I31: =IF(G31<>"",IF(I31<>"",I31,NOW()),"") | J31: =SUBSTITUTE(A31,"NC","") -> nc20304 | L31: Lanete, Rannie | M31: Foley, Megan | N31: =_xlfn.IFNA(VLOOKUP(A31,'Personnel List'!A$1:F$1284,6,FALSE),"") -> Baker, Alistair
A32: nc90130583 | B32: =_xlfn.IFNA(VLOOKUP(A32,'Personnel List'!A$1:E$1284,5,FALSE),"") -> Martin Mulhall | C32: =_xlfn.IFNA(VLOOKUP(A32,'Personnel List'!A$1:E$1284,4,FALSE),"") -> Mader Contracting | D32: =IF(A32<>"",IF(D32<>"",D32,NOW()),"") -> 45530.263 | E32: =IFERROR(VLOOKUP(A32,G:I,3,FALSE),"Onsite") -> Onsite | I32: =IF(G32<>"",IF(I32<>"",I32,NOW()),"") | J32: =SUBSTITUTE(A32,"NC","") -> nc90130583 | L32: Lim, Rangatira | M32: Gates, Darren | N32: =_xlfn.IFNA(VLOOKUP(A32,'Personnel List'!A$1:F$1284,6,FALSE),"") -> Mulhall, Martin
A33: nc90138283 | B33: =_xlfn.IFNA(VLOOKUP(A33,'Personnel List'!A$1:E$1284,5,FALSE),"") | E33: =IFERROR(VLOOKUP(A33,G:I,3,FALSE),"Onsite") -> Onsite | I33: =IF(G33<>"",IF(I33<>"",I33,NOW()),"") | J33: =SUBSTITUTE(A33,"NC","") -> nc90138283 | L33: Lim, Taine | M33: Geary, William | N33: =_xlfn.IFNA(VLOOKUP(A33,'Personnel List'!A$1:F$1284,6,FALSE),"")
A34: nc23783 | B34: =_xlfn.IFNA(VLOOKUP(A34,'Personnel List'!A$1:E$1284,5,FALSE),"") -> Travis Cooper | C34: =_xlfn.IFNA(VLOOKUP(A34,'Personnel List'!A$1:E$1284,4,FALSE),"") -> Newmont | D34: =IF(A34<>"",IF(D34<>"",D34,NOW()),"") -> 45530.263 | E34: =IFERROR(VLOOKUP(A34,G:I,3,FALSE),"Onsite") -> Onsite | I34: =IF(G34<>"",IF(I34<>"",I34,NOW()),"") | J34: =SUBSTITUTE(A34,"NC","") -> nc23783 | L34: Lord, Darren | M34: Gravner, Stuart | N34: =_xlfn.IFNA(VLOOKUP(A34,'Personnel List'!A$1:F$1284,6,FALSE),"") -> Cooper, Travis
A35: nc21191 | B35: =_xlfn.IFNA(VLOOKUP(A35,'Personnel List'!A$1:E$1284,5,FALSE),"") -> Conner Souey | C35: =_xlfn.IFNA(VLOOKUP(A35,'Personnel List'!A$1:E$1284,4,FALSE),"") -> Newmont | D35: =IF(A35<>"",IF(D35<>"",D35,NOW()),"") -> 45530.263 | E35: =IFERROR(VLOOKUP(A35,G:I,3,FALSE),"Onsite") -> Onsite | I35: =IF(G35<>"",IF(I35<>"",I35,NOW()),"") | J35: =SUBSTITUTE(A35,"NC","") -> nc21191 | L35: Maclean, Bronson | M35: Gunn, Michelle | N35: =_xlfn.IFNA(VLOOKUP(A35,'Personnel List'!A$1:F$1284,6,FALSE),"") -> Souey, Conner
A36: nc24490 | B36: =_xlfn.IFNA(VLOOKUP(A36,'Personnel List'!A$1:E$1284,5,FALSE),"") -> Thomas Ryan | C36: =_xlfn.IFNA(VLOOKUP(A36,'Personnel List'!A$1:E$1284,4,FALSE),"") -> Newmont | D36: =IF(A36<>"",IF(D36<>"",D36,NOW()),"") -> 45530.263 | E36: =IFERROR(VLOOKUP(A36,G:I,3,FALSE),"Onsite") -> Onsite | I36: =IF(G36<>"",IF(I36<>"",I36,NOW()),"") | J36: =SUBSTITUTE(A36,"NC","") -> nc24490 | L36: Madronero, Angelo | M36: Ham, Meng | N36: =_xlfn.IFNA(VLOOKUP(A36,'Personnel List'!A$1:F$1284,6,FALSE),"") -> Ryan, Thomas
A37: nc90138122 | B37: =_xlfn.IFNA(VLOOKUP(A37,'Personnel List'!A$1:E$1284,5,FALSE),"") | C37: =_xlfn.IFNA(VLOOKUP(A37,'Personnel List'!A$1:E$1284,4,FALSE),"") | D37: =IF(A37<>"",IF(D37<>"",D37,NOW()),"") -> 45530.263 | E37: =IFERROR(VLOOKUP(A37,G:I,3,FALSE),"Onsite") -> Onsite | I37: =IF(G37<>"",IF(I37<>"",I37,NOW()),"") | J37: =SUBSTITUTE(A37,"NC","") -> nc90138122 | L37: McGougan, Archie | M37: Hari, Dinnesh | N37: =_xlfn.IFNA(VLOOKUP(A37,'Personnel List'!A$1:F$1284,6,FALSE),"")
A38: nc23410 | B38: =_xlfn.IFNA(VLOOKUP(A38,'Personnel List'!A$1:E$1284,5,FALSE),"") -> Trevor Simpson | C38: =_xlfn.IFNA(VLOOKUP(A38,'Personnel List'!A$1:E$1284,4,FALSE),"") -> Newmont | D38: =IF(A38<>"",IF(D38<>"",D38,NOW()),"") -> 45530.263 | E38: =IFERROR(VLOOKUP(A38,G:I,3,FALSE),"Onsite") -> Onsite | I38: =IF(G38<>"",IF(I38<>"",I38,NOW()),"") | J38: =SUBSTITUTE(A38,"NC","") -> nc23410 | L38: McLelland, Scott | M38: Harmsworth, Benjamin | N38: =_xlfn.IFNA(VLOOKUP(A38,'Personnel List'!A$1:F$1284,6,FALSE),"") -> Simpson, Trevor
A39: nc24719 | B39: =_xlfn.IFNA(VLOOKUP(A39,'Personnel List'!A$1:E$1284,5,FALSE),"") -> Emily Lane | C39: =_xlfn.IFNA(VLOOKUP(A39,'Personnel List'!A$1:E$1284,4,FALSE),"") -> Newmont | D39: =IF(A39<>"",IF(D39<>"",D39,NOW()),"") -> 45530.263 | E39: =IFERROR(VLOOKUP(A39,G:I,3,FALSE),"Onsite") -> Onsite | I39: =IF(G39<>"",IF(I39<>"",I39,NOW()),"") | J39: =SUBSTITUTE(A39,"NC","") -> nc24719 | L39: McNally, Wade | M39: Harris, Tyler | N39: =_xlfn.IFNA(VLOOKUP(A39,'Personnel List'!A$1:F$1284,6,FALSE),"") -> Lane, Emily
A40: nc90137948 | B40: =_xlfn.IFNA(VLOOKUP(A40,'Personnel List'!A$1:E$1284,5,FALSE),"") | C40: =_xlfn.IFNA(VLOOKUP(A40,'Personnel List'!A$1:E$1284,4,FALSE),"") | D40: =IF(A40<>"",IF(D40<>"",D40,NOW()),"") -> 45530.263 | E40: =IFERROR(VLOOKUP(A40,G:I,3,FALSE),"Onsite") -> Onsite | I40: =IF(G40<>"",IF(I40<>"",I40,NOW()),"") | J40: =SUBSTITUTE(A40,"NC","") -> nc90137948 | L40: Moore, Simon | M40: Hay, Shaquille | N40: =_xlfn.IFNA(VLOOKUP(A40,'Personnel List'!A$1:F$1284,6,FALSE),"")
A41: nc22900 | D41: =IF(A41<>"",IF(D41<>"",D41,NOW()),"") -> 45530.263 | E41: =IFERROR(VLOOKUP(A41,G:I,3,FALSE),"Onsite") -> Onsite | I41: =IF(G41<>"",IF(I41<>"",I41,NOW()),"") | J41: =SUBSTITUTE(A41,"NC","") -> nc22900 | L41: Morgan, Hauauru | M41: Hitchens, Caleb | N41: =_xlfn.IFNA(VLOOKUP(A41,'Personnel List'!A$1:F$1284,6,FALSE),"") -> Brown, Dominic
A42: nc24687 | B42: =_xlfn.IFNA(VLOOKUP(A42,'Personnel List'!A$1:E$1284,5,FALSE),"") -> Sean Smethurst | C42: =_xlfn.IFNA(VLOOKUP(A42,'Personnel List'!A$1:E$1284,4,FALSE),"") -> Newmont | D42: =IF(A42<>"",IF(D42<>"",D42,NOW()),"") -> 45530.263 | E42: =IFERROR(VLOOKUP(A42,G:I,3,FALSE),"Onsite") -> Onsite | I42: =IF(G42<>"",IF(I42<>"",I42,NOW()),"") | J42: =SUBSTITUTE(A42,"NC","") -> nc24687 | L42: Mulligan, Wesley | M42: Hunt, Simonski | N42: =_xlfn.IFNA(VLOOKUP(A42,'Personnel List'!A$1:F$1284,6,FALSE),"") -> Smethurst, Sean
A43: nc22280 | B43: =_xlfn.IFNA(VLOOKUP(A43,'Personnel List'!A$1:E$1284,5,FALSE),"") -> Lee Coupe | C43: =_xlfn.IFNA(VLOOKUP(A43,'Personnel List'!A$1:E$1284,4,FALSE),"") -> Newmont | D43: =IF(A43<>"",IF(D43<>"",D43,NOW()),"") -> 45530.263 | E43: =IFERROR(VLOOKUP(A43,G:I,3,FALSE),"Onsite") -> Onsite | I43: =IF(G43<>"",IF(I43<>"",I43,NOW()),"") | J43: =SUBSTITUTE(A43,"NC","") -> nc22280 | L43: Murray, Reece | M43: Jones, Cameron | N43: =_xlfn.IFNA(VLOOKUP(A43,'Personnel List'!A$1:F$1284,6,FALSE),"") -> Coupe, Lee
A44: nc16002 | B44: =_xlfn.IFNA(VLOOKUP(A44,'Personnel List'!A$1:E$1284,5,FALSE),"") -> Simon Sheehan | C44: =_xlfn.IFNA(VLOOKUP(A44,'Personnel List'!A$1:E$1284,4,FALSE),"") -> Newmont | D44: =IF(A44<>"",IF(D44<>"",D44,NOW()),"") -> 45530.263 | E44: =IFERROR(VLOOKUP(A44,G:I,3,FALSE),"Onsite") -> Onsite | I44: =IF(G44<>"",IF(I44<>"",I44,NOW()),"") | J44: =SUBSTITUTE(A44,"NC","") -> nc16002 | L44: Neal, Adam | M44: Kattler, Lyndon | N44: =_xlfn.IFNA(VLOOKUP(A44,'Personnel List'!A$1:F$1284,6,FALSE),"") -> Sheehan, Simon
A45: nc90047222 | B45: =_xlfn.IFNA(VLOOKUP(A45,'Personnel List'!A$1:E$1284,5,FALSE),"") -> Russell-Kingi Tawaka | C45: =_xlfn.IFNA(VLOOKUP(A45,'Personnel List'!A$1:E$1284,4,FALSE),"") -> SMS Group Services | D45: =IF(A45<>"",IF(D45<>"",D45,NOW()),"") -> 45530.263 | E45: =IFERROR(VLOOKUP(A45,G:I,3,FALSE),"Onsite") -> Onsite | I45: =IF(G45<>"",IF(I45<>"",I45,NOW()),"") | J45: =SUBSTITUTE(A45,"NC","") -> nc90047222 | L45: Ness, Bradley | M45: Kho, Janelle | N45: =_xlfn.IFNA(VLOOKUP(A45,'Personnel List'!A$1:F$1284,6,FALSE),"") -> Tawaka, Russell-Kingi
A46: nc90040292 | B46: =_xlfn.IFNA(VLOOKUP(A46,'Personnel List'!A$1:E$1284,5,FALSE),"") -> Jerry Taura | C46: =_xlfn.IFNA(VLOOKUP(A46,'Personnel List'!A$1:E$1284,4,FALSE),"") -> SMS Group Services | D46: =IF(A46<>"",IF(D46<>"",D46,NOW()),"") -> 45530.263 | E46: =IFERROR(VLOOKUP(A46,G:I,3,FALSE),"Onsite") -> Onsite | I46: =IF(G886<>"",IF(I46<>"",I46,NOW()),"") | J46: =SUBSTITUTE(A46,"NC","") -> nc90040292 | L46: Newman, Bella | M46: Kim, Jee Yeun | N46: =_xlfn.IFNA(VLOOKUP(A46,'Personnel List'!A$1:F$1284,6,FALSE),"") -> Taura, Jerry
A47: nc90131908 | B47: =_xlfn.IFNA(VLOOKUP(A47,'Personnel List'!A$1:E$1284,5,FALSE),"") | C47: =_xlfn.IFNA(VLOOKUP(A47,'Personnel List'!A$1:E$1284,4,FALSE),"") | D47: =IF(A47<>"",IF(D47<>"",D47,NOW()),"") -> 45530.263 | E47: =IFERROR(VLOOKUP(A47,G:I,3,FALSE),"Onsite") -> Onsite | I47: =IF(G887<>"",IF(I47<>"",I47,NOW()),"") | J47: =SUBSTITUTE(A47,"NC","") -> nc90131908 | L47: O'Connell, Reece | M47: Krause, Colin | N47: =_xlfn.IFNA(VLOOKUP(A47,'Personnel List'!A$1:F$1284,6,FALSE),"")
A48: nc90112330 | B48: =_xlfn.IFNA(VLOOKUP(A48,'Personnel List'!A$1:E$1284,5,FALSE),"") -> Shannon McGregor | C48: =_xlfn.IFNA(VLOOKUP(A48,'Personnel List'!A$1:E$1284,4,FALSE),"") -> Boom Cranes | D48: =IF(A48<>"",IF(D48<>"",D48,NOW()),"") -> 45530.264 | E48: =IFERROR(VLOOKUP(A48,G:I,3,FALSE),"Onsite") -> Onsite | I48: =IF(G888<>"",IF(I48<>"",I48,NOW()),"") | J48: =SUBSTITUTE(A48,"NC","") -> nc90112330 | L48: Parrott, Kevin | M48: Lane, Emily | N48: =_xlfn.IFNA(VLOOKUP(A48,'Personnel List'!A$1:F$1284,6,FALSE),"") -> McGregor, Shannon
A49: nc90107544 | B49: =_xlfn.IFNA(VLOOKUP(A49,'Personnel List'!A$1:E$1284,5,FALSE),"") -> Hohepa Tangiora | C49: =_xlfn.IFNA(VLOOKUP(A49,'Personnel List'!A$1:E$1284,4,FALSE),"") -> Minprovise | D49: =IF(A49<>"",IF(D49<>"",D49,NOW()),"") -> 45530.264 | E49: =IFERROR(VLOOKUP(A49,G:I,3,FALSE),"Onsite") -> Onsite | I49: =IF(G889<>"",IF(I49<>"",I49,NOW()),"") | J49: =SUBSTITUTE(A49,"NC","") -> nc90107544 | L49: Peck, Troy | M49: Lanete, Rannie | N49: =_xlfn.IFNA(VLOOKUP(A49,'Personnel List'!A$1:F$1284,6,FALSE),"") -> Tangiora, Hohepa
A50: nc90117309 | B50: =_xlfn.IFNA(VLOOKUP(A50,'Personnel List'!A$1:E$1284,5,FALSE),"") -> Eleatha Tate | C50: =_xlfn.IFNA(VLOOKUP(A50,'Personnel List'!A$1:E$1284,4,FALSE),"") -> Minprovise | D50: =IF(A50<>"",IF(D50<>"",D50,NOW()),"") -> 45530.264 | E50: =IFERROR(VLOOKUP(A50,G:I,3,FALSE),"Onsite") -> Onsite | I50: =IF(G890<>"",IF(I50<>"",I50,NOW()),"") | J50: =SUBSTITUTE(A50,"NC","") -> nc90117309 | L50: Pluschke, Jack | M50: Lavery, Glenn | N50: =_xlfn.IFNA(VLOOKUP(A50,'Personnel List'!A$1:F$1284,6,FALSE),"") -> Tate, Eleatha
A51: nc90117309 | B51: =_xlfn.IFNA(VLOOKUP(A51,'Personnel List'!A$1:E$1284,5,FALSE),"") -> Eleatha Tate | C51: =_xlfn.IFNA(VLOOKUP(A51,'Personnel List'!A$1:E$1284,4,FALSE),"") -> Minprovise | D51: =IF(A51<>"",IF(D51<>"",D51,NOW()),"") -> 45530.264 | E51: =IFERROR(VLOOKUP(A51,G:I,3,FALSE),"Onsite") -> Onsite | I51: =IF(G891<>"",IF(I51<>"",I51,NOW()),"") | J51: =SUBSTITUTE(A51,"NC","") -> nc90117309 | L51: Pucci, Stefano | M51: Leofo, Renatta | N51: =_xlfn.IFNA(VLOOKUP(A51,'Personnel List'!A$1:F$1284,6,FALSE),"") -> Tate, Eleatha
A52: nc90116535 | B52: =_xlfn.IFNA(VLOOKUP(A52,'Personnel List'!A$1:E$1284,5,FALSE),"") -> David Whittering | C52: =_xlfn.IFNA(VLOOKUP(A52,'Personnel List'!A$1:E$1284,4,FALSE),"") -> Minprovise | D52: =IF(A52<>"",IF(D52<>"",D52,NOW()),"") -> 45530.264 | E52: =IFERROR(VLOOKUP(A52,G:I,3,FALSE),"Onsite") -> Onsite | I52: =IF(G892<>"",IF(I52<>"",I52,NOW()),"") | J52: =SUBSTITUTE(A52,"NC","") -> nc90116535 | L52: Rowley, John | M52: Lim, Rangatira | N52: =_xlfn.IFNA(VLOOKUP(A52,'Personnel List'!A$1:F$1284,6,FALSE),"") -> Whittering, David
A53: nc90118868 | B53: =_xlfn.IFNA(VLOOKUP(A53,'Personnel List'!A$1:E$1284,5,FALSE),"") -> Cameron Jones | D53: =IF(A53<>"",IF(D53<>"",D53,NOW()),"") -> 45530.264 | E53: =IFERROR(VLOOKUP(A53,G:I,3,FALSE),"Onsite") -> Onsite | I53: =IF(G893<>"",IF(I53<>"",I53,NOW()),"") | J53: =SUBSTITUTE(A53,"NC","") -> nc90118868 | L53: Rupasinghe, Sarath | M53: Lim, Taine | N53: =_xlfn.IFNA(VLOOKUP(A53,'Personnel List'!A$1:F$1284,6,FALSE),"") -> Jones, Cameron
A54: nc3413 | B54: =_xlfn.IFNA(VLOOKUP(A54,'Personnel List'!A$1:E$1284,5,FALSE),"") -> Darren Lord | D54: =IF(A54<>"",IF(D54<>"",D54,NOW()),"") -> 45530.264 | E54: =IFERROR(VLOOKUP(A54,G:I,3,FALSE),"Onsite") -> Onsite | I54: =IF(G894<>"",IF(I54<>"",I54,NOW()),"") | J54: =SUBSTITUTE(A54,"NC","") -> nc3413 | L54: Sarpong, Kofi | M54: Lord, Darren | N54: =_xlfn.IFNA(VLOOKUP(A54,'Personnel List'!A$1:F$1284,6,FALSE),"") -> Lord, Darren
A55: nc90009894 | B55: =_xlfn.IFNA(VLOOKUP(A55,'Personnel List'!A$1:E$1284,5,FALSE),"") -> Casey Pompey | C55: =_xlfn.IFNA(VLOOKUP(A55,'Personnel List'!A$1:E$1284,4,FALSE),"") -> SMS Group Services | D55: =IF(A55<>"",IF(D55<>"",D55,NOW()),"") -> 45530.264 | E55: =IFERROR(VLOOKUP(A55,G:I,3,FALSE),"Onsite") -> Onsite | I55: =IF(G895<>"",IF(I55<>"",I55,NOW()),"") | J55: =SUBSTITUTE(A55,"NC","") -> nc90009894 | L55: Strong, Deke | M55: Lord, Davin | N55: =_xlfn.IFNA(VLOOKUP(A55,'Personnel List'!A$1:F$1284,6,FALSE),"") -> Pompey, Casey
A56: nc90128939 | B56: =_xlfn.IFNA(VLOOKUP(A56,'Personnel List'!A$1:E$1284,5,FALSE),"") -> Rolando Ola | C56: =_xlfn.IFNA(VLOOKUP(A56,'Personnel List'!A$1:E$1284,4,FALSE),"") -> APMS | D56: =IF(A56<>"",IF(D56<>"",D56,NOW()),"") -> 45530.264 | E56: =IFERROR(VLOOKUP(A56,G:I,3,FALSE),"Onsite") -> Onsite | I56: =IF(G896<>"",IF(I56<>"",I56,NOW()),"") | J56: =SUBSTITUTE(A56,"NC","") -> nc90128939 | L56: Sujono, Ilya | M56: Maclean, Bronson | N56: =_xlfn.IFNA(VLOOKUP(A56,'Personnel List'!A$1:F$1284,6,FALSE),"") -> Ola, Rolando
A57: nc90135876 | B57: =_xlfn.IFNA(VLOOKUP(A57,'Personnel List'!A$1:E$1284,5,FALSE),"") -> Julie Tran | C57: =_xlfn.IFNA(VLOOKUP(A57,'Personnel List'!A$1:E$1284,4,FALSE),"") -> APMS | D57: =IF(A57<>"",IF(D57<>"",D57,NOW()),"") -> 45530.264 | E57: =IFERROR(VLOOKUP(A57,G:I,3,FALSE),"Onsite") -> Onsite | I57: =IF(G897<>"",IF(I57<>"",I57,NOW()),"") | J57: =SUBSTITUTE(A57,"NC","") -> nc90135876 | L57: Taniwha, Violet | M57: Madronero, Angelo | N57: =_xlfn.IFNA(VLOOKUP(A57,'Personnel List'!A$1:F$1284,6,FALSE),"") -> Tran, Julie
A58: nc90131405 | B58: =_xlfn.IFNA(VLOOKUP(A58,'Personnel List'!A$1:E$1284,5,FALSE),"") -> Renato Navales | C58: =_xlfn.IFNA(VLOOKUP(A58,'Personnel List'!A$1:E$1284,4,FALSE),"") -> APMS | D58: =IF(A58<>"",IF(D58<>"",D58,NOW()),"") -> 45530.264 | E58: =IFERROR(VLOOKUP(A58,G:I,3,FALSE),"Onsite") -> Onsite | I58: =IF(G898<>"",IF(I58<>"",I58,NOW()),"") | J58: =SUBSTITUTE(A58,"NC","") -> nc90131405 | L58: Taura, Jeremiah | M58: McGougan, Archie | N58: =_xlfn.IFNA(VLOOKUP(A58,'Personnel List'!A$1:F$1284,6,FALSE),"") -> Navales, Renato
A59: nc90135106 | B59: =_xlfn.IFNA(VLOOKUP(A59,'Personnel List'!A$1:E$1284,5,FALSE),"") -> Nihad Bendjebbour | C59: =_xlfn.IFNA(VLOOKUP(A59,'Personnel List'!A$1:E$1284,4,FALSE),"") -> APMS | D59: =IF(A59<>"",IF(D59<>"",D59,NOW()),"") -> 45530.264 | E59: =IFERROR(VLOOKUP(A59,G:I,3,FALSE),"Onsite") -> Onsite | I59: =IF(G899<>"",IF(I59<>"",I59,NOW()),"") | J59: =SUBSTITUTE(A59,"NC","") -> nc90135106 | L59: Terranova, Tracy | M59: McGregor, Shannon | N59: =_xlfn.IFNA(VLOOKUP(A59,'Personnel List'!A$1:F$1284,6,FALSE),"") -> Bendjebbour, Nihad
A60: nc90113610 | B60: =_xlfn.IFNA(VLOOKUP(A60,'Personnel List'!A$1:E$1284,5,FALSE),"") -> Anne-Laure Soubies | C60: =_xlfn.IFNA(VLOOKUP(A60,'Personnel List'!A$1:E$1284,4,FALSE),"") -> APMS | D60: =IF(A60<>"",IF(D60<>"",D60,NOW()),"") -> 45530.264 | E60: =IFERROR(VLOOKUP(A60,G:I,3,FALSE),"Onsite") -> Onsite | I60: =IF(G900<>"",IF(I60<>"",I60,NOW()),"") | J60: =SUBSTITUTE(A60,"NC","") -> nc90113610 | L60: Toohey, Colin | M60: McLelland, Scott | N60: =_xlfn.IFNA(VLOOKUP(A60,'Personnel List'!A$1:F$1284,6,FALSE),"") -> Soubies, Anne-Laure
A61: nc90131007 | B61: =_xlfn.IFNA(VLOOKUP(A61,'Personnel List'!A$1:E$1284,5,FALSE),"") -> Chrsitopher Giles | C61: =_xlfn.IFNA(VLOOKUP(A61,'Personnel List'!A$1:E$1284,4,FALSE),"") -> APMS | D61: =IF(A61<>"",IF(D61<>"",D61,NOW()),"") -> 45530.264 | E61: =IFERROR(VLOOKUP(A61,G:I,3,FALSE),"Onsite") -> Onsite | I61: =IF(G901<>"",IF(I61<>"",I61,NOW()),"") | J61: =SUBSTITUTE(A61,"NC","") -> nc90131007 | L61: Van Der Zanden, Christian | M61: McNally, Wade | N61: =_xlfn.IFNA(VLOOKUP(A61,'Personnel List'!A$1:F$1284,6,FALSE),"") -> Giles, Chrsitopher
A62: nc90135104 | B62: =_xlfn.IFNA(VLOOKUP(A62,'Personnel List'!A$1:E$1284,5,FALSE),"") -> Jesus Eclarino | C62: =_xlfn.IFNA(VLOOKUP(A62,'Personnel List'!A$1:E$1284,4,FALSE),"") -> APMS | D62: =IF(A62<>"",IF(D62<>"",D62,NOW()),"") -> 45530.264 | E62: =IFERROR(VLOOKUP(A62,G:I,3,FALSE),"Onsite") -> Onsite | I62: =IF(G902<>"",IF(I62<>"",I62,NOW()),"") | J62: =SUBSTITUTE(A62,"NC","") -> nc90135104 | L62: Wang, Jian | M62: Mdesa, Mohammed | N62: =_xlfn.IFNA(VLOOKUP(A62,'Personnel List'!A$1:F$1284,6,FALSE),"") -> Eclarino, Jesus
A63: nc90118884 | B63: =_xlfn.IFNA(VLOOKUP(A63,'Personnel List'!A$1:E$1284,5,FALSE),"") -> Taleisha Keen | C63: =_xlfn.IFNA(VLOOKUP(A63,'Personnel List'!A$1:E$1284,4,FALSE),"") -> APMS | D63: =IF(A63<>"",IF(D63<>"",D63,NOW()),"") -> 45530.264 | E63: =IFERROR(VLOOKUP(A63,G:I,3,FALSE),"Onsite") -> Onsite | I63: =IF(G903<>"",IF(I63<>"",I63,NOW()),"") | J63: =SUBSTITUTE(A63,"NC","") -> nc90118884 | L63: Weichert, Benjamin | M63: Melgar, Jap | N63: =_xlfn.IFNA(VLOOKUP(A63,'Personnel List'!A$1:F$1284,6,FALSE),"") -> Keen, Taleisha
A64: nc90135063 | B64: =_xlfn.IFNA(VLOOKUP(A64,'Personnel List'!A$1:E$1284,5,FALSE),"") -> Meng Ham | C64: =_xlfn.IFNA(VLOOKUP(A64,'Personnel List'!A$1:E$1284,4,FALSE),"") -> APMS | D64: =IF(A64<>"",IF(D64<>"",D64,NOW()),"") -> 45530.264 | E64: =IFERROR(VLOOKUP(A64,G:I,3,FALSE),"Onsite") -> Onsite | I64: =IF(G904<>"",IF(I64<>"",I64,NOW()),"") | J64: =SUBSTITUTE(A64,"NC","") -> nc90135063 | L64: Witham, Daniel | M64: Moon, Lee | N64: =_xlfn.IFNA(VLOOKUP(A64,'Personnel List'!A$1:F$1284,6,FALSE),"") -> Ham, Meng
A65: nc90119348 | B65: =_xlfn.IFNA(VLOOKUP(A65,'Personnel List'!A$1:E$1284,5,FALSE),"") | C65: =_xlfn.IFNA(VLOOKUP(A65,'Personnel List'!A$1:E$1284,4,FALSE),"") | D65: =IF(A65<>"",IF(D65<>"",D65,NOW()),"") -> 45530.264 | E65: =IFERROR(VLOOKUP(A65,G:I,3,FALSE),"Onsite") -> Onsite | I65: =IF(G905<>"",IF(I65<>"",I65,NOW()),"") | J65: =SUBSTITUTE(A65,"NC","") -> nc90119348 | L65: 0 | M65: Moore, Simon | N65: =_xlfn.IFNA(VLOOKUP(A65,'Personnel List'!A$1:F$1284,6,FALSE),"")
A66: nc90130080 | B66: =_xlfn.IFNA(VLOOKUP(A66,'Personnel List'!A$1:E$1284,5,FALSE),"") -> Edson Alcuizar | C66: =_xlfn.IFNA(VLOOKUP(A66,'Personnel List'!A$1:E$1284,4,FALSE),"") -> APMS | D66: =IF(A66<>"",IF(D66<>"",D66,NOW()),"") -> 45530.264 | E66: =IFERROR(VLOOKUP(A66,G:I,3,FALSE),"Onsite") -> Onsite | I66: =IF(G906<>"",IF(I66<>"",I66,NOW()),"") | J66: =SUBSTITUTE(A66,"NC","") -> nc90130080 | L66: 0 | M66: Morgan, Hauauru | N66: =_xlfn.IFNA(VLOOKUP(A66,'Personnel List'!A$1:F$1284,6,FALSE),"") -> Alcuizar, Edson
A67: nc90074909 | B67: =_xlfn.IFNA(VLOOKUP(A67,'Personnel List'!A$1:E$1284,5,FALSE),"") -> Jap Melgar | C67: =_xlfn.IFNA(VLOOKUP(A67,'Personnel List'!A$1:E$1284,4,FALSE),"") -> APMS | D67: =IF(A67<>"",IF(D67<>"",D67,NOW()),"") -> 45530.264 | E67: =IFERROR(VLOOKUP(A67,G:I,3,FALSE),"Onsite") -> Onsite | I67: =IF(G907<>"",IF(I67<>"",I67,NOW()),"") | J67: =SUBSTITUTE(A67,"NC","") -> nc90074909 | L67: 0 | M67: Mulhall, Martin | N67: =_xlfn.IFNA(VLOOKUP(A67,'Personnel List'!A$1:F$1284,6,FALSE),"") -> Melgar, Jap
A68: nc90113611 | B68: =_xlfn.IFNA(VLOOKUP(A68,'Personnel List'!A$1:E$1284,5,FALSE),"") -> Wilfried Smith | C68: =_xlfn.IFNA(VLOOKUP(A68,'Personnel List'!A$1:E$1284,4,FALSE),"") -> SMS Group Services | D68: =IF(A68<>"",IF(D68<>"",D68,NOW()),"") -> 45530.264 | E68: =IFERROR(VLOOKUP(A68,G:I,3,FALSE),"Onsite") -> Onsite | I68: =IF(G908<>"",IF(I68<>"",I68,NOW()),"") | J68: =SUBSTITUTE(A68,"NC","") -> nc90113611 | L68: 0 | M68: Mulligan, Wesley | N68: =_xlfn.IFNA(VLOOKUP(A68,'Personnel List'!A$1:F$1284,6,FALSE),"") -> Smith, Wilfried
A69: nc4092 | B69: =_xlfn.IFNA(VLOOKUP(A69,'Personnel List'!A$1:E$1284,5,FALSE),"") -> Ben Harmsworth | C69: =_xlfn.IFNA(VLOOKUP(A69,'Personnel List'!A$1:E$1284,4,FALSE),"") -> Newmont | D69: =IF(A69<>"",IF(D69<>"",D69,NOW()),"") -> 45530.264 | E69: =IFERROR(VLOOKUP(A69,G:I,3,FALSE),"Onsite") -> Onsite | I69: =IF(G909<>"",IF(I69<>"",I69,NOW()),"") | J69: =SUBSTITUTE(A69,"NC","") -> nc4092 | L69: 0 | M69: Murphy, Phillip | N69: =_xlfn.IFNA(VLOOKUP(A69,'Personnel List'!A$1:F$1284,6,FALSE),"") -> Harmsworth, Ben
A70: nc90009868 | B70: =_xlfn.IFNA(VLOOKUP(A70,'Personnel List'!A$1:E$1284,5,FALSE),"") -> Reece Murray | C70: =_xlfn.IFNA(VLOOKUP(A70,'Personnel List'!A$1:E$1284,4,FALSE),"") -> APMS | D70: =IF(A70<>"",IF(D70<>"",D70,NOW()),"") -> 45530.264 | E70: =IFERROR(VLOOKUP(A70,G:I,3,FALSE),"Onsite") -> Onsite | I70: =IF(G910<>"",IF(I70<>"",I70,NOW()),"") | J70: =SUBSTITUTE(A70,"NC","") -> nc90009868 | L70: 0 | M70: Murray, Reece | N70: =_xlfn.IFNA(VLOOKUP(A70,'Personnel List'!A$1:F$1284,6,FALSE),"") -> Murray, Reece
A71: nc90065905 | B71: =_xlfn.IFNA(VLOOKUP(A71,'Personnel List'!A$1:E$1284,5,FALSE),"") -> Lee Moon | C71: =_xlfn.IFNA(VLOOKUP(A71,'Personnel List'!A$1:E$1284,4,FALSE),"") -> APMS | D71: =IF(A71<>"",IF(D71<>"",D71,NOW()),"") -> 45530.264 | E71: =IFERROR(VLOOKUP(A71,G:I,3,FALSE),"Onsite") -> Onsite | I71: =IF(G911<>"",IF(I71<>"",I71,NOW()),"") | J71: =SUBSTITUTE(A71,"NC","") -> nc90065905 | L71: 0 | M71: Navales, Renato | N71: =_xlfn.IFNA(VLOOKUP(A71,'Personnel List'!A$1:F$1284,6,FALSE),"") -> Moon, Lee
A72: nc90118876 | B72: =_xlfn.IFNA(VLOOKUP(A72,'Personnel List'!A$1:E$1284,5,FALSE),"") -> Colin Krause | C72: =_xlfn.IFNA(VLOOKUP(A72,'Personnel List'!A$1:E$1284,4,FALSE),"") -> APMS | D72: =IF(A72<>"",IF(D72<>"",D72,NOW()),"") -> 45530.264 | E72: =IFERROR(VLOOKUP(A72,G:I,3,FALSE),"Onsite") -> Onsite | I72: =IF(G912<>"",IF(I72<>"",I72,NOW()),"") | J72: =SUBSTITUTE(A72,"NC","") -> nc90118876 | L72: 0 | M72: Neal, Adam | N72: =_xlfn.IFNA(VLOOKUP(A72,'Personnel List'!A$1:F$1284,6,FALSE),"") -> Krause, Colin
A73: nc90065894 | B73: =_xlfn.IFNA(VLOOKUP(A73,'Personnel List'!A$1:E$1284,5,FALSE),"") -> Geoffrey Harriss | C73: =_xlfn.IFNA(VLOOKUP(A73,'Personnel List'!A$1:E$1284,4,FALSE),"") -> APMS | D73: =IF(A73<>"",IF(D73<>"",D73,NOW()),"") -> 45530.264 | E73: =IFERROR(VLOOKUP(A73,G:I,3,FALSE),"Onsite") -> Onsite | I73: =IF(G913<>"",IF(I73<>"",I73,NOW()),"") | J73: =SUBSTITUTE(A73,"NC","") -> nc90065894 | L73: 0 | M73: Ness, Bradley | N73: =_xlfn.IFNA(VLOOKUP(A73,'Personnel List'!A$1:F$1284,6,FALSE),"") -> Harriss, Geoffrey
A74: nc90135062 | B74: =_xlfn.IFNA(VLOOKUP(A74,'Personnel List'!A$1:E$1284,5,FALSE),"") -> Anthony Altamura | C74: =_xlfn.IFNA(VLOOKUP(A74,'Personnel List'!A$1:E$1284,4,FALSE),"") -> APMS | D74: =IF(A74<>"",IF(D74<>"",D74,NOW()),"") -> 45530.264 | E74: =IFERROR(VLOOKUP(A74,G:I,3,FALSE),"Onsite") -> Onsite | I74: =IF(G914<>"",IF(I74<>"",I74,NOW()),"") | J74: =SUBSTITUTE(A74,"NC","") -> nc90135062 | L74: 0 | M74: Newman, Bella | N74: =_xlfn.IFNA(VLOOKUP(A74,'Personnel List'!A$1:F$1284,6,FALSE),"") -> Altamura, Anthony
A75: nc90135898 | B75: =_xlfn.IFNA(VLOOKUP(A75,'Personnel List'!A$1:E$1284,5,FALSE),"") -> Peter James Bomford | C75: =_xlfn.IFNA(VLOOKUP(A75,'Personnel List'!A$1:E$1284,4,FALSE),"") -> APMS | D75: =IF(A75<>"",IF(D75<>"",D75,NOW()),"") -> 45530.264 | E75: =IFERROR(VLOOKUP(A75,G:I,3,FALSE),"Onsite") -> Onsite | I75: =IF(G915<>"",IF(I75<>"",I75,NOW()),"") | J75: =SUBSTITUTE(A75,"NC","") -> nc90135898 | L75: 0 | M75: Nopueto, Neil | N75: =_xlfn.IFNA(VLOOKUP(A75,'Personnel List'!A$1:F$1284,6,FALSE),"") -> Bomford, Peter James
A76: nc90136043 | B76: =_xlfn.IFNA(VLOOKUP(A76,'Personnel List'!A$1:E$1284,5,FALSE),"") -> Phillip Murphy | C76: =_xlfn.IFNA(VLOOKUP(A76,'Personnel List'!A$1:E$1284,4,FALSE),"") -> APMS | D76: =IF(A76<>"",IF(D76<>"",D76,NOW()),"") -> 45530.264 | E76: =IFERROR(VLOOKUP(A76,G:I,3,FALSE),"Onsite") -> 45530.704 | I76: =IF(G916<>"",IF(I76<>"",I76,NOW()),"") | J76: =SUBSTITUTE(A76,"NC","") -> nc90136043 | L76: 0 | M76: O'Connell, Reece | N76: =_xlfn.IFNA(VLOOKUP(A76,'Personnel List'!A$1:F$1284,6,FALSE),"") -> Murphy, Phillip
... A86: NC4856 | B86: =_xlfn.IFNA(VLOOKUP(A86,'Personnel List'!A$1:E$1284,5,FALSE),"") -> Mohammed Mdesa | C86: =_xlfn.IFNA(VLOOKUP(A86,'Personnel List'!A$1:E$1284,4,FALSE),"") -> Newmont | D86: =IF(A86<>"",IF(D86<>"",D86,NOW()),"") -> 45530.289 | E86: =IFERROR(VLOOKUP(A86,G:I,3,FALSE),"Onsite") -> Onsite | I86: =IF(G926<>"",IF(I86<>"",I86,NOW()),"") | J86: =SUBSTITUTE(A86,"NC","") -> 4856 | L86: 0 | M86: Rowley, John | N86: =_xlfn.IFNA(VLOOKUP(A86,'Personnel List'!A$1:F$1284,6,FALSE),"") -> Mdesa, Mohammed
B87: =_xlfn.IFNA(VLOOKUP(A87,'Personnel List'!A$1:E$1284,5,FALSE),"") | C87: =_xlfn.IFNA(VLOOKUP(A87,'Personnel List'!A$1:E$1284,4,FALSE),"") | D87: =IF(A87<>"",IF(D87<>"",D87,NOW()),"") | E87: =IFERROR(VLOOKUP(A87,G:I,3,FALSE),"Onsite") -> Onsite | I87: =IF(G927<>"",IF(I87<>"",I87,NOW()),"") | J87: =SUBSTITUTE(A87,"NC","") | L87: 0 | M87: Rupasinghe, Sarath | N87: =_xlfn.IFNA(VLOOKUP(A87,'Personnel List'!A$1:F$1284,6,FALSE),"")
B88: =_xlfn.IFNA(VLOOKUP(A88,'Personnel List'!A$1:E$1284,5,FALSE),"") | C88: =_xlfn.IFNA(VLOOKUP(A88,'Personnel List'!A$1:E$1284,4,FALSE),"") | D88: =IF(A88<>"",IF(D88<>"",D88,NOW()),"") | E88: =IFERROR(VLOOKUP(A88,G:I,3,FALSE),"Onsite") -> Onsite | I88: =IF(G928<>"",IF(I88<>"",I88,NOW()),"") | J88: =SUBSTITUTE(A88,"NC","") | L88: 0 | M88: Ryan, Thomas | N88: =_xlfn.IFNA(VLOOKUP(A88,'Personnel List'!A$1:F$1284,6,FALSE),"")
B89: =_xlfn.IFNA(VLOOKUP(A89,'Personnel List'!A$1:E$1284,5,FALSE),"") | C89: =_xlfn.IFNA(VLOOKUP(A89,'Personnel List'!A$1:E$1284,4,FALSE),"") | D89: =IF(A89<>"",IF(D89<>"",D89,NOW()),"") | E89: =IFERROR(VLOOKUP(A89,G:I,3,FALSE),"Onsite") -> Onsite | I89: =IF(G929<>"",IF(I89<>"",I89,NOW()),"") | J89: =SUBSTITUTE(A89,"NC","") | L89: 0 | M89: Sagulenko, Michael | N89: =_xlfn.IFNA(VLOOKUP(A89,'Personnel List'!A$1:F$1284,6,FALSE),"")
B90: =_xlfn.IFNA(VLOOKUP(A90,'Personnel List'!A$1:E$1284,5,FALSE),"") | C90: =_xlfn.IFNA(VLOOKUP(A90,'Personnel List'!A$1:E$1284,4,FALSE),"") | D90: =IF(A90<>"",IF(D90<>"",D90,NOW()),"") | E90: =IFERROR(VLOOKUP(A90,G:I,3,FALSE),"Onsite") -> Onsite | I90: =IF(G930<>"",IF(I90<>"",I90,NOW()),"") | J90: =SUBSTITUTE(A90,"NC","") | L90: 0 | M90: Santhanam, Edward | N90: =_xlfn.IFNA(VLOOKUP(A90,'Personnel List'!A$1:F$1284,6,FALSE),"")
B91: =_xlfn.IFNA(VLOOKUP(A91,'Personnel List'!A$1:E$1284,5,FALSE),"") | C91: =_xlfn.IFNA(VLOOKUP(A91,'Personnel List'!A$1:E$1284,4,FALSE),"") | D91: =IF(A91<>"",IF(D91<>"",D91,NOW()),"") | E91: =IFERROR(VLOOKUP(A91,G:I,3,FALSE),"Onsite") -> Onsite | I91: =IF(G931<>"",IF(I91<>"",I91,NOW()),"") | J91: =SUBSTITUTE(A91,"NC","") | L91: 0 | M91: Sarpong, Kofi | N91: =_xlfn.IFNA(VLOOKUP(A91,'Personnel List'!A$1:F$1284,6,FALSE),"")
B92: =_xlfn.IFNA(VLOOKUP(A92,'Personnel List'!A$1:E$1284,5,FALSE),"") | C92: =_xlfn.IFNA(VLOOKUP(A92,'Personnel List'!A$1:E$1284,4,FALSE),"") | D92: =IF(A92<>"",IF(D92<>"",D92,NOW()),"") | E92: =IFERROR(VLOOKUP(A92,G:I,3,FALSE),"Onsite") -> Onsite | I92: =IF(G932<>"",IF(I92<>"",I92,NOW()),"") | J92: =SUBSTITUTE(A92,"NC","") | L92: 0 | M92: Sheehan, Simon | N92: =_xlfn.IFNA(VLOOKUP(A92,'Personnel List'!A$1:F$1284,6,FALSE),"")
B93: =_xlfn.IFNA(VLOOKUP(A93,'Personnel List'!A$1:E$1284,5,FALSE),"") | C93: =_xlfn.IFNA(VLOOKUP(A93,'Personnel List'!A$1:E$1284,4,FALSE),"") | D93: =IF(A93<>"",IF(D93<>"",D93,NOW()),"") | E93: =IFERROR(VLOOKUP(A93,G:I,3,FALSE),"Onsite") -> Onsite | I93: =IF(G933<>"",IF(I93<>"",I93,NOW()),"") | J93: =SUBSTITUTE(A93,"NC","") | L93: 0 | M93: Simpson, Trevor | N93: =_xlfn.IFNA(VLOOKUP(A93,'Personnel List'!A$1:F$1284,6,FALSE),"")
B94: =_xlfn.IFNA(VLOOKUP(A94,'Personnel List'!A$1:E$1284,5,FALSE),"") | C94: =_xlfn.IFNA(VLOOKUP(A94,'Personnel List'!A$1:E$1284,4,FALSE),"") | D94: =IF(A94<>"",IF(D94<>"",D94,NOW()),"") | E94: =IFERROR(VLOOKUP(A94,G:I,3,FALSE),"Onsite") -> Onsite | I94: =IF(G934<>"",IF(I94<>"",I94,NOW()),"") | J94: =SUBSTITUTE(A94,"NC","") | L94: 0 | M94: Smethurst, Sean | N94: =_xlfn.IFNA(VLOOKUP(A94,'Personnel List'!A$1:F$1284,6,FALSE),"")
B95: =_xlfn.IFNA(VLOOKUP(A95,'Personnel List'!A$1:E$1284,5,FALSE),"") | C95: =_xlfn.IFNA(VLOOKUP(A95,'Personnel List'!A$1:E$1284,4,FALSE),"") | D95: =IF(A95<>"",IF(D95<>"",D95,NOW()),"") | E95: =IFERROR(VLOOKUP(A95,G:I,3,FALSE),"Onsite") -> Onsite | I95: =IF(G935<>"",IF(I95<>"",I95,NOW()),"") | J95: =SUBSTITUTE(A95,"NC","") | L95: 0 | M95: Souey, Conner | N95: =_xlfn.IFNA(VLOOKUP(A95,'Personnel List'!A$1:F$1284,6,FALSE),"")
B96: =_xlfn.IFNA(VLOOKUP(A96,'Personnel List'!A$1:E$1284,5,FALSE),"") | C96: =_xlfn.IFNA(VLOOKUP(A96,'Personnel List'!A$1:E$1284,4,FALSE),"") | D96: =IF(A96<>"",IF(D96<>"",D96,NOW()),"") | E96: =IFERROR(VLOOKUP(A96,G:I,3,FALSE),"Onsite") -> Onsite | I96: =IF(G936<>"",IF(I96<>"",I96,NOW()),"") | J96: =SUBSTITUTE(A96,"NC","") | L96: 0 | M96: Sreekumar, Sreejith | N96: =_xlfn.IFNA(VLOOKUP(A96,'Personnel List'!A$1:F$1284,6,FALSE),"")
B97: =_xlfn.IFNA(VLOOKUP(A97,'Personnel List'!A$1:E$1284,5,FALSE),"") | C97: =_xlfn.IFNA(VLOOKUP(A97,'Personnel List'!A$1:E$1284,4,FALSE),"") | D97: =IF(A97<>"",IF(D97<>"",D97,NOW()),"") | E97: =IFERROR(VLOOKUP(A97,G:I,3,FALSE),"Onsite") -> Onsite | I97: =IF(G937<>"",IF(I97<>"",I97,NOW()),"") | J97: =SUBSTITUTE(A97,"NC","") | L97: 0 | M97: Strong, Deke | N97: =_xlfn.IFNA(VLOOKUP(A97,'Personnel List'!A$1:F$1284,6,FALSE),"")
B98: =_xlfn.IFNA(VLOOKUP(A98,'Personnel List'!A$1:E$1284,5,FALSE),"") | C98: =_xlfn.IFNA(VLOOKUP(A98,'Personnel List'!A$1:E$1284,4,FALSE),"") | D98: =IF(A98<>"",IF(D98<>"",D98,NOW()),"") | E98: =IFERROR(VLOOKUP(A98,G:I,3,FALSE),"Onsite") -> Onsite | I98: =IF(G938<>"",IF(I98<>"",I98,NOW()),"") | J98: =SUBSTITUTE(A98,"NC","") | L98: 0 | M98: Sujono, Ilya | N98: =_xlfn.IFNA(VLOOKUP(A98,'Personnel List'!A$1:F$1284,6,FALSE),"")
... B112: =_xlfn.IFNA(VLOOKUP(A112,'Personnel List'!A$1:E$1284,5,FALSE),"") | C112: =_xlfn.IFNA(VLOOKUP(A112,'Personnel List'!A$1:E$1284,4,FALSE),"") | D112: =IF(A112<>"",IF(D112<>"",D112,NOW()),"") | E112: =IFERROR(VLOOKUP(A112,G:I,3,FALSE),"Onsite") -> Onsite | I112: =IF(G952<>"",IF(I112<>"",I112,NOW()),"") | J112: =SUBSTITUTE(A112,"NC","") | L112: 0 | M112: Zhang, Tom | N112: =_xlfn.IFNA(VLOOKUP(A112,'Personnel List'!A$1:F$1284,6,FALSE),"")
B113: =_xlfn.IFNA(VLOOKUP(A113,'Personnel List'!A$1:E$1284,5,FALSE),"") | C113: =_xlfn.IFNA(VLOOKUP(A113,'Personnel List'!A$1:E$1284,4,FALSE),"") | D113: =IF(A113<>"",IF(D113<>"",D113,NOW()),"") | E113: =IFERROR(VLOOKUP(A113,G:I,3,FALSE),"Onsite") -> Onsite | I113: =IF(G953<>"",IF(I113<>"",I113,NOW()),"") | J113: =SUBSTITUTE(A113,"NC","") | L113: 0 | N113: =_xlfn.IFNA(VLOOKUP(A113,'Personnel List'!A$1:F$1284,6,FALSE),"")
B114: =_xlfn.IFNA(VLOOKUP(A114,'Personnel List'!A$1:E$1284,5,FALSE),"") | C114: =_xlfn.IFNA(VLOOKUP(A114,'Personnel List'!A$1:E$1284,4,FALSE),"") | D114: =IF(A114<>"",IF(D114<>"",D114,NOW()),"") | E114: =IFERROR(VLOOKUP(A114,G:I,3,FALSE),"Onsite") -> Onsite | I114: =IF(G954<>"",IF(I114<>"",I114,NOW()),"") | J114: =SUBSTITUTE(A114,"NC","") | L114: 0 | N114: =_xlfn.IFNA(VLOOKUP(A114,'Personnel List'!A$1:F$1284,6,FALSE),"")
B115: =_xlfn.IFNA(VLOOKUP(A115,'Personnel List'!A$1:E$1284,5,FALSE),"") | C115: =_xlfn.IFNA(VLOOKUP(A115,'Personnel List'!A$1:E$1284,4,FALSE),"") | D115: =IF(A115<>"",IF(D115<>"",D115,NOW()),"") | E115: =IFERROR(VLOOKUP(A115,G:I,3,FALSE),"Onsite") -> Onsite | I115: =IF(G955<>"",IF(I115<>"",I115,NOW()),"") | J115: =SUBSTITUTE(A115,"NC","") | L115: 0 | N115: =_xlfn.IFNA(VLOOKUP(A115,'Personnel List'!A$1:F$1284,6,FALSE),"")
B116: =_xlfn.IFNA(VLOOKUP(A116,'Personnel List'!A$1:E$1284,5,FALSE),"") | C116: =_xlfn.IFNA(VLOOKUP(A116,'Personnel List'!A$1:E$1284,4,FALSE),"") | D116: =IF(A116<>"",IF(D116<>"",D116,NOW()),"") | E116: =IFERROR(VLOOKUP(A116,G:I,3,FALSE),"Onsite") -> Onsite | I116: =IF(G956<>"",IF(I116<>"",I116,NOW()),"") | J116: =SUBSTITUTE(A116,"NC","") | L116: 0 | N116: =_xlfn.IFNA(VLOOKUP(A116,'Personnel List'!A$1:F$1284,6,FALSE),"")
B117: =_xlfn.IFNA(VLOOKUP(A117,'Personnel List'!A$1:E$1284,5,FALSE),"") | C117: =_xlfn.IFNA(VLOOKUP(A117,'Personnel List'!A$1:E$1284,4,FALSE),"") | D117: =IF(A117<>"",IF(D117<>"",D117,NOW()),"") | E117: =IFERROR(VLOOKUP(A117,G:I,3,FALSE),"Onsite") -> Onsite | I117: =IF(G957<>"",IF(I117<>"",I117,NOW()),"") | J117: =SUBSTITUTE(A117,"NC","") | L117: 0 | N117: =_xlfn.IFNA(VLOOKUP(A117,'Personnel List'!A$1:F$1284,6,FALSE),"")
B118: =_xlfn.IFNA(VLOOKUP(A118,'Personnel List'!A$1:E$1284,5,FALSE),"") | C118: =_xlfn.IFNA(VLOOKUP(A118,'Personnel List'!A$1:E$1284,4,FALSE),"") | D118: =IF(A118<>"",IF(D118<>"",D118,NOW()),"") | E118: =IFERROR(VLOOKUP(A118,G:I,3,FALSE),"Onsite") -> Onsite | I118: =IF(G958<>"",IF(I118<>"",I118,NOW()),"") | J118: =SUBSTITUTE(A118,"NC","") | L118: 0 | N118: =_xlfn.IFNA(VLOOKUP(A118,'Personnel List'!A$1:F$1284,6,FALSE),"")
B119: =_xlfn.IFNA(VLOOKUP(A119,'Personnel List'!A$1:E$1284,5,FALSE),"") | C119: =_xlfn.IFNA(VLOOKUP(A119,'Personnel List'!A$1:E$1284,4,FALSE),"") | D119: =IF(A119<>"",IF(D119<>"",D119,NOW()),"") | E119: =IFERROR(VLOOKUP(A119,G:I,3,FALSE),"Onsite") -> Onsite | I119: =IF(G959<>"",IF(I119<>"",I119,NOW()),"") | J119: =SUBSTITUTE(A119,"NC","") | L119: 0 | N119: =_xlfn.IFNA(VLOOKUP(A119,'Personnel List'!A$1:F$1284,6,FALSE),"")
B120: =_xlfn.IFNA(VLOOKUP(A120,'Personnel List'!A$1:E$1284,5,FALSE),"") | C120: =_xlfn.IFNA(VLOOKUP(A120,'Personnel List'!A$1:E$1284,4,FALSE),"") | D120: =IF(A120<>"",IF(D120<>"",D120,NOW()),"") | E120: =IFERROR(VLOOKUP(A120,G:I,3,FALSE),"Onsite") -> Onsite | I120: =IF(G960<>"",IF(I120<>"",I120,NOW()),"") | J120: =SUBSTITUTE(A120,"NC","") | L120: 0 | N120: =_xlfn.IFNA(VLOOKUP(A120,'Personnel List'!A$1:F$1284,6,FALSE),"")
B121: =_xlfn.IFNA(VLOOKUP(A121,'Personnel List'!A$1:E$1284,5,FALSE),"") | C121: =_xlfn.IFNA(VLOOKUP(A121,'Personnel List'!A$1:E$1284,4,FALSE),"") | D121: =IF(A121<>"",IF(D121<>"",D121,NOW()),"") | E121: =IFERROR(VLOOKUP(A121,G:I,3,FALSE),"Onsite") -> Onsite | I121: =IF(G961<>"",IF(I121<>"",I121,NOW()),"") | J121: =SUBSTITUTE(A121,"NC","") | L121: 0 | N121: =_xlfn.IFNA(VLOOKUP(A121,'Personnel List'!A$1:F$1284,6,FALSE),"")
B122: =_xlfn.IFNA(VLOOKUP(A122,'Personnel List'!A$1:E$1284,5,FALSE),"") | C122: =_xlfn.IFNA(VLOOKUP(A122,'Personnel List'!A$1:E$1284,4,FALSE),"") | D122: =IF(A122<>"",IF(D122<>"",D122,NOW()),"") | E122: =IFERROR(VLOOKUP(A122,G:I,3,FALSE),"Onsite") -> Onsite | I122: =IF(G962<>"",IF(I122<>"",I122,NOW()),"") | J122: =SUBSTITUTE(A122,"NC","") | L122: 0 | N122: =_xlfn.IFNA(VLOOKUP(A122,'Personnel List'!A$1:F$1284,6,FALSE),"")
B123: =_xlfn.IFNA(VLOOKUP(A123,'Personnel List'!A$1:E$1284,5,FALSE),"") | C123: =_xlfn.IFNA(VLOOKUP(A123,'Personnel List'!A$1:E$1284,4,FALSE),"") | D123: =IF(A123<>"",IF(D123<>"",D123,NOW()),"") | E123: =IFERROR(VLOOKUP(A123,G:I,3,FALSE),"Onsite") -> Onsite | I123: =IF(G963<>"",IF(I123<>"",I123,NOW()),"") | J123: =SUBSTITUTE(A123,"NC","") | L123: 0 | N123: =_xlfn.IFNA(VLOOKUP(A123,'Personnel List'!A$1:F$1284,6,FALSE),"")
...

Sheet Mon NS
A1: Scan ID | B1: Name | C1: Company Name | D1: Time In | E1: Time Out | G1: Scan Out | I1: Timestamp | J1: SAP Number | L1: Not Scanned Yet | M1: NS | N1: Reverse Name
B2: =_xlfn.IFNA(VLOOKUP(A2,'Personnel List'!A$1:E$1284,5,FALSE),"") | C2: =_xlfn.IFNA(VLOOKUP(A2,'Personnel List'!A$1:E$1284,4,FALSE),"") | D2: =IF(A2<>"",IF(D2<>"",D2,NOW()),"") | E2: =IFERROR(VLOOKUP(A2,G:I,3,FALSE),"Onsite") -> Onsite | I2: =IF(G2<>"",IF(I2<>"",I2,NOW()),"") | J2: =SUBSTITUTE(A2,"NC","") | L2: {=_xlfn._xlws.FILTER(M2:M1000,(ISNA(MATCH(M2:M1000,N2:N1000,0))),"")} -> Allsopp, Andrew | M2: {=_xlfn._xlws.FILTER('Mon Data'!E13:E361,ISNUMBER(_xlfn.XMATCH('Mon Data'!D13:D361,M1)))} -> Allsopp, Andrew | N2: =_xlfn.IFNA(VLOOKUP(A2,'Personnel List'!A$1:F$1284,6,FALSE),"")
B3: =_xlfn.IFNA(VLOOKUP(A3,'Personnel List'!A$1:E$1284,5,FALSE),"") | C3: =_xlfn.IFNA(VLOOKUP(A3,'Personnel List'!A$1:E$1284,4,FALSE),"") | D3: =IF(A3<>"",IF(D3<>"",D3,NOW()),"") | E3: =IFERROR(VLOOKUP(A3,G:I,3,FALSE),"Onsite") -> Onsite | I3: =IF(G3<>"",IF(I3<>"",I3,NOW()),"") | J3: =SUBSTITUTE(A3,"NC","") | L3: Anderton, Paul | M3: Anderton, Paul | N3: =_xlfn.IFNA(VLOOKUP(A3,'Personnel List'!A$1:F$1284,6,FALSE),"")
B4: =_xlfn.IFNA(VLOOKUP(A4,'Personnel List'!A$1:E$1284,5,FALSE),"") | C4: =_xlfn.IFNA(VLOOKUP(A4,'Personnel List'!A$1:E$1284,4,FALSE),"") | D4: =IF(A4<>"",IF(D4<>"",D4,NOW()),"") | E4: =IFERROR(VLOOKUP(A4,G:I,3,FALSE),"Onsite") -> Onsite | I4: =IF(G4<>"",IF(I4<>"",I4,NOW()),"") | J4: =SUBSTITUTE(A4,"NC","") | L4: Aranda, Mark | M4: Aranda, Mark | N4: =_xlfn.IFNA(VLOOKUP(A4,'Personnel List'!A$1:F$1284,6,FALSE),"")
B5: =_xlfn.IFNA(VLOOKUP(A5,'Personnel List'!A$1:E$1284,5,FALSE),"") | C5: =_xlfn.IFNA(VLOOKUP(A5,'Personnel List'!A$1:E$1284,4,FALSE),"") | D5: =IF(A5<>"",IF(D5<>"",D5,NOW()),"") | E5: =IFERROR(VLOOKUP(A5,G:I,3,FALSE),"Onsite") -> Onsite | I5: =IF(G5<>"",IF(I5<>"",I5,NOW()),"") | J5: =SUBSTITUTE(A5,"NC","") | L5: Batinga, Renald | M5: Batinga, Renald | N5: =_xlfn.IFNA(VLOOKUP(A5,'Personnel List'!A$1:F$1284,6,FALSE),"")
B6: =_xlfn.IFNA(VLOOKUP(A6,'Personnel List'!A$1:E$1284,5,FALSE),"") | C6: =_xlfn.IFNA(VLOOKUP(A6,'Personnel List'!A$1:E$1284,4,FALSE),"") | D6: =IF(A6<>"",IF(D6<>"",D6,NOW()),"") | E6: =IFERROR(VLOOKUP(A6,G:I,3,FALSE),"Onsite") -> Onsite | I6: =IF(G6<>"",IF(I6<>"",I6,NOW()),"") | J6: =SUBSTITUTE(A6,"NC","") | L6: Beauchamp, Peter | M6: Beauchamp, Peter | N6: =_xlfn.IFNA(VLOOKUP(A6,'Personnel List'!A$1:F$1284,6,FALSE),"")
B7: =_xlfn.IFNA(VLOOKUP(A7,'Personnel List'!A$1:E$1284,5,FALSE),"") | C7: =_xlfn.IFNA(VLOOKUP(A7,'Personnel List'!A$1:E$1284,4,FALSE),"") | D7: =IF(A7<>"",IF(D7<>"",D7,NOW()),"") | E7: =IFERROR(VLOOKUP(A7,G:I,3,FALSE),"Onsite") -> Onsite | I7: =IF(G7<>"",IF(I7<>"",I7,NOW()),"") | J7: =SUBSTITUTE(A7,"NC","") | L7: Blair, Ruth | M7: Blair, Ruth | N7: =_xlfn.IFNA(VLOOKUP(A7,'Personnel List'!A$1:F$1284,6,FALSE),"")
B8: =_xlfn.IFNA(VLOOKUP(A8,'Personnel List'!A$1:E$1284,5,FALSE),"") | C8: =_xlfn.IFNA(VLOOKUP(A8,'Personnel List'!A$1:E$1284,4,FALSE),"") | D8: =IF(A8<>"",IF(D8<>"",D8,NOW()),"") | E8: =IFERROR(VLOOKUP(A8,G:I,3,FALSE),"Onsite") -> Onsite | I8: =IF(G8<>"",IF(I8<>"",I8,NOW()),"") | J8: =SUBSTITUTE(A8,"NC","") | L8: Bunag, Roy | M8: Bunag, Roy | N8: =_xlfn.IFNA(VLOOKUP(A8,'Personnel List'!A$1:F$1284,6,FALSE),"")
B9: =_xlfn.IFNA(VLOOKUP(A9,'Personnel List'!A$1:E$1284,5,FALSE),"") | C9: =_xlfn.IFNA(VLOOKUP(A9,'Personnel List'!A$1:E$1284,4,FALSE),"") | D9: =IF(A9<>"",IF(D9<>"",D9,NOW()),"") | E9: =IFERROR(VLOOKUP(A9,G:I,3,FALSE),"Onsite") -> Onsite | I9: =IF(G9<>"",IF(I9<>"",I9,NOW()),"") | J9: =SUBSTITUTE(A9,"NC","") | L9: Cavanagh, Bruce | M9: Cavanagh, Bruce | N9: =_xlfn.IFNA(VLOOKUP(A9,'Personnel List'!A$1:F$1284,6,FALSE),"")
B10: =_xlfn.IFNA(VLOOKUP(A10,'Personnel List'!A$1:E$1284,5,FALSE),"") | C10: =_xlfn.IFNA(VLOOKUP(A10,'Personnel List'!A$1:E$1284,4,FALSE),"") | D10: =IF(A10<>"",IF(D10<>"",D10,NOW()),"") | E10: =IFERROR(VLOOKUP(A10,G:I,3,FALSE),"Onsite") -> Onsite | I10: =IF(G10<>"",IF(I10<>"",I10,NOW()),"") | J10: =SUBSTITUTE(A10,"NC","") | L10: Cowley, Jason Anthony | M10: Cowley, Jason Anthony | N10: =_xlfn.IFNA(VLOOKUP(A10,'Personnel List'!A$1:F$1284,6,FALSE),"")
B11: =_xlfn.IFNA(VLOOKUP(A11,'Personnel List'!A$1:E$1284,5,FALSE),"") | C11: =_xlfn.IFNA(VLOOKUP(A11,'Personnel List'!A$1:E$1284,4,FALSE),"") | D11: =IF(A11<>"",IF(D11<>"",D11,NOW()),"") | E11: =IFERROR(VLOOKUP(A11,G:I,3,FALSE),"Onsite") -> Onsite | I11: =IF(G11<>"",IF(I11<>"",I11,NOW()),"") | J11: =SUBSTITUTE(A11,"NC","") | L11: Kulkewycz, David | M11: Kulkewycz, David | N11: =_xlfn.IFNA(VLOOKUP(A11,'Personnel List'!A$1:F$1284,6,FALSE),"")
B12: =_xlfn.IFNA(VLOOKUP(A12,'Personnel List'!A$1:E$1284,5,FALSE),"") | C12: =_xlfn.IFNA(VLOOKUP(A12,'Personnel List'!A$1:E$1284,4,FALSE),"") | D12: =IF(A12<>"",IF(D12<>"",D12,NOW()),"") | E12: =IFERROR(VLOOKUP(A12,G:I,3,FALSE),"Onsite") -> Onsite | I12: =IF(G12<>"",IF(I12<>"",I12,NOW()),"") | J12: =SUBSTITUTE(A12,"NC","") | L12: Martin, Jesse | M12: Martin, Jesse | N12: =_xlfn.IFNA(VLOOKUP(A12,'Personnel List'!A$1:F$1284,6,FALSE),"")
B13: =_xlfn.IFNA(VLOOKUP(A13,'Personnel List'!A$1:E$1284,5,FALSE),"") | C13: =_xlfn.IFNA(VLOOKUP(A13,'Personnel List'!A$1:E$1284,4,FALSE),"") | D13: =IF(A13<>"",IF(D13<>"",D13,NOW()),"") | E13: =IFERROR(VLOOKUP(A13,G:I,3,FALSE),"Onsite") -> Onsite | I13: =IF(G13<>"",IF(I13<>"",I13,NOW()),"") | J13: =SUBSTITUTE(A13,"NC","") | L13: Mason, Trent | M13: Mason, Trent | N13: =_xlfn.IFNA(VLOOKUP(A13,'Personnel List'!A$1:F$1284,6,FALSE),"")
B14: =_xlfn.IFNA(VLOOKUP(A14,'Personnel List'!A$1:E$1284,5,FALSE),"") | C14: =_xlfn.IFNA(VLOOKUP(A14,'Personnel List'!A$1:E$1284,4,FALSE),"") | D14: =IF(A14<>"",IF(D14<>"",D14,NOW()),"") | E14: =IFERROR(VLOOKUP(A14,G:I,3,FALSE),"Onsite") -> Onsite | I14: =IF(G14<>"",IF(I14<>"",I14,NOW()),"") | J14: =SUBSTITUTE(A14,"NC","") | L14: McLelland, Ralph | M14: McLelland, Ralph | N14: =_xlfn.IFNA(VLOOKUP(A14,'Personnel List'!A$1:F$1284,6,FALSE),"")
... B23: =_xlfn.IFNA(VLOOKUP(A23,'Personnel List'!A$1:E$1284,5,FALSE),"") | C23: =_xlfn.IFNA(VLOOKUP(A23,'Personnel List'!A$1:E$1284,4,FALSE),"") | D23: =IF(A23<>"",IF(D23<>"",D23,NOW()),"") | E23: =IFERROR(VLOOKUP(A23,G:I,3,FALSE),"Onsite") -> Onsite | I23: =IF(G23<>"",IF(I23<>"",I23,NOW()),"") | J23: =SUBSTITUTE(A23,"NC","") | L23: Wigley, Robert | M23: Wigley, Robert | N23: =_xlfn.IFNA(VLOOKUP(A23,'Personnel List'!A$1:F$1284,6,FALSE),"")
B24: =_xlfn.IFNA(VLOOKUP(A24,'Personnel List'!A$1:E$1284,5,FALSE),"") | C24: =_xlfn.IFNA(VLOOKUP(A24,'Personnel List'!A$1:E$1284,4,FALSE),"") | D24: =IF(A24<>"",IF(D24<>"",D24,NOW()),"") | E24: =IFERROR(VLOOKUP(A24,G:I,3,FALSE),"Onsite") -> Onsite | I24: =IF(G24<>"",IF(I24<>"",I24,NOW()),"") | J24: =SUBSTITUTE(A24,"NC","") | L24: 0 | N24: =_xlfn.IFNA(VLOOKUP(A24,'Personnel List'!A$1:F$1284,6,FALSE),"")
B25: =_xlfn.IFNA(VLOOKUP(A25,'Personnel List'!A$1:E$1284,5,FALSE),"") | C25: =_xlfn.IFNA(VLOOKUP(A25,'Personnel List'!A$1:E$1284,4,FALSE),"") | D25: =IF(A25<>"",IF(D25<>"",D25,NOW()),"") | E25: =IFERROR(VLOOKUP(A25,G:I,3,FALSE),"Onsite") -> Onsite | I25: =IF(G25<>"",IF(I25<>"",I25,NOW()),"") | J25: =SUBSTITUTE(A25,"NC","") | L25: 0 | N25: =_xlfn.IFNA(VLOOKUP(A25,'Personnel List'!A$1:F$1284,6,FALSE),"")
B26: =_xlfn.IFNA(VLOOKUP(A26,'Personnel List'!A$1:E$1284,5,FALSE),"") | C26: =_xlfn.IFNA(VLOOKUP(A26,'Personnel List'!A$1:E$1284,4,FALSE),"") | D26: =IF(A26<>"",IF(D26<>"",D26,NOW()),"") | E26: =IFERROR(VLOOKUP(A26,G:I,3,FALSE),"Onsite") -> Onsite | I26: =IF(G26<>"",IF(I26<>"",I26,NOW()),"") | J26: =SUBSTITUTE(A26,"NC","") | L26: 0 | N26: =_xlfn.IFNA(VLOOKUP(A26,'Personnel List'!A$1:F$1284,6,FALSE),"")
B27: =_xlfn.IFNA(VLOOKUP(A27,'Personnel List'!A$1:E$1284,5,FALSE),"") | C27: =_xlfn.IFNA(VLOOKUP(A27,'Personnel List'!A$1:E$1284,4,FALSE),"") | D27: =IF(A27<>"",IF(D27<>"",D27,NOW()),"") | E27: =IFERROR(VLOOKUP(A27,G:I,3,FALSE),"Onsite") -> Onsite | I27: =IF(G27<>"",IF(I27<>"",I27,NOW()),"") | J27: =SUBSTITUTE(A27,"NC","") | L27: 0 | N27: =_xlfn.IFNA(VLOOKUP(A27,'Personnel List'!A$1:F$1284,6,FALSE),"")
B28: =_xlfn.IFNA(VLOOKUP(A28,'Personnel List'!A$1:E$1284,5,FALSE),"") | C28: =_xlfn.IFNA(VLOOKUP(A28,'Personnel List'!A$1:E$1284,4,FALSE),"") | D28: =IF(A28<>"",IF(D28<>"",D28,NOW()),"") | E28: =IFERROR(VLOOKUP(A28,G:I,3,FALSE),"Onsite") -> Onsite | I28: =IF(G28<>"",IF(I28<>"",I28,NOW()),"") | J28: =SUBSTITUTE(A28,"NC","") | L28: 0 | N28: =_xlfn.IFNA(VLOOKUP(A28,'Personnel List'!A$1:F$1284,6,FALSE),"")
B29: =_xlfn.IFNA(VLOOKUP(A29,'Personnel List'!A$1:E$1284,5,FALSE),"") | C29: =_xlfn.IFNA(VLOOKUP(A29,'Personnel List'!A$1:E$1284,4,FALSE),"") | D29: =IF(A29<>"",IF(D29<>"",D29,NOW()),"") | E29: =IFERROR(VLOOKUP(A29,G:I,3,FALSE),"Onsite") -> Onsite | I29: =IF(G29<>"",IF(I29<>"",I29,NOW()),"") | J29: =SUBSTITUTE(A29,"NC","") | L29: 0 | N29: =_xlfn.IFNA(VLOOKUP(A29,'Personnel List'!A$1:F$1284,6,FALSE),"")
B30: =_xlfn.IFNA(VLOOKUP(A30,'Personnel List'!A$1:E$1284,5,FALSE),"") | C30: =_xlfn.IFNA(VLOOKUP(A30,'Personnel List'!A$1:E$1284,4,FALSE),"") | D30: =IF(A30<>"",IF(D30<>"",D30,NOW()),"") | E30: =IFERROR(VLOOKUP(A30,G:I,3,FALSE),"Onsite") -> Onsite | I30: =IF(G30<>"",IF(I30<>"",I30,NOW()),"") | J30: =SUBSTITUTE(A30,"NC","") | L30: 0 | N30: =_xlfn.IFNA(VLOOKUP(A30,'Personnel List'!A$1:F$1284,6,FALSE),"")
B31: =_xlfn.IFNA(VLOOKUP(A31,'Personnel List'!A$1:E$1284,5,FALSE),"") | C31: =_xlfn.IFNA(VLOOKUP(A31,'Personnel List'!A$1:E$1284,4,FALSE),"") | D31: =IF(A31<>"",IF(D31<>"",D31,NOW()),"") | E31: =IFERROR(VLOOKUP(A31,G:I,3,FALSE),"Onsite") -> Onsite | I31: =IF(G31<>"",IF(I31<>"",I31,NOW()),"") | J31: =SUBSTITUTE(A31,"NC","") | L31: 0 | N31: =_xlfn.IFNA(VLOOKUP(A31,'Personnel List'!A$1:F$1284,6,FALSE),"")
B32: =_xlfn.IFNA(VLOOKUP(A32,'Personnel List'!A$1:E$1284,5,FALSE),"") | C32: =_xlfn.IFNA(VLOOKUP(A32,'Personnel List'!A$1:E$1284,4,FALSE),"") | D32: =IF(A32<>"",IF(D32<>"",D32,NOW()),"") | E32: =IFERROR(VLOOKUP(A32,G:I,3,FALSE),"Onsite") -> Onsite | I32: =IF(G32<>"",IF(I32<>"",I32,NOW()),"") | J32: =SUBSTITUTE(A32,"NC","") | L32: 0 | N32: =_xlfn.IFNA(VLOOKUP(A32,'Personnel List'!A$1:F$1284,6,FALSE),"")
B33: =_xlfn.IFNA(VLOOKUP(A33,'Personnel List'!A$1:E$1284,5,FALSE),"") | E33: =IFERROR(VLOOKUP(A33,G:I,3,FALSE),"Onsite") -> Onsite | I33: =IF(G33<>"",IF(I33<>"",I33,NOW()),"") | J33: =SUBSTITUTE(A33,"NC","") | L33: 0 | N33: =_xlfn.IFNA(VLOOKUP(A33,'Personnel List'!A$1:F$1284,6,FALSE),"")
B34: =_xlfn.IFNA(VLOOKUP(A34,'Personnel List'!A$1:E$1284,5,FALSE),"") | C34: =_xlfn.IFNA(VLOOKUP(A34,'Personnel List'!A$1:E$1284,4,FALSE),"") | D34: =IF(A34<>"",IF(D34<>"",D34,NOW()),"") | E34: =IFERROR(VLOOKUP(A34,G:I,3,FALSE),"Onsite") -> Onsite | I34: =IF(G34<>"",IF(I34<>"",I34,NOW()),"") | J34: =SUBSTITUTE(A34,"NC","") | L34: 0 | N34: =_xlfn.IFNA(VLOOKUP(A34,'Personnel List'!A$1:F$1284,6,FALSE),"")
B35: =_xlfn.IFNA(VLOOKUP(A35,'Personnel List'!A$1:E$1284,5,FALSE),"") | C35: =_xlfn.IFNA(VLOOKUP(A35,'Personnel List'!A$1:E$1284,4,FALSE),"") | D35: =IF(A35<>"",IF(D35<>"",D35,NOW()),"") | E35: =IFERROR(VLOOKUP(A35,G:I,3,FALSE),"Onsite") -> Onsite | I35: =IF(G35<>"",IF(I35<>"",I35,NOW()),"") | J35: =SUBSTITUTE(A35,"NC","") | L35: 0 | N35: =_xlfn.IFNA(VLOOKUP(A35,'Personnel List'!A$1:F$1284,6,FALSE),"")
B36: =_xlfn.IFNA(VLOOKUP(A36,'Personnel List'!A$1:E$1284,5,FALSE),"") | C36: =_xlfn.IFNA(VLOOKUP(A36,'Personnel List'!A$1:E$1284,4,FALSE),"") | D36: =IF(A36<>"",IF(D36<>"",D36,NOW()),"") | E36: =IFERROR(VLOOKUP(A36,G:I,3,FALSE),"Onsite") -> Onsite | I36: =IF(G36<>"",IF(I36<>"",I36,NOW()),"") | J36: =SUBSTITUTE(A36,"NC","") | L36: 0 | N36: =_xlfn.IFNA(VLOOKUP(A36,'Personnel List'!A$1:F$1284,6,FALSE),"")
B37: =_xlfn.IFNA(VLOOKUP(A37,'Personnel List'!A$1:E$1284,5,FALSE),"") | C37: =_xlfn.IFNA(VLOOKUP(A37,'Personnel List'!A$1:E$1284,4,FALSE),"") | D37: =IF(A37<>"",IF(D37<>"",D37,NOW()),"") | E37: =IFERROR(VLOOKUP(A37,G:I,3,FALSE),"Onsite") -> Onsite | I37: =IF(G37<>"",IF(I37<>"",I37,NOW()),"") | J37: =SUBSTITUTE(A37,"NC","") | L37: 0 | N37: =_xlfn.IFNA(VLOOKUP(A37,'Personnel List'!A$1:F$1284,6,FALSE),"")
B38: =_xlfn.IFNA(VLOOKUP(A38,'Personnel List'!A$1:E$1284,5,FALSE),"") | C38: =_xlfn.IFNA(VLOOKUP(A38,'Personnel List'!A$1:E$1284,4,FALSE),"") | D38: =IF(A38<>"",IF(D38<>"",D38,NOW()),"") | E38: =IFERROR(VLOOKUP(A38,G:I,3,FALSE),"Onsite") -> Onsite | I38: =IF(G38<>"",IF(I38<>"",I38,NOW()),"") | J38: =SUBSTITUTE(A38,"NC","") | L38: 0 | N38: =_xlfn.IFNA(VLOOKUP(A38,'Personnel List'!A$1:F$1284,6,FALSE),"")
B39: =_xlfn.IFNA(VLOOKUP(A39,'Personnel List'!A$1:E$1284,5,FALSE),"") | C39: =_xlfn.IFNA(VLOOKUP(A39,'Personnel List'!A$1:E$1284,4,FALSE),"") | D39: =IF(A39<>"",IF(D39<>"",D39,NOW()),"") | E39: =IFERROR(VLOOKUP(A39,G:I,3,FALSE),"Onsite") -> Onsite | I39: =IF(G39<>"",IF(I39<>"",I39,NOW()),"") | J39: =SUBSTITUTE(A39,"NC","") | L39: 0 | N39: =_xlfn.IFNA(VLOOKUP(A39,'Personnel List'!A$1:F$1284,6,FALSE),"")
B40: =_xlfn.IFNA(VLOOKUP(A40,'Personnel List'!A$1:E$1284,5,FALSE),"") | C40: =_xlfn.IFNA(VLOOKUP(A40,'Personnel List'!A$1:E$1284,4,FALSE),"") | D40: =IF(A40<>"",IF(D40<>"",D40,NOW()),"") | E40: =IFERROR(VLOOKUP(A40,G:I,3,FALSE),"Onsite") -> Onsite | I40: =IF(G40<>"",IF(I40<>"",I40,NOW()),"") | J40: =SUBSTITUTE(A40,"NC","") | L40: 0 | N40: =_xlfn.IFNA(VLOOKUP(A40,'Personnel List'!A$1:F$1284,6,FALSE),"")
D41: =IF(A41<>"",IF(D41<>"",D41,NOW()),"") | E41: =IFERROR(VLOOKUP(A41,G:I,3,FALSE),"Onsite") -> Onsite | I41: =IF(G41<>"",IF(I41<>"",I41,NOW()),"") | J41: =SUBSTITUTE(A41,"NC","") | L41: 0 | N41: =_xlfn.IFNA(VLOOKUP(A41,'Personnel List'!A$1:F$1284,6,FALSE),"")
B42: =_xlfn.IFNA(VLOOKUP(A42,'Personnel List'!A$1:E$1284,5,FALSE),"") | C42: =_xlfn.IFNA(VLOOKUP(A42,'Personnel List'!A$1:E$1284,4,FALSE),"") | D42: =IF(A42<>"",IF(D42<>"",D42,NOW()),"") | E42: =IFERROR(VLOOKUP(A42,G:I,3,FALSE),"Onsite") -> Onsite | I42: =IF(G42<>"",IF(I42<>"",I42,NOW()),"") | J42: =SUBSTITUTE(A42,"NC","") | L42: 0 | N42: =_xlfn.IFNA(VLOOKUP(A42,'Personnel List'!A$1:F$1284,6,FALSE),"")
B43: =_xlfn.IFNA(VLOOKUP(A43,'Personnel List'!A$1:E$1284,5,FALSE),"") | C43: =_xlfn.IFNA(VLOOKUP(A43,'Personnel List'!A$1:E$1284,4,FALSE),"") | D43: =IF(A43<>"",IF(D43<>"",D43,NOW()),"") | E43: =IFERROR(VLOOKUP(A43,G:I,3,FALSE),"Onsite") -> Onsite | I43: =IF(G43<>"",IF(I43<>"",I43,NOW()),"") | J43: =SUBSTITUTE(A43,"NC","") | L43: 0 | N43: =_xlfn.IFNA(VLOOKUP(A43,'Personnel List'!A$1:F$1284,6,FALSE),"")
B44: =_xlfn.IFNA(VLOOKUP(A44,'Personnel List'!A$1:E$1284,5,FALSE),"") | C44: =_xlfn.IFNA(VLOOKUP(A44,'Personnel List'!A$1:E$1284,4,FALSE),"") | D44: =IF(A44<>"",IF(D44<>"",D44,NOW()),"") | E44: =IFERROR(VLOOKUP(A44,G:I,3,FALSE),"Onsite") -> Onsite | I44: =IF(G44<>"",IF(I44<>"",I44,NOW()),"") | J44: =SUBSTITUTE(A44,"NC","") | L44: 0 | N44: =_xlfn.IFNA(VLOOKUP(A44,'Personnel List'!A$1:F$1284,6,FALSE),"")
B45: =_xlfn.IFNA(VLOOKUP(A45,'Personnel List'!A$1:E$1284,5,FALSE),"") | C45: =_xlfn.IFNA(VLOOKUP(A45,'Personnel List'!A$1:E$1284,4,FALSE),"") | D45: =IF(A45<>"",IF(D45<>"",D45,NOW()),"") | E45: =IFERROR(VLOOKUP(A45,G:I,3,FALSE),"Onsite") -> Onsite | I45: =IF(G45<>"",IF(I45<>"",I45,NOW()),"") | J45: =SUBSTITUTE(A45,"NC","") | L45: 0 | N45: =_xlfn.IFNA(VLOOKUP(A45,'Personnel List'!A$1:F$1284,6,FALSE),"")
B46: =_xlfn.IFNA(VLOOKUP(A46,'Personnel List'!A$1:E$1284,5,FALSE),"") | C46: =_xlfn.IFNA(VLOOKUP(A46,'Personnel List'!A$1:E$1284,4,FALSE),"") | D46: =IF(A46<>"",IF(D46<>"",D46,NOW()),"") | E46: =IFERROR(VLOOKUP(A46,G:I,3,FALSE),"Onsite") -> Onsite | I46: =IF(G886<>"",IF(I46<>"",I46,NOW()),"") | J46: =SUBSTITUTE(A46,"NC","") | L46: 0 | N46: =_xlfn.IFNA(VLOOKUP(A46,'Personnel List'!A$1:F$1284,6,FALSE),"")
B47: =_xlfn.IFNA(VLOOKUP(A47,'Personnel List'!A$1:E$1284,5,FALSE),"") | C47: =_xlfn.IFNA(VLOOKUP(A47,'Personnel List'!A$1:E$1284,4,FALSE),"") | D47: =IF(A47<>"",IF(D47<>"",D47,NOW()),"") | E47: =IFERROR(VLOOKUP(A47,G:I,3,FALSE),"Onsite") -> Onsite | I47: =IF(G887<>"",IF(I47<>"",I47,NOW()),"") | J47: =SUBSTITUTE(A47,"NC","") | L47: 0 | N47: =_xlfn.IFNA(VLOOKUP(A47,'Personnel List'!A$1:F$1284,6,FALSE),"")
B48: =_xlfn.IFNA(VLOOKUP(A48,'Personnel List'!A$1:E$1284,5,FALSE),"") | C48: =_xlfn.IFNA(VLOOKUP(A48,'Personnel List'!A$1:E$1284,4,FALSE),"") | D48: =IF(A48<>"",IF(D48<>"",D48,NOW()),"") | E48: =IFERROR(VLOOKUP(A48,G:I,3,FALSE),"Onsite") -> Onsite | I48: =IF(G888<>"",IF(I48<>"",I48,NOW()),"") | J48: =SUBSTITUTE(A48,"NC","") | L48: 0 | N48: =_xlfn.IFNA(VLOOKUP(A48,'Personnel List'!A$1:F$1284,6,FALSE),"")
B49: =_xlfn.IFNA(VLOOKUP(A49,'Personnel List'!A$1:E$1284,5,FALSE),"") | C49: =_xlfn.IFNA(VLOOKUP(A49,'Personnel List'!A$1:E$1284,4,FALSE),"") | D49: =IF(A49<>"",IF(D49<>"",D49,NOW()),"") | E49: =IFERROR(VLOOKUP(A49,G:I,3,FALSE),"Onsite") -> Onsite | I49: =IF(G889<>"",IF(I49<>"",I49,NOW()),"") | J49: =SUBSTITUTE(A49,"NC","") | L49: 0 | N49: =_xlfn.IFNA(VLOOKUP(A49,'Personnel List'!A$1:F$1284,6,FALSE),"")
B50: =_xlfn.IFNA(VLOOKUP(A50,'Personnel List'!A$1:E$1284,5,FALSE),"") | C50: =_xlfn.IFNA(VLOOKUP(A50,'Personnel List'!A$1:E$1284,4,FALSE),"") | D50: =IF(A50<>"",IF(D50<>"",D50,NOW()),"") | E50: =IFERROR(VLOOKUP(A50,G:I,3,FALSE),"Onsite") -> Onsite | I50: =IF(G890<>"",IF(I50<>"",I50,NOW()),"") | J50: =SUBSTITUTE(A50,"NC","") | L50: 0 | N50: =_xlfn.IFNA(VLOOKUP(A50,'Personnel List'!A$1:F$1284,6,FALSE),"")
B51: =_xlfn.IFNA(VLOOKUP(A51,'Personnel List'!A$1:E$1284,5,FALSE),"") | C51: =_xlfn.IFNA(VLOOKUP(A51,'Personnel List'!A$1:E$1284,4,FALSE),"") | D51: =IF(A51<>"",IF(D51<>"",D51,NOW()),"") | E51: =IFERROR(VLOOKUP(A51,G:I,3,FALSE),"Onsite") -> Onsite | I51: =IF(G891<>"",IF(I51<>"",I51,NOW()),"") | J51: =SUBSTITUTE(A51,"NC","") | L51: 0 | N51: =_xlfn.IFNA(VLOOKUP(A51,'Personnel List'!A$1:F$1284,6,FALSE),"")
B52: =_xlfn.IFNA(VLOOKUP(A52,'Personnel List'!A$1:E$1284,5,FALSE),"") | C52: =_xlfn.IFNA(VLOOKUP(A52,'Personnel List'!A$1:E$1284,4,FALSE),"") | D52: =IF(A52<>"",IF(D52<>"",D52,NOW()),"") | E52: =IFERROR(VLOOKUP(A52,G:I,3,FALSE),"Onsite") -> Onsite | I52: =IF(G892<>"",IF(I52<>"",I52,NOW()),"") | J52: =SUBSTITUTE(A52,"NC","") | L52: 0 | N52: =_xlfn.IFNA(VLOOKUP(A52,'Personnel List'!A$1:F$1284,6,FALSE),"")
B53: =_xlfn.IFNA(VLOOKUP(A53,'Personnel List'!A$1:E$1284,5,FALSE),"") | D53: =IF(A53<>"",IF(D53<>"",D53,NOW()),"") | E53: =IFERROR(VLOOKUP(A53,G:I,3,FALSE),"Onsite") -> Onsite | I53: =IF(G893<>"",IF(I53<>"",I53,NOW()),"") | J53: =SUBSTITUTE(A53,"NC","") | L53: 0 | N53: =_xlfn.IFNA(VLOOKUP(A53,'Personnel List'!A$1:F$1284,6,FALSE),"")
B54: =_xlfn.IFNA(VLOOKUP(A54,'Personnel List'!A$1:E$1284,5,FALSE),"") | D54: =IF(A54<>"",IF(D54<>"",D54,NOW()),"") | E54: =IFERROR(VLOOKUP(A54,G:I,3,FALSE),"Onsite") -> Onsite | I54: =IF(G894<>"",IF(I54<>"",I54,NOW()),"") | J54: =SUBSTITUTE(A54,"NC","") | L54: 0 | N54: =_xlfn.IFNA(VLOOKUP(A54,'Personnel List'!A$1:F$1284,6,FALSE),"")
B55: =_xlfn.IFNA(VLOOKUP(A55,'Personnel List'!A$1:E$1284,5,FALSE),"") | C55: =_xlfn.IFNA(VLOOKUP(A55,'Personnel List'!A$1:E$1284,4,FALSE),"") | D55: =IF(A55<>"",IF(D55<>"",D55,NOW()),"") | E55: =IFERROR(VLOOKUP(A55,G:I,3,FALSE),"Onsite") -> Onsite | I55: =IF(G895<>"",IF(I55<>"",I55,NOW()),"") | J55: =SUBSTITUTE(A55,"NC","") | L55: 0 | N55: =_xlfn.IFNA(VLOOKUP(A55,'Personnel List'!A$1:F$1284,6,FALSE),"")
B56: =_xlfn.IFNA(VLOOKUP(A56,'Personnel List'!A$1:E$1284,5,FALSE),"") | C56: =_xlfn.IFNA(VLOOKUP(A56,'Personnel List'!A$1:E$1284,4,FALSE),"") | D56: =IF(A56<>"",IF(D56<>"",D56,NOW()),"") | E56: =IFERROR(VLOOKUP(A56,G:I,3,FALSE),"Onsite") -> Onsite | I56: =IF(G896<>"",IF(I56<>"",I56,NOW()),"") | J56: =SUBSTITUTE(A56,"NC","") | L56: 0 | N56: =_xlfn.IFNA(VLOOKUP(A56,'Personnel List'!A$1:F$1284,6,FALSE),"")
B57: =_xlfn.IFNA(VLOOKUP(A57,'Personnel List'!A$1:E$1284,5,FALSE),"") | C57: =_xlfn.IFNA(VLOOKUP(A57,'Personnel List'!A$1:E$1284,4,FALSE),"") | D57: =IF(A57<>"",IF(D57<>"",D57,NOW()),"") | E57: =IFERROR(VLOOKUP(A57,G:I,3,FALSE),"Onsite") -> Onsite | I57: =IF(G897<>"",IF(I57<>"",I57,NOW()),"") | J57: =SUBSTITUTE(A57,"NC","") | L57: 0 | N57: =_xlfn.IFNA(VLOOKUP(A57,'Personnel List'!A$1:F$1284,6,FALSE),"")
B58: =_xlfn.IFNA(VLOOKUP(A58,'Personnel List'!A$1:E$1284,5,FALSE),"") | C58: =_xlfn.IFNA(VLOOKUP(A58,'Personnel List'!A$1:E$1284,4,FALSE),"") | D58: =IF(A58<>"",IF(D58<>"",D58,NOW()),"") | E58: =IFERROR(VLOOKUP(A58,G:I,3,FALSE),"Onsite") -> Onsite | I58: =IF(G898<>"",IF(I58<>"",I58,NOW()),"") | J58: =SUBSTITUTE(A58,"NC","") | L58: 0 | N58: =_xlfn.IFNA(VLOOKUP(A58,'Personnel List'!A$1:F$1284,6,FALSE),"")
B59: =_xlfn.IFNA(VLOOKUP(A59,'Personnel List'!A$1:E$1284,5,FALSE),"") | C59: =_xlfn.IFNA(VLOOKUP(A59,'Personnel List'!A$1:E$1284,4,FALSE),"") | D59: =IF(A59<>"",IF(D59<>"",D59,NOW()),"") | E59: =IFERROR(VLOOKUP(A59,G:I,3,FALSE),"Onsite") -> Onsite | I59: =IF(G899<>"",IF(I59<>"",I59,NOW()),"") | J59: =SUBSTITUTE(A59,"NC","") | L59: 0 | N59: =_xlfn.IFNA(VLOOKUP(A59,'Personnel List'!A$1:F$1284,6,FALSE),"")
B60: =_xlfn.IFNA(VLOOKUP(A60,'Personnel List'!A$1:E$1284,5,FALSE),"") | C60: =_xlfn.IFNA(VLOOKUP(A60,'Personnel List'!A$1:E$1284,4,FALSE),"") | D60: =IF(A60<>"",IF(D60<>"",D60,NOW()),"") | E60: =IFERROR(VLOOKUP(A60,G:I,3,FALSE),"Onsite") -> Onsite | I60: =IF(G900<>"",IF(I60<>"",I60,NOW()),"") | J60: =SUBSTITUTE(A60,"NC","") | L60: 0 | N60: =_xlfn.IFNA(VLOOKUP(A60,'Personnel List'!A$1:F$1284,6,FALSE),"")
B61: =_xlfn.IFNA(VLOOKUP(A61,'Personnel List'!A$1:E$1284,5,FALSE),"") | C61: =_xlfn.IFNA(VLOOKUP(A61,'Personnel List'!A$1:E$1284,4,FALSE),"") | D61: =IF(A61<>"",IF(D61<>"",D61,NOW()),"") | E61: =IFERROR(VLOOKUP(A61,G:I,3,FALSE),"Onsite") -> Onsite | I61: =IF(G901<>"",IF(I61<>"",I61,NOW()),"") | J61: =SUBSTITUTE(A61,"NC","") | L61: 0 | N61: =_xlfn.IFNA(VLOOKUP(A61,'Personnel List'!A$1:F$1284,6,FALSE),"")
B62: =_xlfn.IFNA(VLOOKUP(A62,'Personnel List'!A$1:E$1284,5,FALSE),"") | C62: =_xlfn.IFNA(VLOOKUP(A62,'Personnel List'!A$1:E$1284,4,FALSE),"") | D62: =IF(A62<>"",IF(D62<>"",D62,NOW()),"") | E62: =IFERROR(VLOOKUP(A62,G:I,3,FALSE),"Onsite") -> Onsite | I62: =IF(G902<>"",IF(I62<>"",I62,NOW()),"") | J62: =SUBSTITUTE(A62,"NC","") | L62: 0 | N62: =_xlfn.IFNA(VLOOKUP(A62,'Personnel List'!A$1:F$1284,6,FALSE),"")
B63: =_xlfn.IFNA(VLOOKUP(A63,'Personnel List'!A$1:E$1284,5,FALSE),"") | C63: =_xlfn.IFNA(VLOOKUP(A63,'Personnel List'!A$1:E$1284,4,FALSE),"") | D63: =IF(A63<>"",IF(D63<>"",D63,NOW()),"") | E63: =IFERROR(VLOOKUP(A63,G:I,3,FALSE),"Onsite") -> Onsite | I63: =IF(G903<>"",IF(I63<>"",I63,NOW()),"") | J63: =SUBSTITUTE(A63,"NC","") | L63: 0 | N63: =_xlfn.IFNA(VLOOKUP(A63,'Personnel List'!A$1:F$1284,6,FALSE),"")
B64: =_xlfn.IFNA(VLOOKUP(A64,'Personnel List'!A$1:E$1284,5,FALSE),"") | C64: =_xlfn.IFNA(VLOOKUP(A64,'Personnel List'!A$1:E$1284,4,FALSE),"") | D64: =IF(A64<>"",IF(D64<>"",D64,NOW()),"") | E64: =IFERROR(VLOOKUP(A64,G:I,3,FALSE),"Onsite") -> Onsite | I64: =IF(G904<>"",IF(I64<>"",I64,NOW()),"") | J64: =SUBSTITUTE(A64,"NC","") | L64: 0 | N64: =_xlfn.IFNA(VLOOKUP(A64,'Personnel List'!A$1:F$1284,6,FALSE),"")
B65: =_xlfn.IFNA(VLOOKUP(A65,'Personnel List'!A$1:E$1284,5,FALSE),"") | C65: =_xlfn.IFNA(VLOOKUP(A65,'Personnel List'!A$1:E$1284,4,FALSE),"") | D65: =IF(A65<>"",IF(D65<>"",D65,NOW()),"") | E65: =IFERROR(VLOOKUP(A65,G:I,3,FALSE),"Onsite") -> Onsite | I65: =IF(G905<>"",IF(I65<>"",I65,NOW()),"") | J65: =SUBSTITUTE(A65,"NC","") | L65: 0 | N65: =_xlfn.IFNA(VLOOKUP(A65,'Personnel List'!A$1:F$1284,6,FALSE),"")
B66: =_xlfn.IFNA(VLOOKUP(A66,'Personnel List'!A$1:E$1284,5,FALSE),"") | C66: =_xlfn.IFNA(VLOOKUP(A66,'Personnel List'!A$1:E$1284,4,FALSE),"") | D66: =IF(A66<>"",IF(D66<>"",D66,NOW()),"") | E66: =IFERROR(VLOOKUP(A66,G:I,3,FALSE),"Onsite") -> Onsite | I66: =IF(G906<>"",IF(I66<>"",I66,NOW()),"") | J66: =SUBSTITUTE(A66,"NC","") | L66: 0 | N66: =_xlfn.IFNA(VLOOKUP(A66,'Personnel List'!A$1:F$1284,6,FALSE),"")
... B876: =_xlfn.IFNA(VLOOKUP(A876,'Personnel List'!A$1:E$1284,5,FALSE),"") | C876: =_xlfn.IFNA(VLOOKUP(A876,'Personnel List'!A$1:E$1284,4,FALSE),"") | D876: =IF(A876<>"",IF(D876<>"",D876,NOW()),"") | E876: =IFERROR(VLOOKUP(A876,G:I,3,FALSE),"Onsite") -> Onsite | I876: =IF(G1716<>"",IF(I876<>"",I876,NOW()),"") | J876: =SUBSTITUTE(A876,"NC","") | L876: 0 | N876: =_xlfn.IFNA(VLOOKUP(A876,'Personnel List'!A$1:F$1284,6,FALSE),"")
I877: =IF(G1717<>"",IF(I877<>"",I877,NOW()),"") | J877: =SUBSTITUTE(A877,"NC","") | L877: 0
L878: 0
L879: 0
L880: 0
L881: 0
L882: 0
L883: 0
L884: 0
L885: 0
L886: 0
L887: 0
L888: 0
L889: 0
... L1000: 0

Sheet Tue DS
A1: Scan ID | B1: Name | C1: Company Name | D1: Time In | E1: Time Out | G1: Scan Out | I1: Timestamp | J1: SAP Number | L1: Not Scanned Yet | M1: DS | N1: Reverse Name
A2: NC90112534 | B2: =_xlfn.IFNA(VLOOKUP(A2,'Personnel List'!A$1:E$1284,5,FALSE),"") -> Sonia Bott | C2: =_xlfn.IFNA(VLOOKUP(A2,'Personnel List'!A$1:E$1284,4,FALSE),"") -> Coates Pty Ltd | D2: =IF(A2<>"",IF(D2<>"",D2,NOW()),"") -> 45531.213 | E2: =IFERROR(VLOOKUP(A2,G:I,3,FALSE),"Onsite") -> 45531.724 | G2: NC6324 | I2: =IF(G2<>"",IF(I2<>"",I2,NOW()),"") -> 45531.604 | J2: =SUBSTITUTE(A2,"NC","") -> 90112534 | L2: {=_xlfn._xlws.FILTER(M2:M1000,(ISNA(MATCH(M2:M1000,N2:N1000,0))),"")} -> 0 | M2: {=_xlfn._xlws.FILTER('Tue Data'!E13:E786,ISNUMBER(_xlfn.XMATCH('Tue Data'!D13:D786,M1)))} -> #VALUE! | N2: =_xlfn.IFNA(VLOOKUP(A2,'Personnel List'!A$1:F$1284,6,FALSE),"") -> Bott, Sonia
A3: NC90070857 | B3: =_xlfn.IFNA(VLOOKUP(A3,'Personnel List'!A$1:E$1284,5,FALSE),"") -> Brodie Eaton | C3: =_xlfn.IFNA(VLOOKUP(A3,'Personnel List'!A$1:E$1284,4,FALSE),"") -> APMS | D3: =IF(A3<>"",IF(D3<>"",D3,NOW()),"") -> 45531.237 | E3: =IFERROR(VLOOKUP(A3,G:I,3,FALSE),"Onsite") -> Onsite | G3: NC22249 | I3: =IF(G3<>"",IF(I3<>"",I3,NOW()),"") -> 45531.604 | J3: =SUBSTITUTE(A3,"NC","") -> 90070857 | L3: 0 | N3: =_xlfn.IFNA(VLOOKUP(A3,'Personnel List'!A$1:F$1284,6,FALSE),"") -> Eaton, Brodie
A4: NC90069096 | B4: =_xlfn.IFNA(VLOOKUP(A4,'Personnel List'!A$1:E$1284,5,FALSE),"") | C4: =_xlfn.IFNA(VLOOKUP(A4,'Personnel List'!A$1:E$1284,4,FALSE),"") | D4: =IF(A4<>"",IF(D4<>"",D4,NOW()),"") -> 45531.237 | E4: =IFERROR(VLOOKUP(A4,G:I,3,FALSE),"Onsite") -> Onsite | G4: NC18645 | I4: =IF(G4<>"",IF(I4<>"",I4,NOW()),"") -> 45531.605 | J4: =SUBSTITUTE(A4,"NC","") -> 90069096 | L4: 0 | N4: =_xlfn.IFNA(VLOOKUP(A4,'Personnel List'!A$1:F$1284,6,FALSE),"")
A5: NC90117684 | B5: =_xlfn.IFNA(VLOOKUP(A5,'Personnel List'!A$1:E$1284,5,FALSE),"") -> Isobel Newman | C5: =_xlfn.IFNA(VLOOKUP(A5,'Personnel List'!A$1:E$1284,4,FALSE),"") -> Hays Personnel Services | D5: =IF(A5<>"",IF(D5<>"",D5,NOW()),"") -> 45531.237 | E5: =IFERROR(VLOOKUP(A5,G:I,3,FALSE),"Onsite") -> 45531.719 | G5: NC4870 | I5: =IF(G5<>"",IF(I5<>"",I5,NOW()),"") -> 45531.605 | J5: =SUBSTITUTE(A5,"NC","") -> 90117684 | L5: 0 | N5: =_xlfn.IFNA(VLOOKUP(A5,'Personnel List'!A$1:F$1284,6,FALSE),"") -> Newman, Isobel
A6: NC90135965 | B6: =_xlfn.IFNA(VLOOKUP(A6,'Personnel List'!A$1:E$1284,5,FALSE),"") | C6: =_xlfn.IFNA(VLOOKUP(A6,'Personnel List'!A$1:E$1284,4,FALSE),"") | D6: =IF(A6<>"",IF(D6<>"",D6,NOW()),"") -> 45531.238 | E6: =IFERROR(VLOOKUP(A6,G:I,3,FALSE),"Onsite") -> Onsite | G6: NC90117684 | I6: =IF(G6<>"",IF(I6<>"",I6,NOW()),"") -> 45531.719 | J6: =SUBSTITUTE(A6,"NC","") -> 90135965 | L6: 0 | N6: =_xlfn.IFNA(VLOOKUP(A6,'Personnel List'!A$1:F$1284,6,FALSE),"")
A7: NC90122588 | B7: =_xlfn.IFNA(VLOOKUP(A7,'Personnel List'!A$1:E$1284,5,FALSE),"") -> Dion Pene-Gavin | C7: =_xlfn.IFNA(VLOOKUP(A7,'Personnel List'!A$1:E$1284,4,FALSE),"") -> Global Mill Relines | D7: =IF(A7<>"",IF(D7<>"",D7,NOW()),"") -> 45531.239 | E7: =IFERROR(VLOOKUP(A7,G:I,3,FALSE),"Onsite") -> Onsite | G7: NC90112534 | I7: =IF(G7<>"",IF(I7<>"",I7,NOW()),"") -> 45531.724 | J7: =SUBSTITUTE(A7,"NC","") -> 90122588 | L7: 0 | N7: =_xlfn.IFNA(VLOOKUP(A7,'Personnel List'!A$1:F$1284,6,FALSE),"") -> Pene-Gavin, Dion
A8: NC90122587 | B8: =_xlfn.IFNA(VLOOKUP(A8,'Personnel List'!A$1:E$1284,5,FALSE),"") -> Deke Colin Strong | C8: =_xlfn.IFNA(VLOOKUP(A8,'Personnel List'!A$1:E$1284,4,FALSE),"") -> Global Mill Relines | D8: =IF(A8<>"",IF(D8<>"",D8,NOW()),"") -> 45531.239 | E8: =IFERROR(VLOOKUP(A8,G:I,3,FALSE),"Onsite") -> Onsite | I8: =IF(G8<>"",IF(I8<>"",I8,NOW()),"") | J8: =SUBSTITUTE(A8,"NC","") -> 90122587 | L8: 0 | N8: =_xlfn.IFNA(VLOOKUP(A8,'Personnel List'!A$1:F$1284,6,FALSE),"") -> Strong, Deke Colin
A9: NC90136780 | B9: =_xlfn.IFNA(VLOOKUP(A9,'Personnel List'!A$1:E$1284,5,FALSE),"") | C9: =_xlfn.IFNA(VLOOKUP(A9,'Personnel List'!A$1:E$1284,4,FALSE),"") | D9: =IF(A9<>"",IF(D9<>"",D9,NOW()),"") -> 45531.239 | E9: =IFERROR(VLOOKUP(A9,G:I,3,FALSE),"Onsite") -> Onsite | I9: =IF(G9<>"",IF(I9<>"",I9,NOW()),"") | J9: =SUBSTITUTE(A9,"NC","") -> 90136780 | L9: 0 | N9: =_xlfn.IFNA(VLOOKUP(A9,'Personnel List'!A$1:F$1284,6,FALSE),"")
A10: NC90109011 | B10: =_xlfn.IFNA(VLOOKUP(A10,'Personnel List'!A$1:E$1284,5,FALSE),"") | C10: =_xlfn.IFNA(VLOOKUP(A10,'Personnel List'!A$1:E$1284,4,FALSE),"") | D10: =IF(A10<>"",IF(D10<>"",D10,NOW()),"") -> 45531.239 | E10: =IFERROR(VLOOKUP(A10,G:I,3,FALSE),"Onsite") -> Onsite | I10: =IF(G10<>"",IF(I10<>"",I10,NOW()),"") | J10: =SUBSTITUTE(A10,"NC","") -> 90109011 | L10: 0 | N10: =_xlfn.IFNA(VLOOKUP(A10,'Personnel List'!A$1:F$1284,6,FALSE),"")
A11: NC6324 | B11: =_xlfn.IFNA(VLOOKUP(A11,'Personnel List'!A$1:E$1284,5,FALSE),"") -> Davin Lord | C11: =_xlfn.IFNA(VLOOKUP(A11,'Personnel List'!A$1:E$1284,4,FALSE),"") -> Newmont | D11: =IF(A11<>"",IF(D11<>"",D11,NOW()),"") -> 45531.245 | E11: =IFERROR(VLOOKUP(A11,G:I,3,FALSE),"Onsite") -> 45531.604 | I11: =IF(G11<>"",IF(I11<>"",I11,NOW()),"") | J11: =SUBSTITUTE(A11,"NC","") -> 6324 | L11: 0 | N11: =_xlfn.IFNA(VLOOKUP(A11,'Personnel List'!A$1:F$1284,6,FALSE),"") -> Lord, Davin
A12: NC22249 | B12: =_xlfn.IFNA(VLOOKUP(A12,'Personnel List'!A$1:E$1284,5,FALSE),"") -> Renatta Leofo | C12: =_xlfn.IFNA(VLOOKUP(A12,'Personnel List'!A$1:E$1284,4,FALSE),"") -> Newmont | D12: =IF(A12<>"",IF(D12<>"",D12,NOW()),"") -> 45531.245 | E12: =IFERROR(VLOOKUP(A12,G:I,3,FALSE),"Onsite") -> 45531.604 | I12: =IF(G12<>"",IF(I12<>"",I12,NOW()),"") | J12: =SUBSTITUTE(A12,"NC","") -> 22249 | L12: 0 | N12: =_xlfn.IFNA(VLOOKUP(A12,'Personnel List'!A$1:F$1284,6,FALSE),"") -> Leofo, Renatta
A13: NC18645 | B13: =_xlfn.IFNA(VLOOKUP(A13,'Personnel List'!A$1:E$1284,5,FALSE),"") -> Glenn Lavery | C13: =_xlfn.IFNA(VLOOKUP(A13,'Personnel List'!A$1:E$1284,4,FALSE),"") -> Newmont | D13: =IF(A13<>"",IF(D13<>"",D13,NOW()),"") -> 45531.245 | E13: =IFERROR(VLOOKUP(A13,G:I,3,FALSE),"Onsite") -> 45531.605 | I13: =IF(G13<>"",IF(I13<>"",I13,NOW()),"") | J13: =SUBSTITUTE(A13,"NC","") -> 18645 | L13: 0 | N13: =_xlfn.IFNA(VLOOKUP(A13,'Personnel List'!A$1:F$1284,6,FALSE),"") -> Lavery, Glenn
A14: NC4870 | B14: =_xlfn.IFNA(VLOOKUP(A14,'Personnel List'!A$1:E$1284,5,FALSE),"") -> Bill Geary | C14: =_xlfn.IFNA(VLOOKUP(A14,'Personnel List'!A$1:E$1284,4,FALSE),"") -> Newmont | D14: =IF(A14<>"",IF(D14<>"",D14,NOW()),"") -> 45531.245 | E14: =IFERROR(VLOOKUP(A14,G:I,3,FALSE),"Onsite") -> 45531.605 | I14: =IF(G14<>"",IF(I14<>"",I14,NOW()),"") | J14: =SUBSTITUTE(A14,"NC","") -> 4870 | L14: 0 | N14: =_xlfn.IFNA(VLOOKUP(A14,'Personnel List'!A$1:F$1284,6,FALSE),"") -> Geary, Bill
A15: NC19989 | B15: =_xlfn.IFNA(VLOOKUP(A15,'Personnel List'!A$1:E$1284,5,FALSE),"") -> Jason Pendreigh | C15: =_xlfn.IFNA(VLOOKUP(A15,'Personnel List'!A$1:E$1284,4,FALSE),"") -> Newmont | D15: =IF(A15<>"",IF(D15<>"",D15,NOW()),"") -> 45531.245 | E15: =IFERROR(VLOOKUP(A15,G:I,3,FALSE),"Onsite") -> Onsite | I15: =IF(G15<>"",IF(I15<>"",I15,NOW()),"") | J15: =SUBSTITUTE(A15,"NC","") -> 19989 | L15: 0 | N15: =_xlfn.IFNA(VLOOKUP(A15,'Personnel List'!A$1:F$1284,6,FALSE),"") -> Pendreigh, Jason
A16: NC18952 | B16: =_xlfn.IFNA(VLOOKUP(A16,'Personnel List'!A$1:E$1284,5,FALSE),"") -> John Rowley | C16: =_xlfn.IFNA(VLOOKUP(A16,'Personnel List'!A$1:E$1284,4,FALSE),"") -> Newmont | D16: =IF(A16<>"",IF(D16<>"",D16,NOW()),"") -> 45531.245 | E16: =IFERROR(VLOOKUP(A16,G:I,3,FALSE),"Onsite") -> Onsite | I16: =IF(G16<>"",IF(I16<>"",I16,NOW()),"") | J16: =SUBSTITUTE(A16,"NC","") -> 18952 | L16: 0 | N16: =_xlfn.IFNA(VLOOKUP(A16,'Personnel List'!A$1:F$1284,6,FALSE),"") -> Rowley, John
A17: NC90050488 | B17: =_xlfn.IFNA(VLOOKUP(A17,'Personnel List'!A$1:E$1284,5,FALSE),"") -> Tyler Harris | C17: =_xlfn.IFNA(VLOOKUP(A17,'Personnel List'!A$1:E$1284,4,FALSE),"") -> Geraldton Hydraulics | D17: =IF(A17<>"",IF(D17<>"",D17,NOW()),"") -> 45531.254 | E17: =IFERROR(VLOOKUP(A17,G:I,3,FALSE),"Onsite") -> Onsite | I17: =IF(G17<>"",IF(I17<>"",I17,NOW()),"") | J17: =SUBSTITUTE(A17,"NC","") -> 90050488 | L17: 0 | N17: =_xlfn.IFNA(VLOOKUP(A17,'Personnel List'!A$1:F$1284,6,FALSE),"") -> Harris, Tyler
A18: NC90128939 | B18: =_xlfn.IFNA(VLOOKUP(A18,'Personnel List'!A$1:E$1284,5,FALSE),"") -> Rolando Ola | C18: =_xlfn.IFNA(VLOOKUP(A18,'Personnel List'!A$1:E$1284,4,FALSE),"") -> APMS | D18: =IF(A18<>"",IF(D18<>"",D18,NOW()),"") -> 45531.26 | E18: =IFERROR(VLOOKUP(A18,G:I,3,FALSE),"Onsite") -> Onsite | I18: =IF(G18<>"",IF(I18<>"",I18,NOW()),"") | J18: =SUBSTITUTE(A18,"NC","") -> 90128939 | L18: 0 | N18: =_xlfn.IFNA(VLOOKUP(A18,'Personnel List'!A$1:F$1284,6,FALSE),"") -> Ola, Rolando
A19: NC90009868 | B19: =_xlfn.IFNA(VLOOKUP(A19,'Personnel List'!A$1:E$1284,5,FALSE),"") -> Reece Murray | C19: =_xlfn.IFNA(VLOOKUP(A19,'Personnel List'!A$1:E$1284,4,FALSE),"") -> APMS | D19: =IF(A19<>"",IF(D19<>"",D19,NOW()),"") -> 45531.261 | E19: =IFERROR(VLOOKUP(A19,G:I,3,FALSE),"Onsite") -> Onsite | I19: =IF(G19<>"",IF(I19<>"",I19,NOW()),"") | J19: =SUBSTITUTE(A19,"NC","") -> 90009868 | L19: 0 | N19: =_xlfn.IFNA(VLOOKUP(A19,'Personnel List'!A$1:F$1284,6,FALSE),"") -> Murray, Reece
... A32: NC90094237 | B32: =_xlfn.IFNA(VLOOKUP(A32,'Personnel List'!A$1:E$1284,5,FALSE),"") -> Edward Santhanam | C32: =_xlfn.IFNA(VLOOKUP(A32,'Personnel List'!A$1:E$1284,4,FALSE),"") -> Losugen | D32: =IF(A32<>"",IF(D32<>"",D32,NOW()),"") -> 45531.264 | E32: =IFERROR(VLOOKUP(A32,G:I,3,FALSE),"Onsite") -> Onsite | I32: =IF(G32<>"",IF(I32<>"",I32,NOW()),"") | J32: =SUBSTITUTE(A32,"NC","") -> 90094237 | L32: 0 | N32: =_xlfn.IFNA(VLOOKUP(A32,'Personnel List'!A$1:F$1284,6,FALSE),"") -> Santhanam, Edward
A33: NC90134808 | B33: =_xlfn.IFNA(VLOOKUP(A33,'Personnel List'!A$1:E$1284,5,FALSE),"") -> Graham Boyd | E33: =IFERROR(VLOOKUP(A33,G:I,3,FALSE),"Onsite") -> Onsite | I33: =IF(G33<>"",IF(I33<>"",I33,NOW()),"") | J33: =SUBSTITUTE(A33,"NC","") -> 90134808 | L33: 0 | N33: =_xlfn.IFNA(VLOOKUP(A33,'Personnel List'!A$1:F$1284,6,FALSE),"") -> Boyd, Graham
A34: NC23783 | B34: =_xlfn.IFNA(VLOOKUP(A34,'Personnel List'!A$1:E$1284,5,FALSE),"") -> Travis Cooper | C34: =_xlfn.IFNA(VLOOKUP(A34,'Personnel List'!A$1:E$1284,4,FALSE),"") -> Newmont | D34: =IF(A34<>"",IF(D34<>"",D34,NOW()),"") -> 45531.264 | E34: =IFERROR(VLOOKUP(A34,G:I,3,FALSE),"Onsite") -> Onsite | I34: =IF(G34<>"",IF(I34<>"",I34,NOW()),"") | J34: =SUBSTITUTE(A34,"NC","") -> 23783 | L34: 0 | N34: =_xlfn.IFNA(VLOOKUP(A34,'Personnel List'!A$1:F$1284,6,FALSE),"") -> Cooper, Travis
A35: NC90130583 | B35: =_xlfn.IFNA(VLOOKUP(A35,'Personnel List'!A$1:E$1284,5,FALSE),"") -> Martin Mulhall | C35: =_xlfn.IFNA(VLOOKUP(A35,'Personnel List'!A$1:E$1284,4,FALSE),"") -> Mader Contracting | D35: =IF(A35<>"",IF(D35<>"",D35,NOW()),"") -> 45531.264 | E35: =IFERROR(VLOOKUP(A35,G:I,3,FALSE),"Onsite") -> Onsite | I35: =IF(G35<>"",IF(I35<>"",I35,NOW()),"") | J35: =SUBSTITUTE(A35,"NC","") -> 90130583 | L35: 0 | N35: =_xlfn.IFNA(VLOOKUP(A35,'Personnel List'!A$1:F$1284,6,FALSE),"") -> Mulhall, Martin
A36: NC24719 | B36: =_xlfn.IFNA(VLOOKUP(A36,'Personnel List'!A$1:E$1284,5,FALSE),"") -> Emily Lane | C36: =_xlfn.IFNA(VLOOKUP(A36,'Personnel List'!A$1:E$1284,4,FALSE),"") -> Newmont | D36: =IF(A36<>"",IF(D36<>"",D36,NOW()),"") -> 45531.264 | E36: =IFERROR(VLOOKUP(A36,G:I,3,FALSE),"Onsite") -> Onsite | I36: =IF(G36<>"",IF(I36<>"",I36,NOW()),"") | J36: =SUBSTITUTE(A36,"NC","") -> 24719 | L36: 0 | N36: =_xlfn.IFNA(VLOOKUP(A36,'Personnel List'!A$1:F$1284,6,FALSE),"") -> Lane, Emily
A37: NC24687 | B37: =_xlfn.IFNA(VLOOKUP(A37,'Personnel List'!A$1:E$1284,5,FALSE),"") -> Sean Smethurst | C37: =_xlfn.IFNA(VLOOKUP(A37,'Personnel List'!A$1:E$1284,4,FALSE),"") -> Newmont | D37: =IF(A37<>"",IF(D37<>"",D37,NOW()),"") -> 45531.264 | E37: =IFERROR(VLOOKUP(A37,G:I,3,FALSE),"Onsite") -> Onsite | I37: =IF(G37<>"",IF(I37<>"",I37,NOW()),"") | J37: =SUBSTITUTE(A37,"NC","") -> 24687 | L37: 0 | N37: =_xlfn.IFNA(VLOOKUP(A37,'Personnel List'!A$1:F$1284,6,FALSE),"") -> Smethurst, Sean
A38: NC20304 | B38: =_xlfn.IFNA(VLOOKUP(A38,'Personnel List'!A$1:E$1284,5,FALSE),"") -> Alistair Baker | C38: =_xlfn.IFNA(VLOOKUP(A38,'Personnel List'!A$1:E$1284,4,FALSE),"") -> Newmont | D38: =IF(A38<>"",IF(D38<>"",D38,NOW()),"") -> 45531.264 | E38: =IFERROR(VLOOKUP(A38,G:I,3,FALSE),"Onsite") -> Onsite | I38: =IF(G38<>"",IF(I38<>"",I38,NOW()),"") | J38: =SUBSTITUTE(A38,"NC","") -> 20304 | L38: 0 | N38: =_xlfn.IFNA(VLOOKUP(A38,'Personnel List'!A$1:F$1284,6,FALSE),"") -> Baker, Alistair
A39: NC18680 | B39: =_xlfn.IFNA(VLOOKUP(A39,'Personnel List'!A$1:E$1284,5,FALSE),"") -> Mark Cahill | C39: =_xlfn.IFNA(VLOOKUP(A39,'Personnel List'!A$1:E$1284,4,FALSE),"") -> Newmont | D39: =IF(A39<>"",IF(D39<>"",D39,NOW()),"") -> 45531.264 | E39: =IFERROR(VLOOKUP(A39,G:I,3,FALSE),"Onsite") -> Onsite | I39: =IF(G39<>"",IF(I39<>"",I39,NOW()),"") | J39: =SUBSTITUTE(A39,"NC","") -> 18680 | L39: 0 | N39: =_xlfn.IFNA(VLOOKUP(A39,'Personnel List'!A$1:F$1284,6,FALSE),"") -> Cahill, Mark
A40: NC23410 | B40: =_xlfn.IFNA(VLOOKUP(A40,'Personnel List'!A$1:E$1284,5,FALSE),"") -> Trevor Simpson | C40: =_xlfn.IFNA(VLOOKUP(A40,'Personnel List'!A$1:E$1284,4,FALSE),"") -> Newmont | D40: =IF(A40<>"",IF(D40<>"",D40,NOW()),"") -> 45531.264 | E40: =IFERROR(VLOOKUP(A40,G:I,3,FALSE),"Onsite") -> Onsite | I40: =IF(G40<>"",IF(I40<>"",I40,NOW()),"") | J40: =SUBSTITUTE(A40,"NC","") -> 23410 | L40: 0 | N40: =_xlfn.IFNA(VLOOKUP(A40,'Personnel List'!A$1:F$1284,6,FALSE),"") -> Simpson, Trevor
A41: NC22900 | D41: =IF(A41<>"",IF(D41<>"",D41,NOW()),"") -> 45531.264 | E41: =IFERROR(VLOOKUP(A41,G:I,3,FALSE),"Onsite") -> Onsite | I41: =IF(G41<>"",IF(I41<>"",I41,NOW()),"") | J41: =SUBSTITUTE(A41,"NC","") -> 22900 | L41: 0 | N41: =_xlfn.IFNA(VLOOKUP(A41,'Personnel List'!A$1:F$1284,6,FALSE),"") -> Brown, Dominic
A42: NC18062 | B42: =_xlfn.IFNA(VLOOKUP(A42,'Personnel List'!A$1:E$1284,5,FALSE),"") -> Angelo Madronero | C42: =_xlfn.IFNA(VLOOKUP(A42,'Personnel List'!A$1:E$1284,4,FALSE),"") -> Newmont | D42: =IF(A42<>"",IF(D42<>"",D42,NOW()),"") -> 45531.264 | E42: =IFERROR(VLOOKUP(A42,G:I,3,FALSE),"Onsite") -> Onsite | I42: =IF(G42<>"",IF(I42<>"",I42,NOW()),"") | J42: =SUBSTITUTE(A42,"NC","") -> 18062 | L42: 0 | N42: =_xlfn.IFNA(VLOOKUP(A42,'Personnel List'!A$1:F$1284,6,FALSE),"") -> Madronero, Angelo
A43: NC24490 | B43: =_xlfn.IFNA(VLOOKUP(A43,'Personnel List'!A$1:E$1284,5,FALSE),"") -> Thomas Ryan | C43: =_xlfn.IFNA(VLOOKUP(A43,'Personnel List'!A$1:E$1284,4,FALSE),"") -> Newmont | D43: =IF(A43<>"",IF(D43<>"",D43,NOW()),"") -> 45531.264 | E43: =IFERROR(VLOOKUP(A43,G:I,3,FALSE),"Onsite") -> Onsite | I43: =IF(G43<>"",IF(I43<>"",I43,NOW()),"") | J43: =SUBSTITUTE(A43,"NC","") -> 24490 | L43: 0 | N43: =_xlfn.IFNA(VLOOKUP(A43,'Personnel List'!A$1:F$1284,6,FALSE),"") -> Ryan, Thomas
A44: NC22794 | B44: =_xlfn.IFNA(VLOOKUP(A44,'Personnel List'!A$1:E$1284,5,FALSE),"") -> Trent Donges | C44: =_xlfn.IFNA(VLOOKUP(A44,'Personnel List'!A$1:E$1284,4,FALSE),"") -> Newmont | D44: =IF(A44<>"",IF(D44<>"",D44,NOW()),"") -> 45531.264 | E44: =IFERROR(VLOOKUP(A44,G:I,3,FALSE),"Onsite") -> Onsite | I44: =IF(G44<>"",IF(I44<>"",I44,NOW()),"") | J44: =SUBSTITUTE(A44,"NC","") -> 22794 | L44: 0 | N44: =_xlfn.IFNA(VLOOKUP(A44,'Personnel List'!A$1:F$1284,6,FALSE),"") -> Donges, Trent
A45: NC90040555 | B45: =_xlfn.IFNA(VLOOKUP(A45,'Personnel List'!A$1:E$1284,5,FALSE),"") -> Bradley Ness | C45: =_xlfn.IFNA(VLOOKUP(A45,'Personnel List'!A$1:E$1284,4,FALSE),"") -> SMS Group Services | D45: =IF(A45<>"",IF(D45<>"",D45,NOW()),"") -> 45531.264 | E45: =IFERROR(VLOOKUP(A45,G:I,3,FALSE),"Onsite") -> Onsite | I45: =IF(G45<>"",IF(I45<>"",I45,NOW()),"") | J45: =SUBSTITUTE(A45,"NC","") -> 90040555 | L45: 0 | N45: =_xlfn.IFNA(VLOOKUP(A45,'Personnel List'!A$1:F$1284,6,FALSE),"") -> Ness, Bradley
A46: NC22280 | B46: =_xlfn.IFNA(VLOOKUP(A46,'Personnel List'!A$1:E$1284,5,FALSE),"") -> Lee Coupe | C46: =_xlfn.IFNA(VLOOKUP(A46,'Personnel List'!A$1:E$1284,4,FALSE),"") -> Newmont | D46: =IF(A46<>"",IF(D46<>"",D46,NOW()),"") -> 45531.265 | E46: =IFERROR(VLOOKUP(A46,G:I,3,FALSE),"Onsite") -> Onsite | I46: =IF(G886<>"",IF(I46<>"",I46,NOW()),"") | J46: =SUBSTITUTE(A46,"NC","") -> 22280 | L46: 0 | N46: =_xlfn.IFNA(VLOOKUP(A46,'Personnel List'!A$1:F$1284,6,FALSE),"") -> Coupe, Lee
A47: NC3413 | B47: =_xlfn.IFNA(VLOOKUP(A47,'Personnel List'!A$1:E$1284,5,FALSE),"") -> Darren Lord | C47: =_xlfn.IFNA(VLOOKUP(A47,'Personnel List'!A$1:E$1284,4,FALSE),"") -> Newmont | D47: =IF(A47<>"",IF(D47<>"",D47,NOW()),"") -> 45531.265 | E47: =IFERROR(VLOOKUP(A47,G:I,3,FALSE),"Onsite") -> Onsite | I47: =IF(G887<>"",IF(I47<>"",I47,NOW()),"") | J47: =SUBSTITUTE(A47,"NC","") -> 3413 | L47: 0 | N47: =_xlfn.IFNA(VLOOKUP(A47,'Personnel List'!A$1:F$1284,6,FALSE),"") -> Lord, Darren
A48: NC90040292 | B48: =_xlfn.IFNA(VLOOKUP(A48,'Personnel List'!A$1:E$1284,5,FALSE),"") -> Jerry Taura | C48: =_xlfn.IFNA(VLOOKUP(A48,'Personnel List'!A$1:E$1284,4,FALSE),"") -> SMS Group Services | D48: =IF(A48<>"",IF(D48<>"",D48,NOW()),"") -> 45531.265 | E48: =IFERROR(VLOOKUP(A48,G:I,3,FALSE),"Onsite") -> Onsite | I48: =IF(G888<>"",IF(I48<>"",I48,NOW()),"") | J48: =SUBSTITUTE(A48,"NC","") -> 90040292 | L48: 0 | N48: =_xlfn.IFNA(VLOOKUP(A48,'Personnel List'!A$1:F$1284,6,FALSE),"") -> Taura, Jerry
A49: NC90112330 | B49: =_xlfn.IFNA(VLOOKUP(A49,'Personnel List'!A$1:E$1284,5,FALSE),"") -> Shannon McGregor | C49: =_xlfn.IFNA(VLOOKUP(A49,'Personnel List'!A$1:E$1284,4,FALSE),"") -> Boom Cranes | D49: =IF(A49<>"",IF(D49<>"",D49,NOW()),"") -> 45531.265 | E49: =IFERROR(VLOOKUP(A49,G:I,3,FALSE),"Onsite") -> Onsite | I49: =IF(G889<>"",IF(I49<>"",I49,NOW()),"") | J49: =SUBSTITUTE(A49,"NC","") -> 90112330 | L49: 0 | N49: =_xlfn.IFNA(VLOOKUP(A49,'Personnel List'!A$1:F$1284,6,FALSE),"") -> McGregor, Shannon
A50: NC90047222 | B50: =_xlfn.IFNA(VLOOKUP(A50,'Personnel List'!A$1:E$1284,5,FALSE),"") -> Russell-Kingi Tawaka | C50: =_xlfn.IFNA(VLOOKUP(A50,'Personnel List'!A$1:E$1284,4,FALSE),"") -> SMS Group Services | D50: =IF(A50<>"",IF(D50<>"",D50,NOW()),"") -> 45531.265 | E50: =IFERROR(VLOOKUP(A50,G:I,3,FALSE),"Onsite") -> Onsite | I50: =IF(G890<>"",IF(I50<>"",I50,NOW()),"") | J50: =SUBSTITUTE(A50,"NC","") -> 90047222 | L50: 0 | N50: =_xlfn.IFNA(VLOOKUP(A50,'Personnel List'!A$1:F$1284,6,FALSE),"") -> Tawaka, Russell-Kingi
A51: NC90009894 | B51: =_xlfn.IFNA(VLOOKUP(A51,'Personnel List'!A$1:E$1284,5,FALSE),"") -> Casey Pompey | C51: =_xlfn.IFNA(VLOOKUP(A51,'Personnel List'!A$1:E$1284,4,FALSE),"") -> SMS Group Services | D51: =IF(A51<>"",IF(D51<>"",D51,NOW()),"") -> 45531.265 | E51: =IFERROR(VLOOKUP(A51,G:I,3,FALSE),"Onsite") -> Onsite | I51: =IF(G891<>"",IF(I51<>"",I51,NOW()),"") | J51: =SUBSTITUTE(A51,"NC","") -> 90009894 | L51: 0 | N51: =_xlfn.IFNA(VLOOKUP(A51,'Personnel List'!A$1:F$1284,6,FALSE),"") -> Pompey, Casey
A52: NC90118868 | B52: =_xlfn.IFNA(VLOOKUP(A52,'Personnel List'!A$1:E$1284,5,FALSE),"") -> Cameron Jones | C52: =_xlfn.IFNA(VLOOKUP(A52,'Personnel List'!A$1:E$1284,4,FALSE),"") -> Minprovise | D52: =IF(A52<>"",IF(D52<>"",D52,NOW()),"") -> 45531.265 | E52: =IFERROR(VLOOKUP(A52,G:I,3,FALSE),"Onsite") -> Onsite | I52: =IF(G892<>"",IF(I52<>"",I52,NOW()),"") | J52: =SUBSTITUTE(A52,"NC","") -> 90118868 | L52: 0 | N52: =_xlfn.IFNA(VLOOKUP(A52,'Personnel List'!A$1:F$1284,6,FALSE),"") -> Jones, Cameron
A53: NC90107544 | B53: =_xlfn.IFNA(VLOOKUP(A53,'Personnel List'!A$1:E$1284,5,FALSE),"") -> Hohepa Tangiora | D53: =IF(A53<>"",IF(D53<>"",D53,NOW()),"") -> 45531.265 | E53: =IFERROR(VLOOKUP(A53,G:I,3,FALSE),"Onsite") -> Onsite | I53: =IF(G893<>"",IF(I53<>"",I53,NOW()),"") | J53: =SUBSTITUTE(A53,"NC","") -> 90107544 | L53: 0 | N53: =_xlfn.IFNA(VLOOKUP(A53,'Personnel List'!A$1:F$1284,6,FALSE),"") -> Tangiora, Hohepa
A54: NC90131908 | B54: =_xlfn.IFNA(VLOOKUP(A54,'Personnel List'!A$1:E$1284,5,FALSE),"") | D54: =IF(A54<>"",IF(D54<>"",D54,NOW()),"") -> 45531.265 | E54: =IFERROR(VLOOKUP(A54,G:I,3,FALSE),"Onsite") -> Onsite | I54: =IF(G894<>"",IF(I54<>"",I54,NOW()),"") | J54: =SUBSTITUTE(A54,"NC","") -> 90131908 | L54: 0 | N54: =_xlfn.IFNA(VLOOKUP(A54,'Personnel List'!A$1:F$1284,6,FALSE),"")
A55: NC21191 | B55: =_xlfn.IFNA(VLOOKUP(A55,'Personnel List'!A$1:E$1284,5,FALSE),"") -> Conner Souey | C55: =_xlfn.IFNA(VLOOKUP(A55,'Personnel List'!A$1:E$1284,4,FALSE),"") -> Newmont | D55: =IF(A55<>"",IF(D55<>"",D55,NOW()),"") -> 45531.265 | E55: =IFERROR(VLOOKUP(A55,G:I,3,FALSE),"Onsite") -> Onsite | I55: =IF(G895<>"",IF(I55<>"",I55,NOW()),"") | J55: =SUBSTITUTE(A55,"NC","") -> 21191 | L55: 0 | N55: =_xlfn.IFNA(VLOOKUP(A55,'Personnel List'!A$1:F$1284,6,FALSE),"") -> Souey, Conner
A56: NC16002 | B56: =_xlfn.IFNA(VLOOKUP(A56,'Personnel List'!A$1:E$1284,5,FALSE),"") -> Simon Sheehan | C56: =_xlfn.IFNA(VLOOKUP(A56,'Personnel List'!A$1:E$1284,4,FALSE),"") -> Newmont | D56: =IF(A56<>"",IF(D56<>"",D56,NOW()),"") -> 45531.265 | E56: =IFERROR(VLOOKUP(A56,G:I,3,FALSE),"Onsite") -> Onsite | I56: =IF(G896<>"",IF(I56<>"",I56,NOW()),"") | J56: =SUBSTITUTE(A56,"NC","") -> 16002 | L56: 0 | N56: =_xlfn.IFNA(VLOOKUP(A56,'Personnel List'!A$1:F$1284,6,FALSE),"") -> Sheehan, Simon
A57: NC4092 | B57: =_xlfn.IFNA(VLOOKUP(A57,'Personnel List'!A$1:E$1284,5,FALSE),"") -> Ben Harmsworth | C57: =_xlfn.IFNA(VLOOKUP(A57,'Personnel List'!A$1:E$1284,4,FALSE),"") -> Newmont | D57: =IF(A57<>"",IF(D57<>"",D57,NOW()),"") -> 45531.265 | E57: =IFERROR(VLOOKUP(A57,G:I,3,FALSE),"Onsite") -> Onsite | I57: =IF(G897<>"",IF(I57<>"",I57,NOW()),"") | J57: =SUBSTITUTE(A57,"NC","") -> 4092 | L57: 0 | N57: =_xlfn.IFNA(VLOOKUP(A57,'Personnel List'!A$1:F$1284,6,FALSE),"") -> Harmsworth, Ben
A58: NC23328 | B58: =_xlfn.IFNA(VLOOKUP(A58,'Personnel List'!A$1:E$1284,5,FALSE),"") -> Nicholas Chase | C58: =_xlfn.IFNA(VLOOKUP(A58,'Personnel List'!A$1:E$1284,4,FALSE),"") -> Newmont | D58: =IF(A58<>"",IF(D58<>"",D58,NOW()),"") -> 45531.29 | E58: =IFERROR(VLOOKUP(A58,G:I,3,FALSE),"Onsite") -> Onsite | I58: =IF(G898<>"",IF(I58<>"",I58,NOW()),"") | J58: =SUBSTITUTE(A58,"NC","") -> 23328 | L58: 0 | N58: =_xlfn.IFNA(VLOOKUP(A58,'Personnel List'!A$1:F$1284,6,FALSE),"") -> Chase, Nicholas
A59: NC24578 | B59: =_xlfn.IFNA(VLOOKUP(A59,'Personnel List'!A$1:E$1284,5,FALSE),"") -> Lachlan Edwards | C59: =_xlfn.IFNA(VLOOKUP(A59,'Personnel List'!A$1:E$1284,4,FALSE),"") -> Newmont | D59: =IF(A59<>"",IF(D59<>"",D59,NOW()),"") -> 45531.29 | E59: =IFERROR(VLOOKUP(A59,G:I,3,FALSE),"Onsite") -> Onsite | I59: =IF(G899<>"",IF(I59<>"",I59,NOW()),"") | J59: =SUBSTITUTE(A59,"NC","") -> 24578 | L59: 0 | N59: =_xlfn.IFNA(VLOOKUP(A59,'Personnel List'!A$1:F$1284,6,FALSE),"") -> Edwards, Lachlan
A60: NC23211 | B60: =_xlfn.IFNA(VLOOKUP(A60,'Personnel List'!A$1:E$1284,5,FALSE),"") -> Ben Weichert | C60: =_xlfn.IFNA(VLOOKUP(A60,'Personnel List'!A$1:E$1284,4,FALSE),"") -> Newmont | D60: =IF(A60<>"",IF(D60<>"",D60,NOW()),"") -> 45531.29 | E60: =IFERROR(VLOOKUP(A60,G:I,3,FALSE),"Onsite") -> Onsite | I60: =IF(G900<>"",IF(I60<>"",I60,NOW()),"") | J60: =SUBSTITUTE(A60,"NC","") -> 23211 | L60: 0 | N60: =_xlfn.IFNA(VLOOKUP(A60,'Personnel List'!A$1:F$1284,6,FALSE),"") -> Weichert, Ben
A61: NC5550 | B61: =_xlfn.IFNA(VLOOKUP(A61,'Personnel List'!A$1:E$1284,5,FALSE),"") -> Colin Brooking | C61: =_xlfn.IFNA(VLOOKUP(A61,'Personnel List'!A$1:E$1284,4,FALSE),"") -> Newmont | D61: =IF(A61<>"",IF(D61<>"",D61,NOW()),"") -> 45531.29 | E61: =IFERROR(VLOOKUP(A61,G:I,3,FALSE),"Onsite") -> Onsite | I61: =IF(G901<>"",IF(I61<>"",I61,NOW()),"") | J61: =SUBSTITUTE(A61,"NC","") -> 5550 | L61: 0 | N61: =_xlfn.IFNA(VLOOKUP(A61,'Personnel List'!A$1:F$1284,6,FALSE),"") -> Brooking, Colin
A62: NC24410 | B62: =_xlfn.IFNA(VLOOKUP(A62,'Personnel List'!A$1:E$1284,5,FALSE),"") -> Ilya Sujono | C62: =_xlfn.IFNA(VLOOKUP(A62,'Personnel List'!A$1:E$1284,4,FALSE),"") -> Newmont | D62: =IF(A62<>"",IF(D62<>"",D62,NOW()),"") -> 45531.29 | E62: =IFERROR(VLOOKUP(A62,G:I,3,FALSE),"Onsite") -> Onsite | I62: =IF(G902<>"",IF(I62<>"",I62,NOW()),"") | J62: =SUBSTITUTE(A62,"NC","") -> 24410 | L62: 0 | N62: =_xlfn.IFNA(VLOOKUP(A62,'Personnel List'!A$1:F$1284,6,FALSE),"") -> Sujono, Ilya
B63: =_xlfn.IFNA(VLOOKUP(A63,'Personnel List'!A$1:E$1284,5,FALSE),"") | C63: =_xlfn.IFNA(VLOOKUP(A63,'Personnel List'!A$1:E$1284,4,FALSE),"") | D63: =IF(A63<>"",IF(D63<>"",D63,NOW()),"") | E63: =IFERROR(VLOOKUP(A63,G:I,3,FALSE),"Onsite") -> Onsite | I63: =IF(G903<>"",IF(I63<>"",I63,NOW()),"") | J63: =SUBSTITUTE(A63,"NC","") | L63: 0 | N63: =_xlfn.IFNA(VLOOKUP(A63,'Personnel List'!A$1:F$1284,6,FALSE),"")
B64: =_xlfn.IFNA(VLOOKUP(A64,'Personnel List'!A$1:E$1284,5,FALSE),"") | C64: =_xlfn.IFNA(VLOOKUP(A64,'Personnel List'!A$1:E$1284,4,FALSE),"") | D64: =IF(A64<>"",IF(D64<>"",D64,NOW()),"") | E64: =IFERROR(VLOOKUP(A64,G:I,3,FALSE),"Onsite") -> Onsite | I64: =IF(G904<>"",IF(I64<>"",I64,NOW()),"") | J64: =SUBSTITUTE(A64,"NC","") | L64: 0 | N64: =_xlfn.IFNA(VLOOKUP(A64,'Personnel List'!A$1:F$1284,6,FALSE),"")
B65: =_xlfn.IFNA(VLOOKUP(A65,'Personnel List'!A$1:E$1284,5,FALSE),"") | C65: =_xlfn.IFNA(VLOOKUP(A65,'Personnel List'!A$1:E$1284,4,FALSE),"") | D65: =IF(A65<>"",IF(D65<>"",D65,NOW()),"") | E65: =IFERROR(VLOOKUP(A65,G:I,3,FALSE),"Onsite") -> Onsite | I65: =IF(G905<>"",IF(I65<>"",I65,NOW()),"") | J65: =SUBSTITUTE(A65,"NC","") | L65: 0 | N65: =_xlfn.IFNA(VLOOKUP(A65,'Personnel List'!A$1:F$1284,6,FALSE),"")
B66: =_xlfn.IFNA(VLOOKUP(A66,'Personnel List'!A$1:E$1284,5,FALSE),"") | C66: =_xlfn.IFNA(VLOOKUP(A66,'Personnel List'!A$1:E$1284,4,FALSE),"") | D66: =IF(A66<>"",IF(D66<>"",D66,NOW()),"") | E66: =IFERROR(VLOOKUP(A66,G:I,3,FALSE),"Onsite") -> Onsite | I66: =IF(G906<>"",IF(I66<>"",I66,NOW()),"") | J66: =SUBSTITUTE(A66,"NC","") | L66: 0 | N66: =_xlfn.IFNA(VLOOKUP(A66,'Personnel List'!A$1:F$1284,6,FALSE),"")
B67: =_xlfn.IFNA(VLOOKUP(A67,'Personnel List'!A$1:E$1284,5,FALSE),"") | C67: =_xlfn.IFNA(VLOOKUP(A67,'Personnel List'!A$1:E$1284,4,FALSE),"") | D67: =IF(A67<>"",IF(D67<>"",D67,NOW()),"") | E67: =IFERROR(VLOOKUP(A67,G:I,3,FALSE),"Onsite") -> Onsite | I67: =IF(G907<>"",IF(I67<>"",I67,NOW()),"") | J67: =SUBSTITUTE(A67,"NC","") | L67: 0 | N67: =_xlfn.IFNA(VLOOKUP(A67,'Personnel List'!A$1:F$1284,6,FALSE),"")
B68: =_xlfn.IFNA(VLOOKUP(A68,'Personnel List'!A$1:E$1284,5,FALSE),"") | C68: =_xlfn.IFNA(VLOOKUP(A68,'Personnel List'!A$1:E$1284,4,FALSE),"") | D68: =IF(A68<>"",IF(D68<>"",D68,NOW()),"") | E68: =IFERROR(VLOOKUP(A68,G:I,3,FALSE),"Onsite") -> Onsite | I68: =IF(G908<>"",IF(I68<>"",I68,NOW()),"") | J68: =SUBSTITUTE(A68,"NC","") | L68: 0 | N68: =_xlfn.IFNA(VLOOKUP(A68,'Personnel List'!A$1:F$1284,6,FALSE),"")
B69: =_xlfn.IFNA(VLOOKUP(A69,'Personnel List'!A$1:E$1284,5,FALSE),"") | C69: =_xlfn.IFNA(VLOOKUP(A69,'Personnel List'!A$1:E$1284,4,FALSE),"") | D69: =IF(A69<>"",IF(D69<>"",D69,NOW()),"") | E69: =IFERROR(VLOOKUP(A69,G:I,3,FALSE),"Onsite") -> Onsite | I69: =IF(G909<>"",IF(I69<>"",I69,NOW()),"") | J69: =SUBSTITUTE(A69,"NC","") | L69: 0 | N69: =_xlfn.IFNA(VLOOKUP(A69,'Personnel List'!A$1:F$1284,6,FALSE),"")
B70: =_xlfn.IFNA(VLOOKUP(A70,'Personnel List'!A$1:E$1284,5,FALSE),"") | C70: =_xlfn.IFNA(VLOOKUP(A70,'Personnel List'!A$1:E$1284,4,FALSE),"") | D70: =IF(A70<>"",IF(D70<>"",D70,NOW()),"") | E70: =IFERROR(VLOOKUP(A70,G:I,3,FALSE),"Onsite") -> Onsite | I70: =IF(G910<>"",IF(I70<>"",I70,NOW()),"") | J70: =SUBSTITUTE(A70,"NC","") | L70: 0 | N70: =_xlfn.IFNA(VLOOKUP(A70,'Personnel List'!A$1:F$1284,6,FALSE),"")
B71: =_xlfn.IFNA(VLOOKUP(A71,'Personnel List'!A$1:E$1284,5,FALSE),"") | C71: =_xlfn.IFNA(VLOOKUP(A71,'Personnel List'!A$1:E$1284,4,FALSE),"") | D71: =IF(A71<>"",IF(D71<>"",D71,NOW()),"") | E71: =IFERROR(VLOOKUP(A71,G:I,3,FALSE),"Onsite") -> Onsite | I71: =IF(G911<>"",IF(I71<>"",I71,NOW()),"") | J71: =SUBSTITUTE(A71,"NC","") | L71: 0 | N71: =_xlfn.IFNA(VLOOKUP(A71,'Personnel List'!A$1:F$1284,6,FALSE),"")
B72: =_xlfn.IFNA(VLOOKUP(A72,'Personnel List'!A$1:E$1284,5,FALSE),"") | C72: =_xlfn.IFNA(VLOOKUP(A72,'Personnel List'!A$1:E$1284,4,FALSE),"") | D72: =IF(A72<>"",IF(D72<>"",D72,NOW()),"") | E72: =IFERROR(VLOOKUP(A72,G:I,3,FALSE),"Onsite") -> Onsite | I72: =IF(G912<>"",IF(I72<>"",I72,NOW()),"") | J72: =SUBSTITUTE(A72,"NC","") | L72: 0 | N72: =_xlfn.IFNA(VLOOKUP(A72,'Personnel List'!A$1:F$1284,6,FALSE),"")
B73: =_xlfn.IFNA(VLOOKUP(A73,'Personnel List'!A$1:E$1284,5,FALSE),"") | C73: =_xlfn.IFNA(VLOOKUP(A73,'Personnel List'!A$1:E$1284,4,FALSE),"") | D73: =IF(A73<>"",IF(D73<>"",D73,NOW()),"") | E73: =IFERROR(VLOOKUP(A73,G:I,3,FALSE),"Onsite") -> Onsite | I73: =IF(G913<>"",IF(I73<>"",I73,NOW()),"") | J73: =SUBSTITUTE(A73,"NC","") | L73: 0 | N73: =_xlfn.IFNA(VLOOKUP(A73,'Personnel List'!A$1:F$1284,6,FALSE),"")
B74: =_xlfn.IFNA(VLOOKUP(A74,'Personnel List'!A$1:E$1284,5,FALSE),"") | C74: =_xlfn.IFNA(VLOOKUP(A74,'Personnel List'!A$1:E$1284,4,FALSE),"") | D74: =IF(A74<>"",IF(D74<>"",D74,NOW()),"") | E74: =IFERROR(VLOOKUP(A74,G:I,3,FALSE),"Onsite") -> Onsite | I74: =IF(G914<>"",IF(I74<>"",I74,NOW()),"") | J74: =SUBSTITUTE(A74,"NC","") | L74: 0 | N74: =_xlfn.IFNA(VLOOKUP(A74,'Personnel List'!A$1:F$1284,6,FALSE),"")
... B876: =_xlfn.IFNA(VLOOKUP(A876,'Personnel List'!A$1:E$1284,5,FALSE),"") | C876: =_xlfn.IFNA(VLOOKUP(A876,'Personnel List'!A$1:E$1284,4,FALSE),"") | D876: =IF(A876<>"",IF(D876<>"",D876,NOW()),"") | E876: =IFERROR(VLOOKUP(A876,G:I,3,FALSE),"Onsite") -> Onsite | I876: =IF(G1716<>"",IF(I876<>"",I876,NOW()),"") | J876: =SUBSTITUTE(A876,"NC","") | L876: 0 | N876: =_xlfn.IFNA(VLOOKUP(A876,'Personnel List'!A$1:F$1284,6,FALSE),"")
I877: =IF(G1717<>"",IF(I877<>"",I877,NOW()),"") | J877: =SUBSTITUTE(A877,"NC","") | L877: 0
L878: 0
L879: 0
L880: 0
L881: 0
L882: 0
L883: 0
L884: 0
L885: 0
L886: 0
L887: 0
L888: 0
L889: 0
... L999: 0

Sheet Tue NS
A1: Scan ID | B1: Name | C1: Company Name | D1: Time In | E1: Time Out | G1: Scan Out | I1: Timestamp | J1: SAP Number | L1: Not Scanned Yet | M1: NS | N1: Reverse Name
B2: =_xlfn.IFNA(VLOOKUP(A2,'Personnel List'!A$1:E$1284,5,FALSE),"") | C2: =_xlfn.IFNA(VLOOKUP(A2,'Personnel List'!A$1:E$1284,4,FALSE),"") | D2: =IF(A2<>"",IF(D2<>"",D2,NOW()),"") | E2: =IFERROR(VLOOKUP(A2,G:I,3,FALSE),"Onsite") -> Onsite | I2: =IF(G2<>"",IF(I2<>"",I2,NOW()),"") | J2: =SUBSTITUTE(A2,"NC","") | L2: {=_xlfn._xlws.FILTER(M2:M1000,(ISNA(MATCH(M2:M1000,N2:N1000,0))),"")} -> 0 | M2: {=_xlfn._xlws.FILTER('Tue Data'!E13:E786,ISNUMBER(_xlfn.XMATCH('Tue Data'!D13:D786,M1)))} -> #VALUE! | N2: =_xlfn.IFNA(VLOOKUP(A2,'Personnel List'!A$1:F$1284,6,FALSE),"")
B3: =_xlfn.IFNA(VLOOKUP(A3,'Personnel List'!A$1:E$1284,5,FALSE),"") | C3: =_xlfn.IFNA(VLOOKUP(A3,'Personnel List'!A$1:E$1284,4,FALSE),"") | D3: =IF(A3<>"",IF(D3<>"",D3,NOW()),"") | E3: =IFERROR(VLOOKUP(A3,G:I,3,FALSE),"Onsite") -> Onsite | I3: =IF(G3<>"",IF(I3<>"",I3,NOW()),"") | J3: =SUBSTITUTE(A3,"NC","") | L3: 0 | N3: =_xlfn.IFNA(VLOOKUP(A3,'Personnel List'!A$1:F$1284,6,FALSE),"")
B4: =_xlfn.IFNA(VLOOKUP(A4,'Personnel List'!A$1:E$1284,5,FALSE),"") | C4: =_xlfn.IFNA(VLOOKUP(A4,'Personnel List'!A$1:E$1284,4,FALSE),"") | D4: =IF(A4<>"",IF(D4<>"",D4,NOW()),"") | E4: =IFERROR(VLOOKUP(A4,G:I,3,FALSE),"Onsite") -> Onsite | I4: =IF(G4<>"",IF(I4<>"",I4,NOW()),"") | J4: =SUBSTITUTE(A4,"NC","") | L4: 0 | N4: =_xlfn.IFNA(VLOOKUP(A4,'Personnel List'!A$1:F$1284,6,FALSE),"")
B5: =_xlfn.IFNA(VLOOKUP(A5,'Personnel List'!A$1:E$1284,5,FALSE),"") | C5: =_xlfn.IFNA(VLOOKUP(A5,'Personnel List'!A$1:E$1284,4,FALSE),"") | D5: =IF(A5<>"",IF(D5<>"",D5,NOW()),"") | E5: =IFERROR(VLOOKUP(A5,G:I,3,FALSE),"Onsite") -> Onsite | I5: =IF(G5<>"",IF(I5<>"",I5,NOW()),"") | J5: =SUBSTITUTE(A5,"NC","") | L5: 0 | N5: =_xlfn.IFNA(VLOOKUP(A5,'Personnel List'!A$1:F$1284,6,FALSE),"")
B6: =_xlfn.IFNA(VLOOKUP(A6,'Personnel List'!A$1:E$1284,5,FALSE),"") | C6: =_xlfn.IFNA(VLOOKUP(A6,'Personnel List'!A$1:E$1284,4,FALSE),"") | D6: =IF(A6<>"",IF(D6<>"",D6,NOW()),"") | E6: =IFERROR(VLOOKUP(A6,G:I,3,FALSE),"Onsite") -> Onsite | I6: =IF(G6<>"",IF(I6<>"",I6,NOW()),"") | J6: =SUBSTITUTE(A6,"NC","") | L6: 0 | N6: =_xlfn.IFNA(VLOOKUP(A6,'Personnel List'!A$1:F$1284,6,FALSE),"")
B7: =_xlfn.IFNA(VLOOKUP(A7,'Personnel List'!A$1:E$1284,5,FALSE),"") | C7: =_xlfn.IFNA(VLOOKUP(A7,'Personnel List'!A$1:E$1284,4,FALSE),"") | D7: =IF(A7<>"",IF(D7<>"",D7,NOW()),"") | E7: =IFERROR(VLOOKUP(A7,G:I,3,FALSE),"Onsite") -> Onsite | I7: =IF(G7<>"",IF(I7<>"",I7,NOW()),"") | J7: =SUBSTITUTE(A7,"NC","") | L7: 0 | N7: =_xlfn.IFNA(VLOOKUP(A7,'Personnel List'!A$1:F$1284,6,FALSE),"")
B8: =_xlfn.IFNA(VLOOKUP(A8,'Personnel List'!A$1:E$1284,5,FALSE),"") | C8: =_xlfn.IFNA(VLOOKUP(A8,'Personnel List'!A$1:E$1284,4,FALSE),"") | D8: =IF(A8<>"",IF(D8<>"",D8,NOW()),"") | E8: =IFERROR(VLOOKUP(A8,G:I,3,FALSE),"Onsite") -> Onsite | I8: =IF(G8<>"",IF(I8<>"",I8,NOW()),"") | J8: =SUBSTITUTE(A8,"NC","") | L8: 0 | N8: =_xlfn.IFNA(VLOOKUP(A8,'Personnel List'!A$1:F$1284,6,FALSE),"")
B9: =_xlfn.IFNA(VLOOKUP(A9,'Personnel List'!A$1:E$1284,5,FALSE),"") | C9: =_xlfn.IFNA(VLOOKUP(A9,'Personnel List'!A$1:E$1284,4,FALSE),"") | D9: =IF(A9<>"",IF(D9<>"",D9,NOW()),"") | E9: =IFERROR(VLOOKUP(A9,G:I,3,FALSE),"Onsite") -> Onsite | I9: =IF(G9<>"",IF(I9<>"",I9,NOW()),"") | J9: =SUBSTITUTE(A9,"NC","") | L9: 0 | N9: =_xlfn.IFNA(VLOOKUP(A9,'Personnel List'!A$1:F$1284,6,FALSE),"")
B10: =_xlfn.IFNA(VLOOKUP(A10,'Personnel List'!A$1:E$1284,5,FALSE),"") | C10: =_xlfn.IFNA(VLOOKUP(A10,'Personnel List'!A$1:E$1284,4,FALSE),"") | D10: =IF(A10<>"",IF(D10<>"",D10,NOW()),"") | E10: =IFERROR(VLOOKUP(A10,G:I,3,FALSE),"Onsite") -> Onsite | I10: =IF(G10<>"",IF(I10<>"",I10,NOW()),"") | J10: =SUBSTITUTE(A10,"NC","") | L10: 0 | N10: =_xlfn.IFNA(VLOOKUP(A10,'Personnel List'!A$1:F$1284,6,FALSE),"")
B11: =_xlfn.IFNA(VLOOKUP(A11,'Personnel List'!A$1:E$1284,5,FALSE),"") | C11: =_xlfn.IFNA(VLOOKUP(A11,'Personnel List'!A$1:E$1284,4,FALSE),"") | D11: =IF(A11<>"",IF(D11<>"",D11,NOW()),"") | E11: =IFERROR(VLOOKUP(A11,G:I,3,FALSE),"Onsite") -> Onsite | I11: =IF(G11<>"",IF(I11<>"",I11,NOW()),"") | J11: =SUBSTITUTE(A11,"NC","") | L11: 0 | N11: =_xlfn.IFNA(VLOOKUP(A11,'Personnel List'!A$1:F$1284,6,FALSE),"")
B12: =_xlfn.IFNA(VLOOKUP(A12,'Personnel List'!A$1:E$1284,5,FALSE),"") | C12: =_xlfn.IFNA(VLOOKUP(A12,'Personnel List'!A$1:E$1284,4,FALSE),"") | D12: =IF(A12<>"",IF(D12<>"",D12,NOW()),"") | E12: =IFERROR(VLOOKUP(A12,G:I,3,FALSE),"Onsite") -> Onsite | I12: =IF(G12<>"",IF(I12<>"",I12,NOW()),"") | J12: =SUBSTITUTE(A12,"NC","") | L12: 0 | N12: =_xlfn.IFNA(VLOOKUP(A12,'Personnel List'!A$1:F$1284,6,FALSE),"")
B13: =_xlfn.IFNA(VLOOKUP(A13,'Personnel List'!A$1:E$1284,5,FALSE),"") | C13: =_xlfn.IFNA(VLOOKUP(A13,'Personnel List'!A$1:E$1284,4,FALSE),"") | D13: =IF(A13<>"",IF(D13<>"",D13,NOW()),"") | E13: =IFERROR(VLOOKUP(A13,G:I,3,FALSE),"Onsite") -> Onsite | I13: =IF(G13<>"",IF(I13<>"",I13,NOW()),"") | J13: =SUBSTITUTE(A13,"NC","") | L13: 0 | N13: =_xlfn.IFNA(VLOOKUP(A13,'Personnel List'!A$1:F$1284,6,FALSE),"")
B14: =_xlfn.IFNA(VLOOKUP(A14,'Personnel List'!A$1:E$1284,5,FALSE),"") | C14: =_xlfn.IFNA(VLOOKUP(A14,'Personnel List'!A$1:E$1284,4,FALSE),"") | D14: =IF(A14<>"",IF(D14<>"",D14,NOW()),"") | E14: =IFERROR(VLOOKUP(A14,G:I,3,FALSE),"Onsite") -> Onsite | I14: =IF(G14<>"",IF(I14<>"",I14,NOW()),"") | J14: =SUBSTITUTE(A14,"NC","") | L14: 0 | N14: =_xlfn.IFNA(VLOOKUP(A14,'Personnel List'!A$1:F$1284,6,FALSE),"")
... B32: =_xlfn.IFNA(VLOOKUP(A32,'Personnel List'!A$1:E$1284,5,FALSE),"") | C32: =_xlfn.IFNA(VLOOKUP(A32,'Personnel List'!A$1:E$1284,4,FALSE),"") | D32: =IF(A32<>"",IF(D32<>"",D32,NOW()),"") | E32: =IFERROR(VLOOKUP(A32,G:I,3,FALSE),"Onsite") -> Onsite | I32: =IF(G32<>"",IF(I32<>"",I32,NOW()),"") | J32: =SUBSTITUTE(A32,"NC","") | L32: 0 | N32: =_xlfn.IFNA(VLOOKUP(A32,'Personnel List'!A$1:F$1284,6,FALSE),"")
B33: =_xlfn.IFNA(VLOOKUP(A33,'Personnel List'!A$1:E$1284,5,FALSE),"") | E33: =IFERROR(VLOOKUP(A33,G:I,3,FALSE),"Onsite") -> Onsite | I33: =IF(G33<>"",IF(I33<>"",I33,NOW()),"") | J33: =SUBSTITUTE(A33,"NC","") | L33: 0 | N33: =_xlfn.IFNA(VLOOKUP(A33,'Personnel List'!A$1:F$1284,6,FALSE),"")
B34: =_xlfn.IFNA(VLOOKUP(A34,'Personnel List'!A$1:E$1284,5,FALSE),"") | C34: =_xlfn.IFNA(VLOOKUP(A34,'Personnel List'!A$1:E$1284,4,FALSE),"") | D34: =IF(A34<>"",IF(D34<>"",D34,NOW()),"") | E34: =IFERROR(VLOOKUP(A34,G:I,3,FALSE),"Onsite") -> Onsite | I34: =IF(G34<>"",IF(I34<>"",I34,NOW()),"") | J34: =SUBSTITUTE(A34,"NC","") | L34: 0 | N34: =_xlfn.IFNA(VLOOKUP(A34,'Personnel List'!A$1:F$1284,6,FALSE),"")
B35: =_xlfn.IFNA(VLOOKUP(A35,'Personnel List'!A$1:E$1284,5,FALSE),"") | C35: =_xlfn.IFNA(VLOOKUP(A35,'Personnel List'!A$1:E$1284,4,FALSE),"") | D35: =IF(A35<>"",IF(D35<>"",D35,NOW()),"") | E35: =IFERROR(VLOOKUP(A35,G:I,3,FALSE),"Onsite") -> Onsite | I35: =IF(G35<>"",IF(I35<>"",I35,NOW()),"") | J35: =SUBSTITUTE(A35,"NC","") | L35: 0 | N35: =_xlfn.IFNA(VLOOKUP(A35,'Personnel List'!A$1:F$1284,6,FALSE),"")
B36: =_xlfn.IFNA(VLOOKUP(A36,'Personnel List'!A$1:E$1284,5,FALSE),"") | C36: =_xlfn.IFNA(VLOOKUP(A36,'Personnel List'!A$1:E$1284,4,FALSE),"") | D36: =IF(A36<>"",IF(D36<>"",D36,NOW()),"") | E36: =IFERROR(VLOOKUP(A36,G:I,3,FALSE),"Onsite") -> Onsite | I36: =IF(G36<>"",IF(I36<>"",I36,NOW()),"") | J36: =SUBSTITUTE(A36,"NC","") | L36: 0 | N36: =_xlfn.IFNA(VLOOKUP(A36,'Personnel List'!A$1:F$1284,6,FALSE),"")
B37: =_xlfn.IFNA(VLOOKUP(A37,'Personnel List'!A$1:E$1284,5,FALSE),"") | C37: =_xlfn.IFNA(VLOOKUP(A37,'Personnel List'!A$1:E$1284,4,FALSE),"") | D37: =IF(A37<>"",IF(D37<>"",D37,NOW()),"") | E37: =IFERROR(VLOOKUP(A37,G:I,3,FALSE),"Onsite") -> Onsite | I37: =IF(G37<>"",IF(I37<>"",I37,NOW()),"") | J37: =SUBSTITUTE(A37,"NC","") | L37: 0 | N37: =_xlfn.IFNA(VLOOKUP(A37,'Personnel List'!A$1:F$1284,6,FALSE),"")
B38: =_xlfn.IFNA(VLOOKUP(A38,'Personnel List'!A$1:E$1284,5,FALSE),"") | C38: =_xlfn.IFNA(VLOOKUP(A38,'Personnel List'!A$1:E$1284,4,FALSE),"") | D38: =IF(A38<>"",IF(D38<>"",D38,NOW()),"") | E38: =IFERROR(VLOOKUP(A38,G:I,3,FALSE),"Onsite") -> Onsite | I38: =IF(G38<>"",IF(I38<>"",I38,NOW()),"") | J38: =SUBSTITUTE(A38,"NC","") | L38: 0 | N38: =_xlfn.IFNA(VLOOKUP(A38,'Personnel List'!A$1:F$1284,6,FALSE),"")
B39: =_xlfn.IFNA(VLOOKUP(A39,'Personnel List'!A$1:E$1284,5,FALSE),"") | C39: =_xlfn.IFNA(VLOOKUP(A39,'Personnel List'!A$1:E$1284,4,FALSE),"") | D39: =IF(A39<>"",IF(D39<>"",D39,NOW()),"") | E39: =IFERROR(VLOOKUP(A39,G:I,3,FALSE),"Onsite") -> Onsite | I39: =IF(G39<>"",IF(I39<>"",I39,NOW()),"") | J39: =SUBSTITUTE(A39,"NC","") | L39: 0 | N39: =_xlfn.IFNA(VLOOKUP(A39,'Personnel List'!A$1:F$1284,6,FALSE),"")
B40: =_xlfn.IFNA(VLOOKUP(A40,'Personnel List'!A$1:E$1284,5,FALSE),"") | C40: =_xlfn.IFNA(VLOOKUP(A40,'Personnel List'!A$1:E$1284,4,FALSE),"") | D40: =IF(A40<>"",IF(D40<>"",D40,NOW()),"") | E40: =IFERROR(VLOOKUP(A40,G:I,3,FALSE),"Onsite") -> Onsite | I40: =IF(G40<>"",IF(I40<>"",I40,NOW()),"") | J40: =SUBSTITUTE(A40,"NC","") | L40: 0 | N40: =_xlfn.IFNA(VLOOKUP(A40,'Personnel List'!A$1:F$1284,6,FALSE),"")
D41: =IF(A41<>"",IF(D41<>"",D41,NOW()),"") | E41: =IFERROR(VLOOKUP(A41,G:I,3,FALSE),"Onsite") -> Onsite | I41: =IF(G41<>"",IF(I41<>"",I41,NOW()),"") | J41: =SUBSTITUTE(A41,"NC","") | L41: 0 | N41: =_xlfn.IFNA(VLOOKUP(A41,'Personnel List'!A$1:F$1284,6,FALSE),"")
B42: =_xlfn.IFNA(VLOOKUP(A42,'Personnel List'!A$1:E$1284,5,FALSE),"") | C42: =_xlfn.IFNA(VLOOKUP(A42,'Personnel List'!A$1:E$1284,4,FALSE),"") | D42: =IF(A42<>"",IF(D42<>"",D42,NOW()),"") | E42: =IFERROR(VLOOKUP(A42,G:I,3,FALSE),"Onsite") -> Onsite | I42: =IF(G42<>"",IF(I42<>"",I42,NOW()),"") | J42: =SUBSTITUTE(A42,"NC","") | L42: 0 | N42: =_xlfn.IFNA(VLOOKUP(A42,'Personnel List'!A$1:F$1284,6,FALSE),"")
B43: =_xlfn.IFNA(VLOOKUP(A43,'Personnel List'!A$1:E$1284,5,FALSE),"") | C43: =_xlfn.IFNA(VLOOKUP(A43,'Personnel List'!A$1:E$1284,4,FALSE),"") | D43: =IF(A43<>"",IF(D43<>"",D43,NOW()),"") | E43: =IFERROR(VLOOKUP(A43,G:I,3,FALSE),"Onsite") -> Onsite | I43: =IF(G43<>"",IF(I43<>"",I43,NOW()),"") | J43: =SUBSTITUTE(A43,"NC","") | L43: 0 | N43: =_xlfn.IFNA(VLOOKUP(A43,'Personnel List'!A$1:F$1284,6,FALSE),"")
B44: =_xlfn.IFNA(VLOOKUP(A44,'Personnel List'!A$1:E$1284,5,FALSE),"") | C44: =_xlfn.IFNA(VLOOKUP(A44,'Personnel List'!A$1:E$1284,4,FALSE),"") | D44: =IF(A44<>"",IF(D44<>"",D44,NOW()),"") | E44: =IFERROR(VLOOKUP(A44,G:I,3,FALSE),"Onsite") -> Onsite | I44: =IF(G44<>"",IF(I44<>"",I44,NOW()),"") | J44: =SUBSTITUTE(A44,"NC","") | L44: 0 | N44: =_xlfn.IFNA(VLOOKUP(A44,'Personnel List'!A$1:F$1284,6,FALSE),"")
B45: =_xlfn.IFNA(VLOOKUP(A45,'Personnel List'!A$1:E$1284,5,FALSE),"") | C45: =_xlfn.IFNA(VLOOKUP(A45,'Personnel List'!A$1:E$1284,4,FALSE),"") | D45: =IF(A45<>"",IF(D45<>"",D45,NOW()),"") | E45: =IFERROR(VLOOKUP(A45,G:I,3,FALSE),"Onsite") -> Onsite | I45: =IF(G45<>"",IF(I45<>"",I45,NOW()),"") | J45: =SUBSTITUTE(A45,"NC","") | L45: 0 | N45: =_xlfn.IFNA(VLOOKUP(A45,'Personnel List'!A$1:F$1284,6,FALSE),"")
B46: =_xlfn.IFNA(VLOOKUP(A46,'Personnel List'!A$1:E$1284,5,FALSE),"") | C46: =_xlfn.IFNA(VLOOKUP(A46,'Personnel List'!A$1:E$1284,4,FALSE),"") | D46: =IF(A46<>"",IF(D46<>"",D46,NOW()),"") | E46: =IFERROR(VLOOKUP(A46,G:I,3,FALSE),"Onsite") -> Onsite | I46: =IF(G886<>"",IF(I46<>"",I46,NOW()),"") | J46: =SUBSTITUTE(A46,"NC","") | L46: 0 | N46: =_xlfn.IFNA(VLOOKUP(A46,'Personnel List'!A$1:F$1284,6,FALSE),"")
B47: =_xlfn.IFNA(VLOOKUP(A47,'Personnel List'!A$1:E$1284,5,FALSE),"") | C47: =_xlfn.IFNA(VLOOKUP(A47,'Personnel List'!A$1:E$1284,4,FALSE),"") | D47: =IF(A47<>"",IF(D47<>"",D47,NOW()),"") | E47: =IFERROR(VLOOKUP(A47,G:I,3,FALSE),"Onsite") -> Onsite | I47: =IF(G887<>"",IF(I47<>"",I47,NOW()),"") | J47: =SUBSTITUTE(A47,"NC","") | L47: 0 | N47: =_xlfn.IFNA(VLOOKUP(A47,'Personnel List'!A$1:F$1284,6,FALSE),"")
B48: =_xlfn.IFNA(VLOOKUP(A48,'Personnel List'!A$1:E$1284,5,FALSE),"") | C48: =_xlfn.IFNA(VLOOKUP(A48,'Personnel List'!A$1:E$1284,4,FALSE),"") | D48: =IF(A48<>"",IF(D48<>"",D48,NOW()),"") | E48: =IFERROR(VLOOKUP(A48,G:I,3,FALSE),"Onsite") -> Onsite | I48: =IF(G888<>"",IF(I48<>"",I48,NOW()),"") | J48: =SUBSTITUTE(A48,"NC","") | L48: 0 | N48: =_xlfn.IFNA(VLOOKUP(A48,'Personnel List'!A$1:F$1284,6,FALSE),"")
B49: =_xlfn.IFNA(VLOOKUP(A49,'Personnel List'!A$1:E$1284,5,FALSE),"") | C49: =_xlfn.IFNA(VLOOKUP(A49,'Personnel List'!A$1:E$1284,4,FALSE),"") | D49: =IF(A49<>"",IF(D49<>"",D49,NOW()),"") | E49: =IFERROR(VLOOKUP(A49,G:I,3,FALSE),"Onsite") -> Onsite | I49: =IF(G889<>"",IF(I49<>"",I49,NOW()),"") | J49: =SUBSTITUTE(A49,"NC","") | L49: 0 | N49: =_xlfn.IFNA(VLOOKUP(A49,'Personnel List'!A$1:F$1284,6,FALSE),"")
B50: =_xlfn.IFNA(VLOOKUP(A50,'Personnel List'!A$1:E$1284,5,FALSE),"") | C50: =_xlfn.IFNA(VLOOKUP(A50,'Personnel List'!A$1:E$1284,4,FALSE),"") | D50: =IF(A50<>"",IF(D50<>"",D50,NOW()),"") | E50: =IFERROR(VLOOKUP(A50,G:I,3,FALSE),"Onsite") -> Onsite | I50: =IF(G890<>"",IF(I50<>"",I50,NOW()),"") | J50: =SUBSTITUTE(A50,"NC","") | L50: 0 | N50: =_xlfn.IFNA(VLOOKUP(A50,'Personnel List'!A$1:F$1284,6,FALSE),"")
B51: =_xlfn.IFNA(VLOOKUP(A51,'Personnel List'!A$1:E$1284,5,FALSE),"") | C51: =_xlfn.IFNA(VLOOKUP(A51,'Personnel List'!A$1:E$1284,4,FALSE),"") | D51: =IF(A51<>"",IF(D51<>"",D51,NOW()),"") | E51: =IFERROR(VLOOKUP(A51,G:I,3,FALSE),"Onsite") -> Onsite | I51: =IF(G891<>"",IF(I51<>"",I51,NOW()),"") | J51: =SUBSTITUTE(A51,"NC","") | L51: 0 | N51: =_xlfn.IFNA(VLOOKUP(A51,'Personnel List'!A$1:F$1284,6,FALSE),"")
B52: =_xlfn.IFNA(VLOOKUP(A52,'Personnel List'!A$1:E$1284,5,FALSE),"") | C52: =_xlfn.IFNA(VLOOKUP(A52,'Personnel List'!A$1:E$1284,4,FALSE),"") | D52: =IF(A52<>"",IF(D52<>"",D52,NOW()),"") | E52: =IFERROR(VLOOKUP(A52,G:I,3,FALSE),"Onsite") -> Onsite | I52: =IF(G892<>"",IF(I52<>"",I52,NOW()),"") | J52: =SUBSTITUTE(A52,"NC","") | L52: 0 | N52: =_xlfn.IFNA(VLOOKUP(A52,'Personnel List'!A$1:F$1284,6,FALSE),"")
B53: =_xlfn.IFNA(VLOOKUP(A53,'Personnel List'!A$1:E$1284,5,FALSE),"") | D53: =IF(A53<>"",IF(D53<>"",D53,NOW()),"") | E53: =IFERROR(VLOOKUP(A53,G:I,3,FALSE),"Onsite") -> Onsite | I53: =IF(G893<>"",IF(I53<>"",I53,NOW()),"") | J53: =SUBSTITUTE(A53,"NC","") | L53: 0 | N53: =_xlfn.IFNA(VLOOKUP(A53,'Personnel List'!A$1:F$1284,6,FALSE),"")
B54: =_xlfn.IFNA(VLOOKUP(A54,'Personnel List'!A$1:E$1284,5,FALSE),"") | D54: =IF(A54<>"",IF(D54<>"",D54,NOW()),"") | E54: =IFERROR(VLOOKUP(A54,G:I,3,FALSE),"Onsite") -> Onsite | I54: =IF(G894<>"",IF(I54<>"",I54,NOW()),"") | J54: =SUBSTITUTE(A54,"NC","") | L54: 0 | N54: =_xlfn.IFNA(VLOOKUP(A54,'Personnel List'!A$1:F$1284,6,FALSE),"")
B55: =_xlfn.IFNA(VLOOKUP(A55,'Personnel List'!A$1:E$1284,5,FALSE),"") | C55: =_xlfn.IFNA(VLOOKUP(A55,'Personnel List'!A$1:E$1284,4,FALSE),"") | D55: =IF(A55<>"",IF(D55<>"",D55,NOW()),"") | E55: =IFERROR(VLOOKUP(A55,G:I,3,FALSE),"Onsite") -> Onsite | I55: =IF(G895<>"",IF(I55<>"",I55,NOW()),"") | J55: =SUBSTITUTE(A55,"NC","") | L55: 0 | N55: =_xlfn.IFNA(VLOOKUP(A55,'Personnel List'!A$1:F$1284,6,FALSE),"")
B56: =_xlfn.IFNA(VLOOKUP(A56,'Personnel List'!A$1:E$1284,5,FALSE),"") | C56: =_xlfn.IFNA(VLOOKUP(A56,'Personnel List'!A$1:E$1284,4,FALSE),"") | D56: =IF(A56<>"",IF(D56<>"",D56,NOW()),"") | E56: =IFERROR(VLOOKUP(A56,G:I,3,FALSE),"Onsite") -> Onsite | I56: =IF(G896<>"",IF(I56<>"",I56,NOW()),"") | J56: =SUBSTITUTE(A56,"NC","") | L56: 0 | N56: =_xlfn.IFNA(VLOOKUP(A56,'Personnel List'!A$1:F$1284,6,FALSE),"")
B57: =_xlfn.IFNA(VLOOKUP(A57,'Personnel List'!A$1:E$1284,5,FALSE),"") | C57: =_xlfn.IFNA(VLOOKUP(A57,'Personnel List'!A$1:E$1284,4,FALSE),"") | D57: =IF(A57<>"",IF(D57<>"",D57,NOW()),"") | E57: =IFERROR(VLOOKUP(A57,G:I,3,FALSE),"Onsite") -> Onsite | I57: =IF(G897<>"",IF(I57<>"",I57,NOW()),"") | J57: =SUBSTITUTE(A57,"NC","") | L57: 0 | N57: =_xlfn.IFNA(VLOOKUP(A57,'Personnel List'!A$1:F$1284,6,FALSE),"")
B58: =_xlfn.IFNA(VLOOKUP(A58,'Personnel List'!A$1:E$1284,5,FALSE),"") | C58: =_xlfn.IFNA(VLOOKUP(A58,'Personnel List'!A$1:E$1284,4,FALSE),"") | D58: =IF(A58<>"",IF(D58<>"",D58,NOW()),"") | E58: =IFERROR(VLOOKUP(A58,G:I,3,FALSE),"Onsite") -> Onsite | I58: =IF(G898<>"",IF(I58<>"",I58,NOW()),"") | J58: =SUBSTITUTE(A58,"NC","") | L58: 0 | N58: =_xlfn.IFNA(VLOOKUP(A58,'Personnel List'!A$1:F$1284,6,FALSE),"")
B59: =_xlfn.IFNA(VLOOKUP(A59,'Personnel List'!A$1:E$1284,5,FALSE),"") | C59: =_xlfn.IFNA(VLOOKUP(A59,'Personnel List'!A$1:E$1284,4,FALSE),"") | D59: =IF(A59<>"",IF(D59<>"",D59,NOW()),"") | E59: =IFERROR(VLOOKUP(A59,G:I,3,FALSE),"Onsite") -> Onsite | I59: =IF(G899<>"",IF(I59<>"",I59,NOW()),"") | J59: =SUBSTITUTE(A59,"NC","") | L59: 0 | N59: =_xlfn.IFNA(VLOOKUP(A59,'Personnel List'!A$1:F$1284,6,FALSE),"")
B60: =_xlfn.IFNA(VLOOKUP(A60,'Personnel List'!A$1:E$1284,5,FALSE),"") | C60: =_xlfn.IFNA(VLOOKUP(A60,'Personnel List'!A$1:E$1284,4,FALSE),"") | D60: =IF(A60<>"",IF(D60<>"",D60,NOW()),"") | E60: =IFERROR(VLOOKUP(A60,G:I,3,FALSE),"Onsite") -> Onsite | I60: =IF(G900<>"",IF(I60<>"",I60,NOW()),"") | J60: =SUBSTITUTE(A60,"NC","") | L60: 0 | N60: =_xlfn.IFNA(VLOOKUP(A60,'Personnel List'!A$1:F$1284,6,FALSE),"")
B61: =_xlfn.IFNA(VLOOKUP(A61,'Personnel List'!A$1:E$1284,5,FALSE),"") | C61: =_xlfn.IFNA(VLOOKUP(A61,'Personnel List'!A$1:E$1284,4,FALSE),"") | D61: =IF(A61<>"",IF(D61<>"",D61,NOW()),"") | E61: =IFERROR(VLOOKUP(A61,G:I,3,FALSE),"Onsite") -> Onsite | I61: =IF(G901<>"",IF(I61<>"",I61,NOW()),"") | J61: =SUBSTITUTE(A61,"NC","") | L61: 0 | N61: =_xlfn.IFNA(VLOOKUP(A61,'Personnel List'!A$1:F$1284,6,FALSE),"")
B62: =_xlfn.IFNA(VLOOKUP(A62,'Personnel List'!A$1:E$1284,5,FALSE),"") | C62: =_xlfn.IFNA(VLOOKUP(A62,'Personnel List'!A$1:E$1284,4,FALSE),"") | D62: =IF(A62<>"",IF(D62<>"",D62,NOW()),"") | E62: =IFERROR(VLOOKUP(A62,G:I,3,FALSE),"Onsite") -> Onsite | I62: =IF(G902<>"",IF(I62<>"",I62,NOW()),"") | J62: =SUBSTITUTE(A62,"NC","") | L62: 0 | N62: =_xlfn.IFNA(VLOOKUP(A62,'Personnel List'!A$1:F$1284,6,FALSE),"")
B63: =_xlfn.IFNA(VLOOKUP(A63,'Personnel List'!A$1:E$1284,5,FALSE),"") | C63: =_xlfn.IFNA(VLOOKUP(A63,'Personnel List'!A$1:E$1284,4,FALSE),"") | D63: =IF(A63<>"",IF(D63<>"",D63,NOW()),"") | E63: =IFERROR(VLOOKUP(A63,G:I,3,FALSE),"Onsite") -> Onsite | I63: =IF(G903<>"",IF(I63<>"",I63,NOW()),"") | J63: =SUBSTITUTE(A63,"NC","") | L63: 0 | N63: =_xlfn.IFNA(VLOOKUP(A63,'Personnel List'!A$1:F$1284,6,FALSE),"")
B64: =_xlfn.IFNA(VLOOKUP(A64,'Personnel List'!A$1:E$1284,5,FALSE),"") | C64: =_xlfn.IFNA(VLOOKUP(A64,'Personnel List'!A$1:E$1284,4,FALSE),"") | D64: =IF(A64<>"",IF(D64<>"",D64,NOW()),"") | E64: =IFERROR(VLOOKUP(A64,G:I,3,FALSE),"Onsite") -> Onsite | I64: =IF(G904<>"",IF(I64<>"",I64,NOW()),"") | J64: =SUBSTITUTE(A64,"NC","") | L64: 0 | N64: =_xlfn.IFNA(VLOOKUP(A64,'Personnel List'!A$1:F$1284,6,FALSE),"")
B65: =_xlfn.IFNA(VLOOKUP(A65,'Personnel List'!A$1:E$1284,5,FALSE),"") | C65: =_xlfn.IFNA(VLOOKUP(A65,'Personnel List'!A$1:E$1284,4,FALSE),"") | D65: =IF(A65<>"",IF(D65<>"",D65,NOW()),"") | E65: =IFERROR(VLOOKUP(A65,G:I,3,FALSE),"Onsite") -> Onsite | I65: =IF(G905<>"",IF(I65<>"",I65,NOW()),"") | J65: =SUBSTITUTE(A65,"NC","") | L65: 0 | N65: =_xlfn.IFNA(VLOOKUP(A65,'Personnel List'!A$1:F$1284,6,FALSE),"")
B66: =_xlfn.IFNA(VLOOKUP(A66,'Personnel List'!A$1:E$1284,5,FALSE),"") | C66: =_xlfn.IFNA(VLOOKUP(A66,'Personnel List'!A$1:E$1284,4,FALSE),"") | D66: =IF(A66<>"",IF(D66<>"",D66,NOW()),"") | E66: =IFERROR(VLOOKUP(A66,G:I,3,FALSE),"Onsite") -> Onsite | I66: =IF(G906<>"",IF(I66<>"",I66,NOW()),"") | J66: =SUBSTITUTE(A66,"NC","") | L66: 0 | N66: =_xlfn.IFNA(VLOOKUP(A66,'Personnel List'!A$1:F$1284,6,FALSE),"")
... B876: =_xlfn.IFNA(VLOOKUP(A876,'Personnel List'!A$1:E$1284,5,FALSE),"") | C876: =_xlfn.IFNA(VLOOKUP(A876,'Personnel List'!A$1:E$1284,4,FALSE),"") | D876: =IF(A876<>"",IF(D876<>"",D876,NOW()),"") | E876: =IFERROR(VLOOKUP(A876,G:I,3,FALSE),"Onsite") -> Onsite | I876: =IF(G1716<>"",IF(I876<>"",I876,NOW()),"") | J876: =SUBSTITUTE(A876,"NC","") | L876: 0 | N876: =_xlfn.IFNA(VLOOKUP(A876,'Personnel List'!A$1:F$1284,6,FALSE),"")
I877: =IF(G1717<>"",IF(I877<>"",I877,NOW()),"") | J877: =SUBSTITUTE(A877,"NC","") | L877: 0
L878: 0
L879: 0
L880: 0
L881: 0
L882: 0
L883: 0
L884: 0
L885: 0
L886: 0
L887: 0
L888: 0
L889: 0
... L999: 0

Sheet Wed DS
A1: Scan ID | B1: Name | C1: Company Name | D1: Time In | E1: Time Out | G1: Scan Out | I1: Timestamp | J1: SAP Number | L1: Not Scanned Yet | M1: DS | N1: Reverse Name
A2: NC90117684 | B2: =_xlfn.IFNA(VLOOKUP(A2,'Personnel List'!A$1:E$1284,5,FALSE),"") -> Isobel Newman | C2: =_xlfn.IFNA(VLOOKUP(A2,'Personnel List'!A$1:E$1284,4,FALSE),"") -> Hays Personnel Services | D2: =IF(A2<>"",IF(D2<>"",D2,NOW()),"") -> 45532.232 | E2: =IFERROR(VLOOKUP(A2,G:I,3,FALSE),"Onsite") -> 45533.228 | G2: NC90117684 | I2: =IF(G2<>"",IF(I2<>"",I2,NOW()),"") -> 45533.228 | J2: =SUBSTITUTE(A2,"NC","") -> 90117684 | L2: {=_xlfn._xlws.FILTER(M2:M1000,(ISNA(MATCH(M2:M1000,N2:N1000,0))),"")} -> Ashby Kaukau, Bula | M2: {=_xlfn._xlws.FILTER('Wed Data'!E13:E895,ISNUMBER(_xlfn.XMATCH('Wed Data'!D13:D895,M1)))} -> Aguinaldo, Roger | N2: =_xlfn.IFNA(VLOOKUP(A2,'Personnel List'!A$1:F$1284,6,FALSE),"") -> Newman, Isobel
A3: NC90135965 | B3: =_xlfn.IFNA(VLOOKUP(A3,'Personnel List'!A$1:E$1284,5,FALSE),"") | C3: =_xlfn.IFNA(VLOOKUP(A3,'Personnel List'!A$1:E$1284,4,FALSE),"") | D3: =IF(A3<>"",IF(D3<>"",D3,NOW()),"") -> 45532.239 | E3: =IFERROR(VLOOKUP(A3,G:I,3,FALSE),"Onsite") -> Onsite | I3: =IF(G3<>"",IF(I3<>"",I3,NOW()),"") | J3: =SUBSTITUTE(A3,"NC","") -> 90135965 | L3: Baker, Alistair | M3: Ashby Kaukau, Bula | N3: =_xlfn.IFNA(VLOOKUP(A3,'Personnel List'!A$1:F$1284,6,FALSE),"")
A4: NC90109011 | B4: =_xlfn.IFNA(VLOOKUP(A4,'Personnel List'!A$1:E$1284,5,FALSE),"") | C4: =_xlfn.IFNA(VLOOKUP(A4,'Personnel List'!A$1:E$1284,4,FALSE),"") | D4: =IF(A4<>"",IF(D4<>"",D4,NOW()),"") -> 45532.239 | E4: =IFERROR(VLOOKUP(A4,G:I,3,FALSE),"Onsite") -> Onsite | I4: =IF(G4<>"",IF(I4<>"",I4,NOW()),"") | J4: =SUBSTITUTE(A4,"NC","") -> 90109011 | L4: Baldock, Grant | M4: Baker, Alistair | N4: =_xlfn.IFNA(VLOOKUP(A4,'Personnel List'!A$1:F$1284,6,FALSE),"")
A5: NC90136780 | B5: =_xlfn.IFNA(VLOOKUP(A5,'Personnel List'!A$1:E$1284,5,FALSE),"") | C5: =_xlfn.IFNA(VLOOKUP(A5,'Personnel List'!A$1:E$1284,4,FALSE),"") | D5: =IF(A5<>"",IF(D5<>"",D5,NOW()),"") -> 45532.239 | E5: =IFERROR(VLOOKUP(A5,G:I,3,FALSE),"Onsite") -> Onsite | I5: =IF(G5<>"",IF(I5<>"",I5,NOW()),"") | J5: =SUBSTITUTE(A5,"NC","") -> 90136780 | L5: Batty, Noah | M5: Baldock, Grant | N5: =_xlfn.IFNA(VLOOKUP(A5,'Personnel List'!A$1:F$1284,6,FALSE),"")
A6: NC90112063 | B6: =_xlfn.IFNA(VLOOKUP(A6,'Personnel List'!A$1:E$1284,5,FALSE),"") -> Rangatira Lim | C6: =_xlfn.IFNA(VLOOKUP(A6,'Personnel List'!A$1:E$1284,4,FALSE),"") -> Contitech (Continental) | D6: =IF(A6<>"",IF(D6<>"",D6,NOW()),"") -> 45532.252 | E6: =IFERROR(VLOOKUP(A6,G:I,3,FALSE),"Onsite") -> Onsite | I6: =IF(G6<>"",IF(I6<>"",I6,NOW()),"") | J6: =SUBSTITUTE(A6,"NC","") -> 90112063 | L6: Beitsch, Sam | M6: Batty, Noah | N6: =_xlfn.IFNA(VLOOKUP(A6,'Personnel List'!A$1:F$1284,6,FALSE),"") -> Lim, Rangatira
A7: NC90138269 | B7: =_xlfn.IFNA(VLOOKUP(A7,'Personnel List'!A$1:E$1284,5,FALSE),"") | C7: =_xlfn.IFNA(VLOOKUP(A7,'Personnel List'!A$1:E$1284,4,FALSE),"") | D7: =IF(A7<>"",IF(D7<>"",D7,NOW()),"") -> 45532.252 | E7: =IFERROR(VLOOKUP(A7,G:I,3,FALSE),"Onsite") -> Onsite | I7: =IF(G7<>"",IF(I7<>"",I7,NOW()),"") | J7: =SUBSTITUTE(A7,"NC","") -> 90138269 | L7: Benamati, Federico | M7: Beitsch, Sam | N7: =_xlfn.IFNA(VLOOKUP(A7,'Personnel List'!A$1:F$1284,6,FALSE),"")
A8: NC90138271 | B8: =_xlfn.IFNA(VLOOKUP(A8,'Personnel List'!A$1:E$1284,5,FALSE),"") | C8: =_xlfn.IFNA(VLOOKUP(A8,'Personnel List'!A$1:E$1284,4,FALSE),"") | D8: =IF(A8<>"",IF(D8<>"",D8,NOW()),"") -> 45532.252 | E8: =IFERROR(VLOOKUP(A8,G:I,3,FALSE),"Onsite") -> Onsite | I8: =IF(G8<>"",IF(I8<>"",I8,NOW()),"") | J8: =SUBSTITUTE(A8,"NC","") -> 90138271 | L8: Bendjebbour, Nihad | M8: Benamati, Federico | N8: =_xlfn.IFNA(VLOOKUP(A8,'Personnel List'!A$1:F$1284,6,FALSE),"")
A9: NC90138340 | B9: =_xlfn.IFNA(VLOOKUP(A9,'Personnel List'!A$1:E$1284,5,FALSE),"") | C9: =_xlfn.IFNA(VLOOKUP(A9,'Personnel List'!A$1:E$1284,4,FALSE),"") | D9: =IF(A9<>"",IF(D9<>"",D9,NOW()),"") -> 45532.252 | E9: =IFERROR(VLOOKUP(A9,G:I,3,FALSE),"Onsite") -> Onsite | I9: =IF(G9<>"",IF(I9<>"",I9,NOW()),"") | J9: =SUBSTITUTE(A9,"NC","") -> 90138340 | L9: Bickham, Lincoln | M9: Bendjebbour, Nihad | N9: =_xlfn.IFNA(VLOOKUP(A9,'Personnel List'!A$1:F$1284,6,FALSE),"")
A10: NC90095836 | B10: =_xlfn.IFNA(VLOOKUP(A10,'Personnel List'!A$1:E$1284,5,FALSE),"") -> Michael O'Keane | C10: =_xlfn.IFNA(VLOOKUP(A10,'Personnel List'!A$1:E$1284,4,FALSE),"") -> Minprovise | D10: =IF(A10<>"",IF(D10<>"",D10,NOW()),"") -> 45532.253 | E10: =IFERROR(VLOOKUP(A10,G:I,3,FALSE),"Onsite") -> Onsite | I10: =IF(G10<>"",IF(I10<>"",I10,NOW()),"") | J10: =SUBSTITUTE(A10,"NC","") -> 90095836 | L10: Biljabu, Jaydin | M10: Bickham, Lincoln | N10: =_xlfn.IFNA(VLOOKUP(A10,'Personnel List'!A$1:F$1284,6,FALSE),"") -> O'Keane, Michael
A11: NC90076757 | B11: =_xlfn.IFNA(VLOOKUP(A11,'Personnel List'!A$1:E$1284,5,FALSE),"") -> Weixin Zhang | C11: =_xlfn.IFNA(VLOOKUP(A11,'Personnel List'!A$1:E$1284,4,FALSE),"") -> Minprovise | D11: =IF(A11<>"",IF(D11<>"",D11,NOW()),"") -> 45532.253 | E11: =IFERROR(VLOOKUP(A11,G:I,3,FALSE),"Onsite") -> Onsite | I11: =IF(G11<>"",IF(I11<>"",I11,NOW()),"") | J11: =SUBSTITUTE(A11,"NC","") -> 90076757 | L11: Bott, Sonia | M11: Biljabu, Jaydin | N11: =_xlfn.IFNA(VLOOKUP(A11,'Personnel List'!A$1:F$1284,6,FALSE),"") -> Zhang, Weixin
A12: NC90094440 | B12: =_xlfn.IFNA(VLOOKUP(A12,'Personnel List'!A$1:E$1284,5,FALSE),"") -> Jarred Walker | C12: =_xlfn.IFNA(VLOOKUP(A12,'Personnel List'!A$1:E$1284,4,FALSE),"") -> Minprovise | D12: =IF(A12<>"",IF(D12<>"",D12,NOW()),"") -> 45532.253 | E12: =IFERROR(VLOOKUP(A12,G:I,3,FALSE),"Onsite") -> Onsite | I12: =IF(G12<>"",IF(I12<>"",I12,NOW()),"") | J12: =SUBSTITUTE(A12,"NC","") -> 90094440 | L12: Boyd, Graham | M12: Bott, Sonia | N12: =_xlfn.IFNA(VLOOKUP(A12,'Personnel List'!A$1:F$1284,6,FALSE),"") -> Walker, Jarred
A13: NC90061866 | B13: =_xlfn.IFNA(VLOOKUP(A13,'Personnel List'!A$1:E$1284,5,FALSE),"") -> Cheynne Mitchell | C13: =_xlfn.IFNA(VLOOKUP(A13,'Personnel List'!A$1:E$1284,4,FALSE),"") -> APMS | D13: =IF(A13<>"",IF(D13<>"",D13,NOW()),"") -> 45532.253 | E13: =IFERROR(VLOOKUP(A13,G:I,3,FALSE),"Onsite") -> Onsite | I13: =IF(G13<>"",IF(I13<>"",I13,NOW()),"") | J13: =SUBSTITUTE(A13,"NC","") -> 90061866 | L13: Brewer, Corry | M13: Boyd, Graham | N13: =_xlfn.IFNA(VLOOKUP(A13,'Personnel List'!A$1:F$1284,6,FALSE),"") -> Mitchell, Cheynne
A14: NC90123703 | B14: =_xlfn.IFNA(VLOOKUP(A14,'Personnel List'!A$1:E$1284,5,FALSE),"") -> Grace Walker Smith | C14: =_xlfn.IFNA(VLOOKUP(A14,'Personnel List'!A$1:E$1284,4,FALSE),"") -> Minprovise | D14: =IF(A14<>"",IF(D14<>"",D14,NOW()),"") -> 45532.253 | E14: =IFERROR(VLOOKUP(A14,G:I,3,FALSE),"Onsite") -> Onsite | I14: =IF(G14<>"",IF(I14<>"",I14,NOW()),"") | J14: =SUBSTITUTE(A14,"NC","") -> 90123703 | L14: Brooking, Desmond | M14: Brewer, Corry | N14: =_xlfn.IFNA(VLOOKUP(A14,'Personnel List'!A$1:F$1284,6,FALSE),"") -> Walker Smith, Grace
... A24: NC90109838 | B24: =_xlfn.IFNA(VLOOKUP(A24,'Personnel List'!A$1:E$1284,5,FALSE),"") -> Thomas Rogers | C24: =_xlfn.IFNA(VLOOKUP(A24,'Personnel List'!A$1:E$1284,4,FALSE),"") -> SMS Group Services | D24: =IF(A24<>"",IF(D24<>"",D24,NOW()),"") -> 45532.258 | E24: =IFERROR(VLOOKUP(A24,G:I,3,FALSE),"Onsite") -> Onsite | I24: =IF(G24<>"",IF(I24<>"",I24,NOW()),"") | J24: =SUBSTITUTE(A24,"NC","") -> 90109838 | L24: Derfoufi, Mohamed | M24: Coupe, Lee | N24: =_xlfn.IFNA(VLOOKUP(A24,'Personnel List'!A$1:F$1284,6,FALSE),"") -> Rogers, Thomas
B25: =_xlfn.IFNA(VLOOKUP(A25,'Personnel List'!A$1:E$1284,5,FALSE),"") | C25: =_xlfn.IFNA(VLOOKUP(A25,'Personnel List'!A$1:E$1284,4,FALSE),"") | D25: =IF(A25<>"",IF(D25<>"",D25,NOW()),"") | E25: =IFERROR(VLOOKUP(A25,G:I,3,FALSE),"Onsite") -> Onsite | I25: =IF(G25<>"",IF(I25<>"",I25,NOW()),"") | J25: =SUBSTITUTE(A25,"NC","") | L25: Dileo, Michael | M25: Davasse-Prendergast, Luke | N25: =_xlfn.IFNA(VLOOKUP(A25,'Personnel List'!A$1:F$1284,6,FALSE),"")
B26: =_xlfn.IFNA(VLOOKUP(A26,'Personnel List'!A$1:E$1284,5,FALSE),"") | C26: =_xlfn.IFNA(VLOOKUP(A26,'Personnel List'!A$1:E$1284,4,FALSE),"") | D26: =IF(A26<>"",IF(D26<>"",D26,NOW()),"") | E26: =IFERROR(VLOOKUP(A26,G:I,3,FALSE),"Onsite") -> Onsite | I26: =IF(G26<>"",IF(I26<>"",I26,NOW()),"") | J26: =SUBSTITUTE(A26,"NC","") | L26: Donges, Trent | M26: Derfoufi, Mohamed | N26: =_xlfn.IFNA(VLOOKUP(A26,'Personnel List'!A$1:F$1284,6,FALSE),"")
B27: =_xlfn.IFNA(VLOOKUP(A27,'Personnel List'!A$1:E$1284,5,FALSE),"") | C27: =_xlfn.IFNA(VLOOKUP(A27,'Personnel List'!A$1:E$1284,4,FALSE),"") | D27: =IF(A27<>"",IF(D27<>"",D27,NOW()),"") | E27: =IFERROR(VLOOKUP(A27,G:I,3,FALSE),"Onsite") -> Onsite | I27: =IF(G27<>"",IF(I27<>"",I27,NOW()),"") | J27: =SUBSTITUTE(A27,"NC","") | L27: Eaton, Brodie | M27: Dileo, Michael | N27: =_xlfn.IFNA(VLOOKUP(A27,'Personnel List'!A$1:F$1284,6,FALSE),"")
B28: =_xlfn.IFNA(VLOOKUP(A28,'Personnel List'!A$1:E$1284,5,FALSE),"") | C28: =_xlfn.IFNA(VLOOKUP(A28,'Personnel List'!A$1:E$1284,4,FALSE),"") | D28: =IF(A28<>"",IF(D28<>"",D28,NOW()),"") | E28: =IFERROR(VLOOKUP(A28,G:I,3,FALSE),"Onsite") -> Onsite | I28: =IF(G28<>"",IF(I28<>"",I28,NOW()),"") | J28: =SUBSTITUTE(A28,"NC","") | L28: Edwards, Lachlan | M28: Donges, Trent | N28: =_xlfn.IFNA(VLOOKUP(A28,'Personnel List'!A$1:F$1284,6,FALSE),"")
B29: =_xlfn.IFNA(VLOOKUP(A29,'Personnel List'!A$1:E$1284,5,FALSE),"") | C29: =_xlfn.IFNA(VLOOKUP(A29,'Personnel List'!A$1:E$1284,4,FALSE),"") | D29: =IF(A29<>"",IF(D29<>"",D29,NOW()),"") | E29: =IFERROR(VLOOKUP(A29,G:I,3,FALSE),"Onsite") -> Onsite | I29: =IF(G29<>"",IF(I29<>"",I29,NOW()),"") | J29: =SUBSTITUTE(A29,"NC","") | L29: Gates, Darren | M29: Eaton, Brodie | N29: =_xlfn.IFNA(VLOOKUP(A29,'Personnel List'!A$1:F$1284,6,FALSE),"")
B30: =_xlfn.IFNA(VLOOKUP(A30,'Personnel List'!A$1:E$1284,5,FALSE),"") | C30: =_xlfn.IFNA(VLOOKUP(A30,'Personnel List'!A$1:E$1284,4,FALSE),"") | D30: =IF(A30<>"",IF(D30<>"",D30,NOW()),"") | E30: =IFERROR(VLOOKUP(A30,G:I,3,FALSE),"Onsite") -> Onsite | I30: =IF(G30<>"",IF(I30<>"",I30,NOW()),"") | J30: =SUBSTITUTE(A30,"NC","") | L30: Georgel, Dion | M30: Edwards, Lachlan | N30: =_xlfn.IFNA(VLOOKUP(A30,'Personnel List'!A$1:F$1284,6,FALSE),"")
B31: =_xlfn.IFNA(VLOOKUP(A31,'Personnel List'!A$1:E$1284,5,FALSE),"") | C31: =_xlfn.IFNA(VLOOKUP(A31,'Personnel List'!A$1:E$1284,4,FALSE),"") | D31: =IF(A31<>"",IF(D31<>"",D31,NOW()),"") | E31: =IFERROR(VLOOKUP(A31,G:I,3,FALSE),"Onsite") -> Onsite | I31: =IF(G31<>"",IF(I31<>"",I31,NOW()),"") | J31: =SUBSTITUTE(A31,"NC","") | L31: Gravner, Stuart | M31: Ferrand, Thomas | N31: =_xlfn.IFNA(VLOOKUP(A31,'Personnel List'!A$1:F$1284,6,FALSE),"")
B32: =_xlfn.IFNA(VLOOKUP(A32,'Personnel List'!A$1:E$1284,5,FALSE),"") | C32: =_xlfn.IFNA(VLOOKUP(A32,'Personnel List'!A$1:E$1284,4,FALSE),"") | D32: =IF(A32<>"",IF(D32<>"",D32,NOW()),"") | E32: =IFERROR(VLOOKUP(A32,G:I,3,FALSE),"Onsite") -> Onsite | I32: =IF(G32<>"",IF(I32<>"",I32,NOW()),"") | J32: =SUBSTITUTE(A32,"NC","") | L32: Harmsworth, Benjamin | M32: Gates, Darren | N32: =_xlfn.IFNA(VLOOKUP(A32,'Personnel List'!A$1:F$1284,6,FALSE),"")
B33: =_xlfn.IFNA(VLOOKUP(A33,'Personnel List'!A$1:E$1284,5,FALSE),"") | E33: =IFERROR(VLOOKUP(A33,G:I,3,FALSE),"Onsite") -> Onsite | I33: =IF(G33<>"",IF(I33<>"",I33,NOW()),"") | J33: =SUBSTITUTE(A33,"NC","") | L33: Harris, Tyler | M33: Gearing, Sean | N33: =_xlfn.IFNA(VLOOKUP(A33,'Personnel List'!A$1:F$1284,6,FALSE),"")
B34: =_xlfn.IFNA(VLOOKUP(A34,'Personnel List'!A$1:E$1284,5,FALSE),"") | C34: =_xlfn.IFNA(VLOOKUP(A34,'Personnel List'!A$1:E$1284,4,FALSE),"") | D34: =IF(A34<>"",IF(D34<>"",D34,NOW()),"") | E34: =IFERROR(VLOOKUP(A34,G:I,3,FALSE),"Onsite") -> Onsite | I34: =IF(G34<>"",IF(I34<>"",I34,NOW()),"") | J34: =SUBSTITUTE(A34,"NC","") | L34: Higuchi, Kanna | M34: Georgel, Dion | N34: =_xlfn.IFNA(VLOOKUP(A34,'Personnel List'!A$1:F$1284,6,FALSE),"")
B35: =_xlfn.IFNA(VLOOKUP(A35,'Personnel List'!A$1:E$1284,5,FALSE),"") | C35: =_xlfn.IFNA(VLOOKUP(A35,'Personnel List'!A$1:E$1284,4,FALSE),"") | D35: =IF(A35<>"",IF(D35<>"",D35,NOW()),"") | E35: =IFERROR(VLOOKUP(A35,G:I,3,FALSE),"Onsite") -> Onsite | I35: =IF(G35<>"",IF(I35<>"",I35,NOW()),"") | J35: =SUBSTITUTE(A35,"NC","") | L35: Hitchens, Caleb | M35: Gravner, Stuart | N35: =_xlfn.IFNA(VLOOKUP(A35,'Personnel List'!A$1:F$1284,6,FALSE),"")
B36: =_xlfn.IFNA(VLOOKUP(A36,'Personnel List'!A$1:E$1284,5,FALSE),"") | C36: =_xlfn.IFNA(VLOOKUP(A36,'Personnel List'!A$1:E$1284,4,FALSE),"") | D36: =IF(A36<>"",IF(D36<>"",D36,NOW()),"") | E36: =IFERROR(VLOOKUP(A36,G:I,3,FALSE),"Onsite") -> Onsite | I36: =IF(G36<>"",IF(I36<>"",I36,NOW()),"") | J36: =SUBSTITUTE(A36,"NC","") | L36: Holmes, Glenn | M36: Harmsworth, Benjamin | N36: =_xlfn.IFNA(VLOOKUP(A36,'Personnel List'!A$1:F$1284,6,FALSE),"")
B37: =_xlfn.IFNA(VLOOKUP(A37,'Personnel List'!A$1:E$1284,5,FALSE),"") | C37: =_xlfn.IFNA(VLOOKUP(A37,'Personnel List'!A$1:E$1284,4,FALSE),"") | D37: =IF(A37<>"",IF(D37<>"",D37,NOW()),"") | E37: =IFERROR(VLOOKUP(A37,G:I,3,FALSE),"Onsite") -> Onsite | I37: =IF(G37<>"",IF(I37<>"",I37,NOW()),"") | J37: =SUBSTITUTE(A37,"NC","") | L37: Hunt, Simonski | M37: Harris, Tyler | N37: =_xlfn.IFNA(VLOOKUP(A37,'Personnel List'!A$1:F$1284,6,FALSE),"")
B38: =_xlfn.IFNA(VLOOKUP(A38,'Personnel List'!A$1:E$1284,5,FALSE),"") | C38: =_xlfn.IFNA(VLOOKUP(A38,'Personnel List'!A$1:E$1284,4,FALSE),"") | D38: =IF(A38<>"",IF(D38<>"",D38,NOW()),"") | E38: =IFERROR(VLOOKUP(A38,G:I,3,FALSE),"Onsite") -> Onsite | I38: =IF(G38<>"",IF(I38<>"",I38,NOW()),"") | J38: =SUBSTITUTE(A38,"NC","") | L38: Jones, Cameron | M38: Higuchi, Kanna | N38: =_xlfn.IFNA(VLOOKUP(A38,'Personnel List'!A$1:F$1284,6,FALSE),"")
B39: =_xlfn.IFNA(VLOOKUP(A39,'Personnel List'!A$1:E$1284,5,FALSE),"") | C39: =_xlfn.IFNA(VLOOKUP(A39,'Personnel List'!A$1:E$1284,4,FALSE),"") | D39: =IF(A39<>"",IF(D39<>"",D39,NOW()),"") | E39: =IFERROR(VLOOKUP(A39,G:I,3,FALSE),"Onsite") -> Onsite | I39: =IF(G39<>"",IF(I39<>"",I39,NOW()),"") | J39: =SUBSTITUTE(A39,"NC","") | L39: Jury, Mark | M39: Hitchens, Caleb | N39: =_xlfn.IFNA(VLOOKUP(A39,'Personnel List'!A$1:F$1284,6,FALSE),"")
B40: =_xlfn.IFNA(VLOOKUP(A40,'Personnel List'!A$1:E$1284,5,FALSE),"") | C40: =_xlfn.IFNA(VLOOKUP(A40,'Personnel List'!A$1:E$1284,4,FALSE),"") | D40: =IF(A40<>"",IF(D40<>"",D40,NOW()),"") | E40: =IFERROR(VLOOKUP(A40,G:I,3,FALSE),"Onsite") -> Onsite | I40: =IF(G40<>"",IF(I40<>"",I40,NOW()),"") | J40: =SUBSTITUTE(A40,"NC","") | L40: Kattler, Lyndon | M40: Holmes, Glenn | N40: =_xlfn.IFNA(VLOOKUP(A40,'Personnel List'!A$1:F$1284,6,FALSE),"")
D41: =IF(A41<>"",IF(D41<>"",D41,NOW()),"") | E41: =IFERROR(VLOOKUP(A41,G:I,3,FALSE),"Onsite") -> Onsite | I41: =IF(G41<>"",IF(I41<>"",I41,NOW()),"") | J41: =SUBSTITUTE(A41,"NC","") | L41: Kelly, Russell | M41: Hunt, Simonski | N41: =_xlfn.IFNA(VLOOKUP(A41,'Personnel List'!A$1:F$1284,6,FALSE),"")
B42: =_xlfn.IFNA(VLOOKUP(A42,'Personnel List'!A$1:E$1284,5,FALSE),"") | C42: =_xlfn.IFNA(VLOOKUP(A42,'Personnel List'!A$1:E$1284,4,FALSE),"") | D42: =IF(A42<>"",IF(D42<>"",D42,NOW()),"") | E42: =IFERROR(VLOOKUP(A42,G:I,3,FALSE),"Onsite") -> Onsite | I42: =IF(G42<>"",IF(I42<>"",I42,NOW()),"") | J42: =SUBSTITUTE(A42,"NC","") | L42: Kingi, Te Raukohe | M42: Itchon, Victor | N42: =_xlfn.IFNA(VLOOKUP(A42,'Personnel List'!A$1:F$1284,6,FALSE),"")
B43: =_xlfn.IFNA(VLOOKUP(A43,'Personnel List'!A$1:E$1284,5,FALSE),"") | C43: =_xlfn.IFNA(VLOOKUP(A43,'Personnel List'!A$1:E$1284,4,FALSE),"") | D43: =IF(A43<>"",IF(D43<>"",D43,NOW()),"") | E43: =IFERROR(VLOOKUP(A43,G:I,3,FALSE),"Onsite") -> Onsite | I43: =IF(G43<>"",IF(I43<>"",I43,NOW()),"") | J43: =SUBSTITUTE(A43,"NC","") | L43: Lane, Emily | M43: Jones, Cameron | N43: =_xlfn.IFNA(VLOOKUP(A43,'Personnel List'!A$1:F$1284,6,FALSE),"")
B44: =_xlfn.IFNA(VLOOKUP(A44,'Personnel List'!A$1:E$1284,5,FALSE),"") | C44: =_xlfn.IFNA(VLOOKUP(A44,'Personnel List'!A$1:E$1284,4,FALSE),"") | D44: =IF(A44<>"",IF(D44<>"",D44,NOW()),"") | E44: =IFERROR(VLOOKUP(A44,G:I,3,FALSE),"Onsite") -> Onsite | I44: =IF(G44<>"",IF(I44<>"",I44,NOW()),"") | J44: =SUBSTITUTE(A44,"NC","") | L44: Lanete, Randy | M44: Jury, Mark | N44: =_xlfn.IFNA(VLOOKUP(A44,'Personnel List'!A$1:F$1284,6,FALSE),"")
B45: =_xlfn.IFNA(VLOOKUP(A45,'Personnel List'!A$1:E$1284,5,FALSE),"") | C45: =_xlfn.IFNA(VLOOKUP(A45,'Personnel List'!A$1:E$1284,4,FALSE),"") | D45: =IF(A45<>"",IF(D45<>"",D45,NOW()),"") | E45: =IFERROR(VLOOKUP(A45,G:I,3,FALSE),"Onsite") -> Onsite | I45: =IF(G45<>"",IF(I45<>"",I45,NOW()),"") | J45: =SUBSTITUTE(A45,"NC","") | L45: Lim, Taine | M45: Kattler, Lyndon | N45: =_xlfn.IFNA(VLOOKUP(A45,'Personnel List'!A$1:F$1284,6,FALSE),"")
B46: =_xlfn.IFNA(VLOOKUP(A46,'Personnel List'!A$1:E$1284,5,FALSE),"") | C46: =_xlfn.IFNA(VLOOKUP(A46,'Personnel List'!A$1:E$1284,4,FALSE),"") | D46: =IF(A46<>"",IF(D46<>"",D46,NOW()),"") | E46: =IFERROR(VLOOKUP(A46,G:I,3,FALSE),"Onsite") -> Onsite | I46: =IF(G886<>"",IF(I46<>"",I46,NOW()),"") | J46: =SUBSTITUTE(A46,"NC","") | L46: Lord, Darren | M46: Kelly, Russell | N46: =_xlfn.IFNA(VLOOKUP(A46,'Personnel List'!A$1:F$1284,6,FALSE),"")
B47: =_xlfn.IFNA(VLOOKUP(A47,'Personnel List'!A$1:E$1284,5,FALSE),"") | C47: =_xlfn.IFNA(VLOOKUP(A47,'Personnel List'!A$1:E$1284,4,FALSE),"") | D47: =IF(A47<>"",IF(D47<>"",D47,NOW()),"") | E47: =IFERROR(VLOOKUP(A47,G:I,3,FALSE),"Onsite") -> Onsite | I47: =IF(G887<>"",IF(I47<>"",I47,NOW()),"") | J47: =SUBSTITUTE(A47,"NC","") | L47: Maclean, Bronson | M47: Kingi, Te Raukohe | N47: =_xlfn.IFNA(VLOOKUP(A47,'Personnel List'!A$1:F$1284,6,FALSE),"")
B48: =_xlfn.IFNA(VLOOKUP(A48,'Personnel List'!A$1:E$1284,5,FALSE),"") | C48: =_xlfn.IFNA(VLOOKUP(A48,'Personnel List'!A$1:E$1284,4,FALSE),"") | D48: =IF(A48<>"",IF(D48<>"",D48,NOW()),"") | E48: =IFERROR(VLOOKUP(A48,G:I,3,FALSE),"Onsite") -> Onsite | I48: =IF(G888<>"",IF(I48<>"",I48,NOW()),"") | J48: =SUBSTITUTE(A48,"NC","") | L48: Madden, Jason | M48: Lane, Emily | N48: =_xlfn.IFNA(VLOOKUP(A48,'Personnel List'!A$1:F$1284,6,FALSE),"")
B49: =_xlfn.IFNA(VLOOKUP(A49,'Personnel List'!A$1:E$1284,5,FALSE),"") | C49: =_xlfn.IFNA(VLOOKUP(A49,'Personnel List'!A$1:E$1284,4,FALSE),"") | D49: =IF(A49<>"",IF(D49<>"",D49,NOW()),"") | E49: =IFERROR(VLOOKUP(A49,G:I,3,FALSE),"Onsite") -> Onsite | I49: =IF(G889<>"",IF(I49<>"",I49,NOW()),"") | J49: =SUBSTITUTE(A49,"NC","") | L49: Madronero, Angelo | M49: Lanete, Randy | N49: =_xlfn.IFNA(VLOOKUP(A49,'Personnel List'!A$1:F$1284,6,FALSE),"")
B50: =_xlfn.IFNA(VLOOKUP(A50,'Personnel List'!A$1:E$1284,5,FALSE),"") | C50: =_xlfn.IFNA(VLOOKUP(A50,'Personnel List'!A$1:E$1284,4,FALSE),"") | D50: =IF(A50<>"",IF(D50<>"",D50,NOW()),"") | E50: =IFERROR(VLOOKUP(A50,G:I,3,FALSE),"Onsite") -> Onsite | I50: =IF(G890<>"",IF(I50<>"",I50,NOW()),"") | J50: =SUBSTITUTE(A50,"NC","") | L50: Martiren, Joaquin | M50: Lim, Rangatira | N50: =_xlfn.IFNA(VLOOKUP(A50,'Personnel List'!A$1:F$1284,6,FALSE),"")
B51: =_xlfn.IFNA(VLOOKUP(A51,'Personnel List'!A$1:E$1284,5,FALSE),"") | C51: =_xlfn.IFNA(VLOOKUP(A51,'Personnel List'!A$1:E$1284,4,FALSE),"") | D51: =IF(A51<>"",IF(D51<>"",D51,NOW()),"") | E51: =IFERROR(VLOOKUP(A51,G:I,3,FALSE),"Onsite") -> Onsite | I51: =IF(G891<>"",IF(I51<>"",I51,NOW()),"") | J51: =SUBSTITUTE(A51,"NC","") | L51: McGougan, Archie | M51: Lim, Taine | N51: =_xlfn.IFNA(VLOOKUP(A51,'Personnel List'!A$1:F$1284,6,FALSE),"")
B52: =_xlfn.IFNA(VLOOKUP(A52,'Personnel List'!A$1:E$1284,5,FALSE),"") | C52: =_xlfn.IFNA(VLOOKUP(A52,'Personnel List'!A$1:E$1284,4,FALSE),"") | D52: =IF(A52<>"",IF(D52<>"",D52,NOW()),"") | E52: =IFERROR(VLOOKUP(A52,G:I,3,FALSE),"Onsite") -> Onsite | I52: =IF(G892<>"",IF(I52<>"",I52,NOW()),"") | J52: =SUBSTITUTE(A52,"NC","") | L52: McGregor, Shannon | M52: Lord, Darren | N52: =_xlfn.IFNA(VLOOKUP(A52,'Personnel List'!A$1:F$1284,6,FALSE),"")
B53: =_xlfn.IFNA(VLOOKUP(A53,'Personnel List'!A$1:E$1284,5,FALSE),"") | D53: =IF(A53<>"",IF(D53<>"",D53,NOW()),"") | E53: =IFERROR(VLOOKUP(A53,G:I,3,FALSE),"Onsite") -> Onsite | I53: =IF(G893<>"",IF(I53<>"",I53,NOW()),"") | J53: =SUBSTITUTE(A53,"NC","") | L53: McLelland, Scott | M53: Maclean, Bronson | N53: =_xlfn.IFNA(VLOOKUP(A53,'Personnel List'!A$1:F$1284,6,FALSE),"")
B54: =_xlfn.IFNA(VLOOKUP(A54,'Personnel List'!A$1:E$1284,5,FALSE),"") | D54: =IF(A54<>"",IF(D54<>"",D54,NOW()),"") | E54: =IFERROR(VLOOKUP(A54,G:I,3,FALSE),"Onsite") -> Onsite | I54: =IF(G894<>"",IF(I54<>"",I54,NOW()),"") | J54: =SUBSTITUTE(A54,"NC","") | L54: McNally, Wade | M54: Madden, Jason | N54: =_xlfn.IFNA(VLOOKUP(A54,'Personnel List'!A$1:F$1284,6,FALSE),"")
B55: =_xlfn.IFNA(VLOOKUP(A55,'Personnel List'!A$1:E$1284,5,FALSE),"") | C55: =_xlfn.IFNA(VLOOKUP(A55,'Personnel List'!A$1:E$1284,4,FALSE),"") | D55: =IF(A55<>"",IF(D55<>"",D55,NOW()),"") | E55: =IFERROR(VLOOKUP(A55,G:I,3,FALSE),"Onsite") -> Onsite | I55: =IF(G895<>"",IF(I55<>"",I55,NOW()),"") | J55: =SUBSTITUTE(A55,"NC","") | L55: McQuarrie, Timothy | M55: Madronero, Angelo | N55: =_xlfn.IFNA(VLOOKUP(A55,'Personnel List'!A$1:F$1284,6,FALSE),"")
B56: =_xlfn.IFNA(VLOOKUP(A56,'Personnel List'!A$1:E$1284,5,FALSE),"") | C56: =_xlfn.IFNA(VLOOKUP(A56,'Personnel List'!A$1:E$1284,4,FALSE),"") | D56: =IF(A56<>"",IF(D56<>"",D56,NOW()),"") | E56: =IFERROR(VLOOKUP(A56,G:I,3,FALSE),"Onsite") -> Onsite | I56: =IF(G896<>"",IF(I56<>"",I56,NOW()),"") | J56: =SUBSTITUTE(A56,"NC","") | L56: Mulhall, Martin | M56: Martiren, Joaquin | N56: =_xlfn.IFNA(VLOOKUP(A56,'Personnel List'!A$1:F$1284,6,FALSE),"")
B57: =_xlfn.IFNA(VLOOKUP(A57,'Personnel List'!A$1:E$1284,5,FALSE),"") | C57: =_xlfn.IFNA(VLOOKUP(A57,'Personnel List'!A$1:E$1284,4,FALSE),"") | D57: =IF(A57<>"",IF(D57<>"",D57,NOW()),"") | E57: =IFERROR(VLOOKUP(A57,G:I,3,FALSE),"Onsite") -> Onsite | I57: =IF(G897<>"",IF(I57<>"",I57,NOW()),"") | J57: =SUBSTITUTE(A57,"NC","") | L57: Mulligan, Wesley | M57: McGougan, Archie | N57: =_xlfn.IFNA(VLOOKUP(A57,'Personnel List'!A$1:F$1284,6,FALSE),"")
B58: =_xlfn.IFNA(VLOOKUP(A58,'Personnel List'!A$1:E$1284,5,FALSE),"") | C58: =_xlfn.IFNA(VLOOKUP(A58,'Personnel List'!A$1:E$1284,4,FALSE),"") | D58: =IF(A58<>"",IF(D58<>"",D58,NOW()),"") | E58: =IFERROR(VLOOKUP(A58,G:I,3,FALSE),"Onsite") -> Onsite | I58: =IF(G898<>"",IF(I58<>"",I58,NOW()),"") | J58: =SUBSTITUTE(A58,"NC","") | L58: Nakayama, Sumika | M58: McGregor, Shannon | N58: =_xlfn.IFNA(VLOOKUP(A58,'Personnel List'!A$1:F$1284,6,FALSE),"")
B59: =_xlfn.IFNA(VLOOKUP(A59,'Personnel List'!A$1:E$1284,5,FALSE),"") | C59: =_xlfn.IFNA(VLOOKUP(A59,'Personnel List'!A$1:E$1284,4,FALSE),"") | D59: =IF(A59<>"",IF(D59<>"",D59,NOW()),"") | E59: =IFERROR(VLOOKUP(A59,G:I,3,FALSE),"Onsite") -> Onsite | I59: =IF(G899<>"",IF(I59<>"",I59,NOW()),"") | J59: =SUBSTITUTE(A59,"NC","") | L59: Neal, Adam | M59: McLelland, Scott | N59: =_xlfn.IFNA(VLOOKUP(A59,'Personnel List'!A$1:F$1284,6,FALSE),"")
B60: =_xlfn.IFNA(VLOOKUP(A60,'Personnel List'!A$1:E$1284,5,FALSE),"") | C60: =_xlfn.IFNA(VLOOKUP(A60,'Personnel List'!A$1:E$1284,4,FALSE),"") | D60: =IF(A60<>"",IF(D60<>"",D60,NOW()),"") | E60: =IFERROR(VLOOKUP(A60,G:I,3,FALSE),"Onsite") -> Onsite | I60: =IF(G900<>"",IF(I60<>"",I60,NOW()),"") | J60: =SUBSTITUTE(A60,"NC","") | L60: Ness, Bradley | M60: McNally, Wade | N60: =_xlfn.IFNA(VLOOKUP(A60,'Personnel List'!A$1:F$1284,6,FALSE),"")
B61: =_xlfn.IFNA(VLOOKUP(A61,'Personnel List'!A$1:E$1284,5,FALSE),"") | C61: =_xlfn.IFNA(VLOOKUP(A61,'Personnel List'!A$1:E$1284,4,FALSE),"") | D61: =IF(A61<>"",IF(D61<>"",D61,NOW()),"") | E61: =IFERROR(VLOOKUP(A61,G:I,3,FALSE),"Onsite") -> Onsite | I61: =IF(G901<>"",IF(I61<>"",I61,NOW()),"") | J61: =SUBSTITUTE(A61,"NC","") | L61: Neville, Mark | M61: McQuarrie, Timothy | N61: =_xlfn.IFNA(VLOOKUP(A61,'Personnel List'!A$1:F$1284,6,FALSE),"")
B62: =_xlfn.IFNA(VLOOKUP(A62,'Personnel List'!A$1:E$1284,5,FALSE),"") | C62: =_xlfn.IFNA(VLOOKUP(A62,'Personnel List'!A$1:E$1284,4,FALSE),"") | D62: =IF(A62<>"",IF(D62<>"",D62,NOW()),"") | E62: =IFERROR(VLOOKUP(A62,G:I,3,FALSE),"Onsite") -> Onsite | I62: =IF(G902<>"",IF(I62<>"",I62,NOW()),"") | J62: =SUBSTITUTE(A62,"NC","") | L62: Newman, Bella | M62: Mitchell, Cheynne | N62: =_xlfn.IFNA(VLOOKUP(A62,'Personnel List'!A$1:F$1284,6,FALSE),"")
B63: =_xlfn.IFNA(VLOOKUP(A63,'Personnel List'!A$1:E$1284,5,FALSE),"") | C63: =_xlfn.IFNA(VLOOKUP(A63,'Personnel List'!A$1:E$1284,4,FALSE),"") | D63: =IF(A63<>"",IF(D63<>"",D63,NOW()),"") | E63: =IFERROR(VLOOKUP(A63,G:I,3,FALSE),"Onsite") -> Onsite | I63: =IF(G903<>"",IF(I63<>"",I63,NOW()),"") | J63: =SUBSTITUTE(A63,"NC","") | L63: O'Connell, Reece | M63: Mulhall, Martin | N63: =_xlfn.IFNA(VLOOKUP(A63,'Personnel List'!A$1:F$1284,6,FALSE),"")
B64: =_xlfn.IFNA(VLOOKUP(A64,'Personnel List'!A$1:E$1284,5,FALSE),"") | C64: =_xlfn.IFNA(VLOOKUP(A64,'Personnel List'!A$1:E$1284,4,FALSE),"") | D64: =IF(A64<>"",IF(D64<>"",D64,NOW()),"") | E64: =IFERROR(VLOOKUP(A64,G:I,3,FALSE),"Onsite") -> Onsite | I64: =IF(G904<>"",IF(I64<>"",I64,NOW()),"") | J64: =SUBSTITUTE(A64,"NC","") | L64: Paki, Kiel | M64: Mulligan, Wesley | N64: =_xlfn.IFNA(VLOOKUP(A64,'Personnel List'!A$1:F$1284,6,FALSE),"")
B65: =_xlfn.IFNA(VLOOKUP(A65,'Personnel List'!A$1:E$1284,5,FALSE),"") | C65: =_xlfn.IFNA(VLOOKUP(A65,'Personnel List'!A$1:E$1284,4,FALSE),"") | D65: =IF(A65<>"",IF(D65<>"",D65,NOW()),"") | E65: =IFERROR(VLOOKUP(A65,G:I,3,FALSE),"Onsite") -> Onsite | I65: =IF(G905<>"",IF(I65<>"",I65,NOW()),"") | J65: =SUBSTITUTE(A65,"NC","") | L65: Parrott, Kevin | M65: Nakayama, Sumika | N65: =_xlfn.IFNA(VLOOKUP(A65,'Personnel List'!A$1:F$1284,6,FALSE),"")
B66: =_xlfn.IFNA(VLOOKUP(A66,'Personnel List'!A$1:E$1284,5,FALSE),"") | C66: =_xlfn.IFNA(VLOOKUP(A66,'Personnel List'!A$1:E$1284,4,FALSE),"") | D66: =IF(A66<>"",IF(D66<>"",D66,NOW()),"") | E66: =IFERROR(VLOOKUP(A66,G:I,3,FALSE),"Onsite") -> Onsite | I66: =IF(G906<>"",IF(I66<>"",I66,NOW()),"") | J66: =SUBSTITUTE(A66,"NC","") | L66: Pendreigh, Jason | M66: Neal, Adam | N66: =_xlfn.IFNA(VLOOKUP(A66,'Personnel List'!A$1:F$1284,6,FALSE),"")
... B92: =_xlfn.IFNA(VLOOKUP(A92,'Personnel List'!A$1:E$1284,5,FALSE),"") | C92: =_xlfn.IFNA(VLOOKUP(A92,'Personnel List'!A$1:E$1284,4,FALSE),"") | D92: =IF(A92<>"",IF(D92<>"",D92,NOW()),"") | E92: =IFERROR(VLOOKUP(A92,G:I,3,FALSE),"Onsite") -> Onsite | I92: =IF(G932<>"",IF(I92<>"",I92,NOW()),"") | J92: =SUBSTITUTE(A92,"NC","") | L92: Zarekar, Chandrakant | M92: Strong, Deke | N92: =_xlfn.IFNA(VLOOKUP(A92,'Personnel List'!A$1:F$1284,6,FALSE),"")
B93: =_xlfn.IFNA(VLOOKUP(A93,'Personnel List'!A$1:E$1284,5,FALSE),"") | C93: =_xlfn.IFNA(VLOOKUP(A93,'Personnel List'!A$1:E$1284,4,FALSE),"") | D93: =IF(A93<>"",IF(D93<>"",D93,NOW()),"") | E93: =IFERROR(VLOOKUP(A93,G:I,3,FALSE),"Onsite") -> Onsite | I93: =IF(G933<>"",IF(I93<>"",I93,NOW()),"") | J93: =SUBSTITUTE(A93,"NC","") | L93: 0 | M93: Sujono, Ilya | N93: =_xlfn.IFNA(VLOOKUP(A93,'Personnel List'!A$1:F$1284,6,FALSE),"")
B94: =_xlfn.IFNA(VLOOKUP(A94,'Personnel List'!A$1:E$1284,5,FALSE),"") | C94: =_xlfn.IFNA(VLOOKUP(A94,'Personnel List'!A$1:E$1284,4,FALSE),"") | D94: =IF(A94<>"",IF(D94<>"",D94,NOW()),"") | E94: =IFERROR(VLOOKUP(A94,G:I,3,FALSE),"Onsite") -> Onsite | I94: =IF(G934<>"",IF(I94<>"",I94,NOW()),"") | J94: =SUBSTITUTE(A94,"NC","") | L94: 0 | M94: Taura, Jeremiah | N94: =_xlfn.IFNA(VLOOKUP(A94,'Personnel List'!A$1:F$1284,6,FALSE),"")
B95: =_xlfn.IFNA(VLOOKUP(A95,'Personnel List'!A$1:E$1284,5,FALSE),"") | C95: =_xlfn.IFNA(VLOOKUP(A95,'Personnel List'!A$1:E$1284,4,FALSE),"") | D95: =IF(A95<>"",IF(D95<>"",D95,NOW()),"") | E95: =IFERROR(VLOOKUP(A95,G:I,3,FALSE),"Onsite") -> Onsite | I95: =IF(G935<>"",IF(I95<>"",I95,NOW()),"") | J95: =SUBSTITUTE(A95,"NC","") | L95: 0 | M95: Tawaka, Ohomairangi | N95: =_xlfn.IFNA(VLOOKUP(A95,'Personnel List'!A$1:F$1284,6,FALSE),"")
B96: =_xlfn.IFNA(VLOOKUP(A96,'Personnel List'!A$1:E$1284,5,FALSE),"") | C96: =_xlfn.IFNA(VLOOKUP(A96,'Personnel List'!A$1:E$1284,4,FALSE),"") | D96: =IF(A96<>"",IF(D96<>"",D96,NOW()),"") | E96: =IFERROR(VLOOKUP(A96,G:I,3,FALSE),"Onsite") -> Onsite | I96: =IF(G936<>"",IF(I96<>"",I96,NOW()),"") | J96: =SUBSTITUTE(A96,"NC","") | L96: 0 | M96: Tawaka, Russell-Kingi | N96: =_xlfn.IFNA(VLOOKUP(A96,'Personnel List'!A$1:F$1284,6,FALSE),"")
B97: =_xlfn.IFNA(VLOOKUP(A97,'Personnel List'!A$1:E$1284,5,FALSE),"") | C97: =_xlfn.IFNA(VLOOKUP(A97,'Personnel List'!A$1:E$1284,4,FALSE),"") | D97: =IF(A97<>"",IF(D97<>"",D97,NOW()),"") | E97: =IFERROR(VLOOKUP(A97,G:I,3,FALSE),"Onsite") -> Onsite | I97: =IF(G937<>"",IF(I97<>"",I97,NOW()),"") | J97: =SUBSTITUTE(A97,"NC","") | L97: 0 | M97: Tioke, Leon | N97: =_xlfn.IFNA(VLOOKUP(A97,'Personnel List'!A$1:F$1284,6,FALSE),"")
B98: =_xlfn.IFNA(VLOOKUP(A98,'Personnel List'!A$1:E$1284,5,FALSE),"") | C98: =_xlfn.IFNA(VLOOKUP(A98,'Personnel List'!A$1:E$1284,4,FALSE),"") | D98: =IF(A98<>"",IF(D98<>"",D98,NOW()),"") | E98: =IFERROR(VLOOKUP(A98,G:I,3,FALSE),"Onsite") -> Onsite | I98: =IF(G938<>"",IF(I98<>"",I98,NOW()),"") | J98: =SUBSTITUTE(A98,"NC","") | L98: 0 | M98: Walker, Jarred | N98: =_xlfn.IFNA(VLOOKUP(A98,'Personnel List'!A$1:F$1284,6,FALSE),"")
B99: =_xlfn.IFNA(VLOOKUP(A99,'Personnel List'!A$1:E$1284,5,FALSE),"") | C99: =_xlfn.IFNA(VLOOKUP(A99,'Personnel List'!A$1:E$1284,4,FALSE),"") | D99: =IF(A99<>"",IF(D99<>"",D99,NOW()),"") | E99: =IFERROR(VLOOKUP(A99,G:I,3,FALSE),"Onsite") -> Onsite | I99: =IF(G939<>"",IF(I99<>"",I99,NOW()),"") | J99: =SUBSTITUTE(A99,"NC","") | L99: 0 | M99: Walker-Smith, Grace | N99: =_xlfn.IFNA(VLOOKUP(A99,'Personnel List'!A$1:F$1284,6,FALSE),"")
B100: =_xlfn.IFNA(VLOOKUP(A100,'Personnel List'!A$1:E$1284,5,FALSE),"") | C100: =_xlfn.IFNA(VLOOKUP(A100,'Personnel List'!A$1:E$1284,4,FALSE),"") | D100: =IF(A100<>"",IF(D100<>"",D100,NOW()),"") | E100: =IFERROR(VLOOKUP(A100,G:I,3,FALSE),"Onsite") -> Onsite | I100: =IF(G940<>"",IF(I100<>"",I100,NOW()),"") | J100: =SUBSTITUTE(A100,"NC","") | L100: 0 | M100: Wang, Jian | N100: =_xlfn.IFNA(VLOOKUP(A100,'Personnel List'!A$1:F$1284,6,FALSE),"")
B101: =_xlfn.IFNA(VLOOKUP(A101,'Personnel List'!A$1:E$1284,5,FALSE),"") | C101: =_xlfn.IFNA(VLOOKUP(A101,'Personnel List'!A$1:E$1284,4,FALSE),"") | D101: =IF(A101<>"",IF(D101<>"",D101,NOW()),"") | E101: =IFERROR(VLOOKUP(A101,G:I,3,FALSE),"Onsite") -> Onsite | I101: =IF(G941<>"",IF(I101<>"",I101,NOW()),"") | J101: =SUBSTITUTE(A101,"NC","") | L101: 0 | M101: Weichert, Benjamin | N101: =_xlfn.IFNA(VLOOKUP(A101,'Personnel List'!A$1:F$1284,6,FALSE),"")
B102: =_xlfn.IFNA(VLOOKUP(A102,'Personnel List'!A$1:E$1284,5,FALSE),"") | C102: =_xlfn.IFNA(VLOOKUP(A102,'Personnel List'!A$1:E$1284,4,FALSE),"") | D102: =IF(A102<>"",IF(D102<>"",D102,NOW()),"") | E102: =IFERROR(VLOOKUP(A102,G:I,3,FALSE),"Onsite") -> Onsite | I102: =IF(G942<>"",IF(I102<>"",I102,NOW()),"") | J102: =SUBSTITUTE(A102,"NC","") | L102: 0 | M102: Zarekar, Chandrakant | N102: =_xlfn.IFNA(VLOOKUP(A102,'Personnel List'!A$1:F$1284,6,FALSE),"")
B103: =_xlfn.IFNA(VLOOKUP(A103,'Personnel List'!A$1:E$1284,5,FALSE),"") | C103: =_xlfn.IFNA(VLOOKUP(A103,'Personnel List'!A$1:E$1284,4,FALSE),"") | D103: =IF(A103<>"",IF(D103<>"",D103,NOW()),"") | E103: =IFERROR(VLOOKUP(A103,G:I,3,FALSE),"Onsite") -> Onsite | I103: =IF(G943<>"",IF(I103<>"",I103,NOW()),"") | J103: =SUBSTITUTE(A103,"NC","") | L103: 0 | M103: Zhang, Weixin | N103: =_xlfn.IFNA(VLOOKUP(A103,'Personnel List'!A$1:F$1284,6,FALSE),"")
B104: =_xlfn.IFNA(VLOOKUP(A104,'Personnel List'!A$1:E$1284,5,FALSE),"") | C104: =_xlfn.IFNA(VLOOKUP(A104,'Personnel List'!A$1:E$1284,4,FALSE),"") | D104: =IF(A104<>"",IF(D104<>"",D104,NOW()),"") | E104: =IFERROR(VLOOKUP(A104,G:I,3,FALSE),"Onsite") -> Onsite | I104: =IF(G944<>"",IF(I104<>"",I104,NOW()),"") | J104: =SUBSTITUTE(A104,"NC","") | L104: 0 | N104: =_xlfn.IFNA(VLOOKUP(A104,'Personnel List'!A$1:F$1284,6,FALSE),"")
B105: =_xlfn.IFNA(VLOOKUP(A105,'Personnel List'!A$1:E$1284,5,FALSE),"") | C105: =_xlfn.IFNA(VLOOKUP(A105,'Personnel List'!A$1:E$1284,4,FALSE),"") | D105: =IF(A105<>"",IF(D105<>"",D105,NOW()),"") | E105: =IFERROR(VLOOKUP(A105,G:I,3,FALSE),"Onsite") -> Onsite | I105: =IF(G945<>"",IF(I105<>"",I105,NOW()),"") | J105: =SUBSTITUTE(A105,"NC","") | L105: 0 | N105: =_xlfn.IFNA(VLOOKUP(A105,'Personnel List'!A$1:F$1284,6,FALSE),"")
B106: =_xlfn.IFNA(VLOOKUP(A106,'Personnel List'!A$1:E$1284,5,FALSE),"") | C106: =_xlfn.IFNA(VLOOKUP(A106,'Personnel List'!A$1:E$1284,4,FALSE),"") | D106: =IF(A106<>"",IF(D106<>"",D106,NOW()),"") | E106: =IFERROR(VLOOKUP(A106,G:I,3,FALSE),"Onsite") -> Onsite | I106: =IF(G946<>"",IF(I106<>"",I106,NOW()),"") | J106: =SUBSTITUTE(A106,"NC","") | L106: 0 | N106: =_xlfn.IFNA(VLOOKUP(A106,'Personnel List'!A$1:F$1284,6,FALSE),"")
B107: =_xlfn.IFNA(VLOOKUP(A107,'Personnel List'!A$1:E$1284,5,FALSE),"") | C107: =_xlfn.IFNA(VLOOKUP(A107,'Personnel List'!A$1:E$1284,4,FALSE),"") | D107: =IF(A107<>"",IF(D107<>"",D107,NOW()),"") | E107: =IFERROR(VLOOKUP(A107,G:I,3,FALSE),"Onsite") -> Onsite | I107: =IF(G947<>"",IF(I107<>"",I107,NOW()),"") | J107: =SUBSTITUTE(A107,"NC","") | L107: 0 | N107: =_xlfn.IFNA(VLOOKUP(A107,'Personnel List'!A$1:F$1284,6,FALSE),"")
B108: =_xlfn.IFNA(VLOOKUP(A108,'Personnel List'!A$1:E$1284,5,FALSE),"") | C108: =_xlfn.IFNA(VLOOKUP(A108,'Personnel List'!A$1:E$1284,4,FALSE),"") | D108: =IF(A108<>"",IF(D108<>"",D108,NOW()),"") | E108: =IFERROR(VLOOKUP(A108,G:I,3,FALSE),"Onsite") -> Onsite | I108: =IF(G948<>"",IF(I108<>"",I108,NOW()),"") | J108: =SUBSTITUTE(A108,"NC","") | L108: 0 | N108: =_xlfn.IFNA(VLOOKUP(A108,'Personnel List'!A$1:F$1284,6,FALSE),"")
B109: =_xlfn.IFNA(VLOOKUP(A109,'Personnel List'!A$1:E$1284,5,FALSE),"") | C109: =_xlfn.IFNA(VLOOKUP(A109,'Personnel List'!A$1:E$1284,4,FALSE),"") | D109: =IF(A109<>"",IF(D109<>"",D109,NOW()),"") | E109: =IFERROR(VLOOKUP(A109,G:I,3,FALSE),"Onsite") -> Onsite | I109: =IF(G949<>"",IF(I109<>"",I109,NOW()),"") | J109: =SUBSTITUTE(A109,"NC","") | L109: 0 | N109: =_xlfn.IFNA(VLOOKUP(A109,'Personnel List'!A$1:F$1284,6,FALSE),"")
B110: =_xlfn.IFNA(VLOOKUP(A110,'Personnel List'!A$1:E$1284,5,FALSE),"") | C110: =_xlfn.IFNA(VLOOKUP(A110,'Personnel List'!A$1:E$1284,4,FALSE),"") | D110: =IF(A110<>"",IF(D110<>"",D110,NOW()),"") | E110: =IFERROR(VLOOKUP(A110,G:I,3,FALSE),"Onsite") -> Onsite | I110: =IF(G950<>"",IF(I110<>"",I110,NOW()),"") | J110: =SUBSTITUTE(A110,"NC","") | L110: 0 | N110: =_xlfn.IFNA(VLOOKUP(A110,'Personnel List'!A$1:F$1284,6,FALSE),"")
B111: =_xlfn.IFNA(VLOOKUP(A111,'Personnel List'!A$1:E$1284,5,FALSE),"") | C111: =_xlfn.IFNA(VLOOKUP(A111,'Personnel List'!A$1:E$1284,4,FALSE),"") | D111: =IF(A111<>"",IF(D111<>"",D111,NOW()),"") | E111: =IFERROR(VLOOKUP(A111,G:I,3,FALSE),"Onsite") -> Onsite | I111: =IF(G951<>"",IF(I111<>"",I111,NOW()),"") | J111: =SUBSTITUTE(A111,"NC","") | L111: 0 | N111: =_xlfn.IFNA(VLOOKUP(A111,'Personnel List'!A$1:F$1284,6,FALSE),"")
B112: =_xlfn.IFNA(VLOOKUP(A112,'Personnel List'!A$1:E$1284,5,FALSE),"") | C112: =_xlfn.IFNA(VLOOKUP(A112,'Personnel List'!A$1:E$1284,4,FALSE),"") | D112: =IF(A112<>"",IF(D112<>"",D112,NOW()),"") | E112: =IFERROR(VLOOKUP(A112,G:I,3,FALSE),"Onsite") -> Onsite | I112: =IF(G952<>"",IF(I112<>"",I112,NOW()),"") | J112: =SUBSTITUTE(A112,"NC","") | L112: 0 | N112: =_xlfn.IFNA(VLOOKUP(A112,'Personnel List'!A$1:F$1284,6,FALSE),"")
B113: =_xlfn.IFNA(VLOOKUP(A113,'Personnel List'!A$1:E$1284,5,FALSE),"") | C113: =_xlfn.IFNA(VLOOKUP(A113,'Personnel List'!A$1:E$1284,4,FALSE),"") | D113: =IF(A113<>"",IF(D113<>"",D113,NOW()),"") | E113: =IFERROR(VLOOKUP(A113,G:I,3,FALSE),"Onsite") -> Onsite | I113: =IF(G953<>"",IF(I113<>"",I113,NOW()),"") | J113: =SUBSTITUTE(A113,"NC","") | L113: 0 | N113: =_xlfn.IFNA(VLOOKUP(A113,'Personnel List'!A$1:F$1284,6,FALSE),"")
B114: =_xlfn.IFNA(VLOOKUP(A114,'Personnel List'!A$1:E$1284,5,FALSE),"") | C114: =_xlfn.IFNA(VLOOKUP(A114,'Personnel List'!A$1:E$1284,4,FALSE),"") | D114: =IF(A114<>"",IF(D114<>"",D114,NOW()),"") | E114: =IFERROR(VLOOKUP(A114,G:I,3,FALSE),"Onsite") -> Onsite | I114: =IF(G954<>"",IF(I114<>"",I114,NOW()),"") | J114: =SUBSTITUTE(A114,"NC","") | L114: 0 | N114: =_xlfn.IFNA(VLOOKUP(A114,'Personnel List'!A$1:F$1284,6,FALSE),"")
B115: =_xlfn.IFNA(VLOOKUP(A115,'Personnel List'!A$1:E$1284,5,FALSE),"") | C115: =_xlfn.IFNA(VLOOKUP(A115,'Personnel List'!A$1:E$1284,4,FALSE),"") | D115: =IF(A115<>"",IF(D115<>"",D115,NOW()),"") | E115: =IFERROR(VLOOKUP(A115,G:I,3,FALSE),"Onsite") -> Onsite | I115: =IF(G955<>"",IF(I115<>"",I115,NOW()),"") | J115: =SUBSTITUTE(A115,"NC","") | L115: 0 | N115: =_xlfn.IFNA(VLOOKUP(A115,'Personnel List'!A$1:F$1284,6,FALSE),"")
... B876: =_xlfn.IFNA(VLOOKUP(A876,'Personnel List'!A$1:E$1284,5,FALSE),"") | C876: =_xlfn.IFNA(VLOOKUP(A876,'Personnel List'!A$1:E$1284,4,FALSE),"") | D876: =IF(A876<>"",IF(D876<>"",D876,NOW()),"") | E876: =IFERROR(VLOOKUP(A876,G:I,3,FALSE),"Onsite") -> Onsite | I876: =IF(G1716<>"",IF(I876<>"",I876,NOW()),"") | J876: =SUBSTITUTE(A876,"NC","") | L876: 0 | N876: =_xlfn.IFNA(VLOOKUP(A876,'Personnel List'!A$1:F$1284,6,FALSE),"")
I877: =IF(G1717<>"",IF(I877<>"",I877,NOW()),"") | J877: =SUBSTITUTE(A877,"NC","") | L877: 0
L878: 0
L879: 0
L880: 0
L881: 0
L882: 0
L883: 0
L884: 0
L885: 0
L886: 0
L887: 0
L888: 0
L889: 0
... L989: 0

Sheet Wed NS
A1: Scan ID | B1: Name | C1: Company Name | D1: Time In | E1: Time Out | G1: Scan Out | I1: Timestamp | J1: SAP Number | L1: Not Scanned Yet | M1: NS | N1: Reverse Name
B2: =_xlfn.IFNA(VLOOKUP(A2,'Personnel List'!A$1:E$1284,5,FALSE),"") | C2: =_xlfn.IFNA(VLOOKUP(A2,'Personnel List'!A$1:E$1284,4,FALSE),"") | D2: =IF(A2<>"",IF(D2<>"",D2,NOW()),"") | E2: =IFERROR(VLOOKUP(A2,G:I,3,FALSE),"Onsite") -> Onsite | I2: =IF(G2<>"",IF(I2<>"",I2,NOW()),"") | J2: =SUBSTITUTE(A2,"NC","") | L2: {=_xlfn._xlws.FILTER(M2:M1000,(ISNA(MATCH(M2:M1000,N2:N1000,0))),"")} -> Allsopp, Andrew | M2: {=_xlfn._xlws.FILTER('Wed Data'!E13:E895,ISNUMBER(_xlfn.XMATCH('Wed Data'!D13:D895,M1)))} -> Allsopp, Andrew | N2: =_xlfn.IFNA(VLOOKUP(A2,'Personnel List'!A$1:F$1284,6,FALSE),"")
B3: =_xlfn.IFNA(VLOOKUP(A3,'Personnel List'!A$1:E$1284,5,FALSE),"") | C3: =_xlfn.IFNA(VLOOKUP(A3,'Personnel List'!A$1:E$1284,4,FALSE),"") | D3: =IF(A3<>"",IF(D3<>"",D3,NOW()),"") | E3: =IFERROR(VLOOKUP(A3,G:I,3,FALSE),"Onsite") -> Onsite | I3: =IF(G3<>"",IF(I3<>"",I3,NOW()),"") | J3: =SUBSTITUTE(A3,"NC","") | L3: Aranda, Mark | M3: Aranda, Mark | N3: =_xlfn.IFNA(VLOOKUP(A3,'Personnel List'!A$1:F$1284,6,FALSE),"")
B4: =_xlfn.IFNA(VLOOKUP(A4,'Personnel List'!A$1:E$1284,5,FALSE),"") | C4: =_xlfn.IFNA(VLOOKUP(A4,'Personnel List'!A$1:E$1284,4,FALSE),"") | D4: =IF(A4<>"",IF(D4<>"",D4,NOW()),"") | E4: =IFERROR(VLOOKUP(A4,G:I,3,FALSE),"Onsite") -> Onsite | I4: =IF(G4<>"",IF(I4<>"",I4,NOW()),"") | J4: =SUBSTITUTE(A4,"NC","") | L4: Batinga, Renald | M4: Batinga, Renald | N4: =_xlfn.IFNA(VLOOKUP(A4,'Personnel List'!A$1:F$1284,6,FALSE),"")
B5: =_xlfn.IFNA(VLOOKUP(A5,'Personnel List'!A$1:E$1284,5,FALSE),"") | C5: =_xlfn.IFNA(VLOOKUP(A5,'Personnel List'!A$1:E$1284,4,FALSE),"") | D5: =IF(A5<>"",IF(D5<>"",D5,NOW()),"") | E5: =IFERROR(VLOOKUP(A5,G:I,3,FALSE),"Onsite") -> Onsite | I5: =IF(G5<>"",IF(I5<>"",I5,NOW()),"") | J5: =SUBSTITUTE(A5,"NC","") | L5: Beauchamp, Peter | M5: Beauchamp, Peter | N5: =_xlfn.IFNA(VLOOKUP(A5,'Personnel List'!A$1:F$1284,6,FALSE),"")
B6: =_xlfn.IFNA(VLOOKUP(A6,'Personnel List'!A$1:E$1284,5,FALSE),"") | C6: =_xlfn.IFNA(VLOOKUP(A6,'Personnel List'!A$1:E$1284,4,FALSE),"") | D6: =IF(A6<>"",IF(D6<>"",D6,NOW()),"") | E6: =IFERROR(VLOOKUP(A6,G:I,3,FALSE),"Onsite") -> Onsite | I6: =IF(G6<>"",IF(I6<>"",I6,NOW()),"") | J6: =SUBSTITUTE(A6,"NC","") | L6: Beeston, Lewis | M6: Beeston, Lewis | N6: =_xlfn.IFNA(VLOOKUP(A6,'Personnel List'!A$1:F$1284,6,FALSE),"")
B7: =_xlfn.IFNA(VLOOKUP(A7,'Personnel List'!A$1:E$1284,5,FALSE),"") | C7: =_xlfn.IFNA(VLOOKUP(A7,'Personnel List'!A$1:E$1284,4,FALSE),"") | D7: =IF(A7<>"",IF(D7<>"",D7,NOW()),"") | E7: =IFERROR(VLOOKUP(A7,G:I,3,FALSE),"Onsite") -> Onsite | I7: =IF(G7<>"",IF(I7<>"",I7,NOW()),"") | J7: =SUBSTITUTE(A7,"NC","") | L7: Boggetti, Santiago | M7: Boggetti, Santiago | N7: =_xlfn.IFNA(VLOOKUP(A7,'Personnel List'!A$1:F$1284,6,FALSE),"")
B8: =_xlfn.IFNA(VLOOKUP(A8,'Personnel List'!A$1:E$1284,5,FALSE),"") | C8: =_xlfn.IFNA(VLOOKUP(A8,'Personnel List'!A$1:E$1284,4,FALSE),"") | D8: =IF(A8<>"",IF(D8<>"",D8,NOW()),"") | E8: =IFERROR(VLOOKUP(A8,G:I,3,FALSE),"Onsite") -> Onsite | I8: =IF(G8<>"",IF(I8<>"",I8,NOW()),"") | J8: =SUBSTITUTE(A8,"NC","") | L8: Briney, John | M8: Briney, John | N8: =_xlfn.IFNA(VLOOKUP(A8,'Personnel List'!A$1:F$1284,6,FALSE),"")
B9: =_xlfn.IFNA(VLOOKUP(A9,'Personnel List'!A$1:E$1284,5,FALSE),"") | C9: =_xlfn.IFNA(VLOOKUP(A9,'Personnel List'!A$1:E$1284,4,FALSE),"") | D9: =IF(A9<>"",IF(D9<>"",D9,NOW()),"") | E9: =IFERROR(VLOOKUP(A9,G:I,3,FALSE),"Onsite") -> Onsite | I9: =IF(G9<>"",IF(I9<>"",I9,NOW()),"") | J9: =SUBSTITUTE(A9,"NC","") | L9: Cowley, Jason Anthony | M9: Cowley, Jason Anthony | N9: =_xlfn.IFNA(VLOOKUP(A9,'Personnel List'!A$1:F$1284,6,FALSE),"")
B10: =_xlfn.IFNA(VLOOKUP(A10,'Personnel List'!A$1:E$1284,5,FALSE),"") | C10: =_xlfn.IFNA(VLOOKUP(A10,'Personnel List'!A$1:E$1284,4,FALSE),"") | D10: =IF(A10<>"",IF(D10<>"",D10,NOW()),"") | E10: =IFERROR(VLOOKUP(A10,G:I,3,FALSE),"Onsite") -> Onsite | I10: =IF(G10<>"",IF(I10<>"",I10,NOW()),"") | J10: =SUBSTITUTE(A10,"NC","") | L10: Dunkley, Daniel | M10: Dunkley, Daniel | N10: =_xlfn.IFNA(VLOOKUP(A10,'Personnel List'!A$1:F$1284,6,FALSE),"")
B11: =_xlfn.IFNA(VLOOKUP(A11,'Personnel List'!A$1:E$1284,5,FALSE),"") | C11: =_xlfn.IFNA(VLOOKUP(A11,'Personnel List'!A$1:E$1284,4,FALSE),"") | D11: =IF(A11<>"",IF(D11<>"",D11,NOW()),"") | E11: =IFERROR(VLOOKUP(A11,G:I,3,FALSE),"Onsite") -> Onsite | I11: =IF(G11<>"",IF(I11<>"",I11,NOW()),"") | J11: =SUBSTITUTE(A11,"NC","") | L11: Fussell, Bradley | M11: Fussell, Bradley | N11: =_xlfn.IFNA(VLOOKUP(A11,'Personnel List'!A$1:F$1284,6,FALSE),"")
B12: =_xlfn.IFNA(VLOOKUP(A12,'Personnel List'!A$1:E$1284,5,FALSE),"") | C12: =_xlfn.IFNA(VLOOKUP(A12,'Personnel List'!A$1:E$1284,4,FALSE),"") | D12: =IF(A12<>"",IF(D12<>"",D12,NOW()),"") | E12: =IFERROR(VLOOKUP(A12,G:I,3,FALSE),"Onsite") -> Onsite | I12: =IF(G12<>"",IF(I12<>"",I12,NOW()),"") | J12: =SUBSTITUTE(A12,"NC","") | L12: George, Charles | M12: George, Charles | N12: =_xlfn.IFNA(VLOOKUP(A12,'Personnel List'!A$1:F$1284,6,FALSE),"")
B13: =_xlfn.IFNA(VLOOKUP(A13,'Personnel List'!A$1:E$1284,5,FALSE),"") | C13: =_xlfn.IFNA(VLOOKUP(A13,'Personnel List'!A$1:E$1284,4,FALSE),"") | D13: =IF(A13<>"",IF(D13<>"",D13,NOW()),"") | E13: =IFERROR(VLOOKUP(A13,G:I,3,FALSE),"Onsite") -> Onsite | I13: =IF(G13<>"",IF(I13<>"",I13,NOW()),"") | J13: =SUBSTITUTE(A13,"NC","") | L13: Kim, Minsung | M13: Kim, Minsung | N13: =_xlfn.IFNA(VLOOKUP(A13,'Personnel List'!A$1:F$1284,6,FALSE),"")
B14: =_xlfn.IFNA(VLOOKUP(A14,'Personnel List'!A$1:E$1284,5,FALSE),"") | C14: =_xlfn.IFNA(VLOOKUP(A14,'Personnel List'!A$1:E$1284,4,FALSE),"") | D14: =IF(A14<>"",IF(D14<>"",D14,NOW()),"") | E14: =IFERROR(VLOOKUP(A14,G:I,3,FALSE),"Onsite") -> Onsite | I14: =IF(G14<>"",IF(I14<>"",I14,NOW()),"") | J14: =SUBSTITUTE(A14,"NC","") | L14: Koch, Adrian | M14: Koch, Adrian | N14: =_xlfn.IFNA(VLOOKUP(A14,'Personnel List'!A$1:F$1284,6,FALSE),"")
... B32: =_xlfn.IFNA(VLOOKUP(A32,'Personnel List'!A$1:E$1284,5,FALSE),"") | C32: =_xlfn.IFNA(VLOOKUP(A32,'Personnel List'!A$1:E$1284,4,FALSE),"") | D32: =IF(A32<>"",IF(D32<>"",D32,NOW()),"") | E32: =IFERROR(VLOOKUP(A32,G:I,3,FALSE),"Onsite") -> Onsite | I32: =IF(G32<>"",IF(I32<>"",I32,NOW()),"") | J32: =SUBSTITUTE(A32,"NC","") | L32: Suckling, Kim | M32: Suckling, Kim | N32: =_xlfn.IFNA(VLOOKUP(A32,'Personnel List'!A$1:F$1284,6,FALSE),"")
B33: =_xlfn.IFNA(VLOOKUP(A33,'Personnel List'!A$1:E$1284,5,FALSE),"") | E33: =IFERROR(VLOOKUP(A33,G:I,3,FALSE),"Onsite") -> Onsite | I33: =IF(G33<>"",IF(I33<>"",I33,NOW()),"") | J33: =SUBSTITUTE(A33,"NC","") | L33: Triplett, Warren | M33: Triplett, Warren | N33: =_xlfn.IFNA(VLOOKUP(A33,'Personnel List'!A$1:F$1284,6,FALSE),"")
B34: =_xlfn.IFNA(VLOOKUP(A34,'Personnel List'!A$1:E$1284,5,FALSE),"") | C34: =_xlfn.IFNA(VLOOKUP(A34,'Personnel List'!A$1:E$1284,4,FALSE),"") | D34: =IF(A34<>"",IF(D34<>"",D34,NOW()),"") | E34: =IFERROR(VLOOKUP(A34,G:I,3,FALSE),"Onsite") -> Onsite | I34: =IF(G34<>"",IF(I34<>"",I34,NOW()),"") | J34: =SUBSTITUTE(A34,"NC","") | L34: Vervaet, Wouter | M34: Vervaet, Wouter | N34: =_xlfn.IFNA(VLOOKUP(A34,'Personnel List'!A$1:F$1284,6,FALSE),"")
B35: =_xlfn.IFNA(VLOOKUP(A35,'Personnel List'!A$1:E$1284,5,FALSE),"") | C35: =_xlfn.IFNA(VLOOKUP(A35,'Personnel List'!A$1:E$1284,4,FALSE),"") | D35: =IF(A35<>"",IF(D35<>"",D35,NOW()),"") | E35: =IFERROR(VLOOKUP(A35,G:I,3,FALSE),"Onsite") -> Onsite | I35: =IF(G35<>"",IF(I35<>"",I35,NOW()),"") | J35: =SUBSTITUTE(A35,"NC","") | L35: Waiwiri, Hohepa | M35: Waiwiri, Hohepa | N35: =_xlfn.IFNA(VLOOKUP(A35,'Personnel List'!A$1:F$1284,6,FALSE),"")
B36: =_xlfn.IFNA(VLOOKUP(A36,'Personnel List'!A$1:E$1284,5,FALSE),"") | C36: =_xlfn.IFNA(VLOOKUP(A36,'Personnel List'!A$1:E$1284,4,FALSE),"") | D36: =IF(A36<>"",IF(D36<>"",D36,NOW()),"") | E36: =IFERROR(VLOOKUP(A36,G:I,3,FALSE),"Onsite") -> Onsite | I36: =IF(G36<>"",IF(I36<>"",I36,NOW()),"") | J36: =SUBSTITUTE(A36,"NC","") | L36: Wigley, Robert | M36: Wigley, Robert | N36: =_xlfn.IFNA(VLOOKUP(A36,'Personnel List'!A$1:F$1284,6,FALSE),"")
B37: =_xlfn.IFNA(VLOOKUP(A37,'Personnel List'!A$1:E$1284,5,FALSE),"") | C37: =_xlfn.IFNA(VLOOKUP(A37,'Personnel List'!A$1:E$1284,4,FALSE),"") | D37: =IF(A37<>"",IF(D37<>"",D37,NOW()),"") | E37: =IFERROR(VLOOKUP(A37,G:I,3,FALSE),"Onsite") -> Onsite | I37: =IF(G37<>"",IF(I37<>"",I37,NOW()),"") | J37: =SUBSTITUTE(A37,"NC","") | L37: 0 | N37: =_xlfn.IFNA(VLOOKUP(A37,'Personnel List'!A$1:F$1284,6,FALSE),"")
B38: =_xlfn.IFNA(VLOOKUP(A38,'Personnel List'!A$1:E$1284,5,FALSE),"") | C38: =_xlfn.IFNA(VLOOKUP(A38,'Personnel List'!A$1:E$1284,4,FALSE),"") | D38: =IF(A38<>"",IF(D38<>"",D38,NOW()),"") | E38: =IFERROR(VLOOKUP(A38,G:I,3,FALSE),"Onsite") -> Onsite | I38: =IF(G38<>"",IF(I38<>"",I38,NOW()),"") | J38: =SUBSTITUTE(A38,"NC","") | L38: 0 | N38: =_xlfn.IFNA(VLOOKUP(A38,'Personnel List'!A$1:F$1284,6,FALSE),"")
B39: =_xlfn.IFNA(VLOOKUP(A39,'Personnel List'!A$1:E$1284,5,FALSE),"") | C39: =_xlfn.IFNA(VLOOKUP(A39,'Personnel List'!A$1:E$1284,4,FALSE),"") | D39: =IF(A39<>"",IF(D39<>"",D39,NOW()),"") | E39: =IFERROR(VLOOKUP(A39,G:I,3,FALSE),"Onsite") -> Onsite | I39: =IF(G39<>"",IF(I39<>"",I39,NOW()),"") | J39: =SUBSTITUTE(A39,"NC","") | L39: 0 | N39: =_xlfn.IFNA(VLOOKUP(A39,'Personnel List'!A$1:F$1284,6,FALSE),"")
B40: =_xlfn.IFNA(VLOOKUP(A40,'Personnel List'!A$1:E$1284,5,FALSE),"") | C40: =_xlfn.IFNA(VLOOKUP(A40,'Personnel List'!A$1:E$1284,4,FALSE),"") | D40: =IF(A40<>"",IF(D40<>"",D40,NOW()),"") | E40: =IFERROR(VLOOKUP(A40,G:I,3,FALSE),"Onsite") -> Onsite | I40: =IF(G40<>"",IF(I40<>"",I40,NOW()),"") | J40: =SUBSTITUTE(A40,"NC","") | L40: 0 | N40: =_xlfn.IFNA(VLOOKUP(A40,'Personnel List'!A$1:F$1284,6,FALSE),"")
D41: =IF(A41<>"",IF(D41<>"",D41,NOW()),"") | E41: =IFERROR(VLOOKUP(A41,G:I,3,FALSE),"Onsite") -> Onsite | I41: =IF(G41<>"",IF(I41<>"",I41,NOW()),"") | J41: =SUBSTITUTE(A41,"NC","") | L41: 0 | N41: =_xlfn.IFNA(VLOOKUP(A41,'Personnel List'!A$1:F$1284,6,FALSE),"")
B42: =_xlfn.IFNA(VLOOKUP(A42,'Personnel List'!A$1:E$1284,5,FALSE),"") | C42: =_xlfn.IFNA(VLOOKUP(A42,'Personnel List'!A$1:E$1284,4,FALSE),"") | D42: =IF(A42<>"",IF(D42<>"",D42,NOW()),"") | E42: =IFERROR(VLOOKUP(A42,G:I,3,FALSE),"Onsite") -> Onsite | I42: =IF(G42<>"",IF(I42<>"",I42,NOW()),"") | J42: =SUBSTITUTE(A42,"NC","") | L42: 0 | N42: =_xlfn.IFNA(VLOOKUP(A42,'Personnel List'!A$1:F$1284,6,FALSE),"")
B43: =_xlfn.IFNA(VLOOKUP(A43,'Personnel List'!A$1:E$1284,5,FALSE),"") | C43: =_xlfn.IFNA(VLOOKUP(A43,'Personnel List'!A$1:E$1284,4,FALSE),"") | D43: =IF(A43<>"",IF(D43<>"",D43,NOW()),"") | E43: =IFERROR(VLOOKUP(A43,G:I,3,FALSE),"Onsite") -> Onsite | I43: =IF(G43<>"",IF(I43<>"",I43,NOW()),"") | J43: =SUBSTITUTE(A43,"NC","") | L43: 0 | N43: =_xlfn.IFNA(VLOOKUP(A43,'Personnel List'!A$1:F$1284,6,FALSE),"")
B44: =_xlfn.IFNA(VLOOKUP(A44,'Personnel List'!A$1:E$1284,5,FALSE),"") | C44: =_xlfn.IFNA(VLOOKUP(A44,'Personnel List'!A$1:E$1284,4,FALSE),"") | D44: =IF(A44<>"",IF(D44<>"",D44,NOW()),"") | E44: =IFERROR(VLOOKUP(A44,G:I,3,FALSE),"Onsite") -> Onsite | I44: =IF(G44<>"",IF(I44<>"",I44,NOW()),"") | J44: =SUBSTITUTE(A44,"NC","") | L44: 0 | N44: =_xlfn.IFNA(VLOOKUP(A44,'Personnel List'!A$1:F$1284,6,FALSE),"")
B45: =_xlfn.IFNA(VLOOKUP(A45,'Personnel List'!A$1:E$1284,5,FALSE),"") | C45: =_xlfn.IFNA(VLOOKUP(A45,'Personnel List'!A$1:E$1284,4,FALSE),"") | D45: =IF(A45<>"",IF(D45<>"",D45,NOW()),"") | E45: =IFERROR(VLOOKUP(A45,G:I,3,FALSE),"Onsite") -> Onsite | I45: =IF(G45<>"",IF(I45<>"",I45,NOW()),"") | J45: =SUBSTITUTE(A45,"NC","") | L45: 0 | N45: =_xlfn.IFNA(VLOOKUP(A45,'Personnel List'!A$1:F$1284,6,FALSE),"")
B46: =_xlfn.IFNA(VLOOKUP(A46,'Personnel List'!A$1:E$1284,5,FALSE),"") | C46: =_xlfn.IFNA(VLOOKUP(A46,'Personnel List'!A$1:E$1284,4,FALSE),"") | D46: =IF(A46<>"",IF(D46<>"",D46,NOW()),"") | E46: =IFERROR(VLOOKUP(A46,G:I,3,FALSE),"Onsite") -> Onsite | I46: =IF(G886<>"",IF(I46<>"",I46,NOW()),"") | J46: =SUBSTITUTE(A46,"NC","") | L46: 0 | N46: =_xlfn.IFNA(VLOOKUP(A46,'Personnel List'!A$1:F$1284,6,FALSE),"")
B47: =_xlfn.IFNA(VLOOKUP(A47,'Personnel List'!A$1:E$1284,5,FALSE),"") | C47: =_xlfn.IFNA(VLOOKUP(A47,'Personnel List'!A$1:E$1284,4,FALSE),"") | D47: =IF(A47<>"",IF(D47<>"",D47,NOW()),"") | E47: =IFERROR(VLOOKUP(A47,G:I,3,FALSE),"Onsite") -> Onsite | I47: =IF(G887<>"",IF(I47<>"",I47,NOW()),"") | J47: =SUBSTITUTE(A47,"NC","") | L47: 0 | N47: =_xlfn.IFNA(VLOOKUP(A47,'Personnel List'!A$1:F$1284,6,FALSE),"")
B48: =_xlfn.IFNA(VLOOKUP(A48,'Personnel List'!A$1:E$1284,5,FALSE),"") | C48: =_xlfn.IFNA(VLOOKUP(A48,'Personnel List'!A$1:E$1284,4,FALSE),"") | D48: =IF(A48<>"",IF(D48<>"",D48,NOW()),"") | E48: =IFERROR(VLOOKUP(A48,G:I,3,FALSE),"Onsite") -> Onsite | I48: =IF(G888<>"",IF(I48<>"",I48,NOW()),"") | J48: =SUBSTITUTE(A48,"NC","") | L48: 0 | N48: =_xlfn.IFNA(VLOOKUP(A48,'Personnel List'!A$1:F$1284,6,FALSE),"")
B49: =_xlfn.IFNA(VLOOKUP(A49,'Personnel List'!A$1:E$1284,5,FALSE),"") | C49: =_xlfn.IFNA(VLOOKUP(A49,'Personnel List'!A$1:E$1284,4,FALSE),"") | D49: =IF(A49<>"",IF(D49<>"",D49,NOW()),"") | E49: =IFERROR(VLOOKUP(A49,G:I,3,FALSE),"Onsite") -> Onsite | I49: =IF(G889<>"",IF(I49<>"",I49,NOW()),"") | J49: =SUBSTITUTE(A49,"NC","") | L49: 0 | N49: =_xlfn.IFNA(VLOOKUP(A49,'Personnel List'!A$1:F$1284,6,FALSE),"")
B50: =_xlfn.IFNA(VLOOKUP(A50,'Personnel List'!A$1:E$1284,5,FALSE),"") | C50: =_xlfn.IFNA(VLOOKUP(A50,'Personnel List'!A$1:E$1284,4,FALSE),"") | D50: =IF(A50<>"",IF(D50<>"",D50,NOW()),"") | E50: =IFERROR(VLOOKUP(A50,G:I,3,FALSE),"Onsite") -> Onsite | I50: =IF(G890<>"",IF(I50<>"",I50,NOW()),"") | J50: =SUBSTITUTE(A50,"NC","") | L50: 0 | N50: =_xlfn.IFNA(VLOOKUP(A50,'Personnel List'!A$1:F$1284,6,FALSE),"")
B51: =_xlfn.IFNA(VLOOKUP(A51,'Personnel List'!A$1:E$1284,5,FALSE),"") | C51: =_xlfn.IFNA(VLOOKUP(A51,'Personnel List'!A$1:E$1284,4,FALSE),"") | D51: =IF(A51<>"",IF(D51<>"",D51,NOW()),"") | E51: =IFERROR(VLOOKUP(A51,G:I,3,FALSE),"Onsite") -> Onsite | I51: =IF(G891<>"",IF(I51<>"",I51,NOW()),"") | J51: =SUBSTITUTE(A51,"NC","") | L51: 0 | N51: =_xlfn.IFNA(VLOOKUP(A51,'Personnel List'!A$1:F$1284,6,FALSE),"")
B52: =_xlfn.IFNA(VLOOKUP(A52,'Personnel List'!A$1:E$1284,5,FALSE),"") | C52: =_xlfn.IFNA(VLOOKUP(A52,'Personnel List'!A$1:E$1284,4,FALSE),"") | D52: =IF(A52<>"",IF(D52<>"",D52,NOW()),"") | E52: =IFERROR(VLOOKUP(A52,G:I,3,FALSE),"Onsite") -> Onsite | I52: =IF(G892<>"",IF(I52<>"",I52,NOW()),"") | J52: =SUBSTITUTE(A52,"NC","") | L52: 0 | N52: =_xlfn.IFNA(VLOOKUP(A52,'Personnel List'!A$1:F$1284,6,FALSE),"")
B53: =_xlfn.IFNA(VLOOKUP(A53,'Personnel List'!A$1:E$1284,5,FALSE),"") | D53: =IF(A53<>"",IF(D53<>"",D53,NOW()),"") | E53: =IFERROR(VLOOKUP(A53,G:I,3,FALSE),"Onsite") -> Onsite | I53: =IF(G893<>"",IF(I53<>"",I53,NOW()),"") | J53: =SUBSTITUTE(A53,"NC","") | L53: 0 | N53: =_xlfn.IFNA(VLOOKUP(A53,'Personnel List'!A$1:F$1284,6,FALSE),"")
B54: =_xlfn.IFNA(VLOOKUP(A54,'Personnel List'!A$1:E$1284,5,FALSE),"") | D54: =IF(A54<>"",IF(D54<>"",D54,NOW()),"") | E54: =IFERROR(VLOOKUP(A54,G:I,3,FALSE),"Onsite") -> Onsite | I54: =IF(G894<>"",IF(I54<>"",I54,NOW()),"") | J54: =SUBSTITUTE(A54,"NC","") | L54: 0 | N54: =_xlfn.IFNA(VLOOKUP(A54,'Personnel List'!A$1:F$1284,6,FALSE),"")
B55: =_xlfn.IFNA(VLOOKUP(A55,'Personnel List'!A$1:E$1284,5,FALSE),"") | C55: =_xlfn.IFNA(VLOOKUP(A55,'Personnel List'!A$1:E$1284,4,FALSE),"") | D55: =IF(A55<>"",IF(D55<>"",D55,NOW()),"") | E55: =IFERROR(VLOOKUP(A55,G:I,3,FALSE),"Onsite") -> Onsite | I55: =IF(G895<>"",IF(I55<>"",I55,NOW()),"") | J55: =SUBSTITUTE(A55,"NC","") | L55: 0 | N55: =_xlfn.IFNA(VLOOKUP(A55,'Personnel List'!A$1:F$1284,6,FALSE),"")
B56: =_xlfn.IFNA(VLOOKUP(A56,'Personnel List'!A$1:E$1284,5,FALSE),"") | C56: =_xlfn.IFNA(VLOOKUP(A56,'Personnel List'!A$1:E$1284,4,FALSE),"") | D56: =IF(A56<>"",IF(D56<>"",D56,NOW()),"") | E56: =IFERROR(VLOOKUP(A56,G:I,3,FALSE),"Onsite") -> Onsite | I56: =IF(G896<>"",IF(I56<>"",I56,NOW()),"") | J56: =SUBSTITUTE(A56,"NC","") | L56: 0 | N56: =_xlfn.IFNA(VLOOKUP(A56,'Personnel List'!A$1:F$1284,6,FALSE),"")
B57: =_xlfn.IFNA(VLOOKUP(A57,'Personnel List'!A$1:E$1284,5,FALSE),"") | C57: =_xlfn.IFNA(VLOOKUP(A57,'Personnel List'!A$1:E$1284,4,FALSE),"") | D57: =IF(A57<>"",IF(D57<>"",D57,NOW()),"") | E57: =IFERROR(VLOOKUP(A57,G:I,3,FALSE),"Onsite") -> Onsite | I57: =IF(G897<>"",IF(I57<>"",I57,NOW()),"") | J57: =SUBSTITUTE(A57,"NC","") | L57: 0 | N57: =_xlfn.IFNA(VLOOKUP(A57,'Personnel List'!A$1:F$1284,6,FALSE),"")
B58: =_xlfn.IFNA(VLOOKUP(A58,'Personnel List'!A$1:E$1284,5,FALSE),"") | C58: =_xlfn.IFNA(VLOOKUP(A58,'Personnel List'!A$1:E$1284,4,FALSE),"") | D58: =IF(A58<>"",IF(D58<>"",D58,NOW()),"") | E58: =IFERROR(VLOOKUP(A58,G:I,3,FALSE),"Onsite") -> Onsite | I58: =IF(G898<>"",IF(I58<>"",I58,NOW()),"") | J58: =SUBSTITUTE(A58,"NC","") | L58: 0 | N58: =_xlfn.IFNA(VLOOKUP(A58,'Personnel List'!A$1:F$1284,6,FALSE),"")
B59: =_xlfn.IFNA(VLOOKUP(A59,'Personnel List'!A$1:E$1284,5,FALSE),"") | C59: =_xlfn.IFNA(VLOOKUP(A59,'Personnel List'!A$1:E$1284,4,FALSE),"") | D59: =IF(A59<>"",IF(D59<>"",D59,NOW()),"") | E59: =IFERROR(VLOOKUP(A59,G:I,3,FALSE),"Onsite") -> Onsite | I59: =IF(G899<>"",IF(I59<>"",I59,NOW()),"") | J59: =SUBSTITUTE(A59,"NC","") | L59: 0 | N59: =_xlfn.IFNA(VLOOKUP(A59,'Personnel List'!A$1:F$1284,6,FALSE),"")
B60: =_xlfn.IFNA(VLOOKUP(A60,'Personnel List'!A$1:E$1284,5,FALSE),"") | C60: =_xlfn.IFNA(VLOOKUP(A60,'Personnel List'!A$1:E$1284,4,FALSE),"") | D60: =IF(A60<>"",IF(D60<>"",D60,NOW()),"") | E60: =IFERROR(VLOOKUP(A60,G:I,3,FALSE),"Onsite") -> Onsite | I60: =IF(G900<>"",IF(I60<>"",I60,NOW()),"") | J60: =SUBSTITUTE(A60,"NC","") | L60: 0 | N60: =_xlfn.IFNA(VLOOKUP(A60,'Personnel List'!A$1:F$1284,6,FALSE),"")
B61: =_xlfn.IFNA(VLOOKUP(A61,'Personnel List'!A$1:E$1284,5,FALSE),"") | C61: =_xlfn.IFNA(VLOOKUP(A61,'Personnel List'!A$1:E$1284,4,FALSE),"") | D61: =IF(A61<>"",IF(D61<>"",D61,NOW()),"") | E61: =IFERROR(VLOOKUP(A61,G:I,3,FALSE),"Onsite") -> Onsite | I61: =IF(G901<>"",IF(I61<>"",I61,NOW()),"") | J61: =SUBSTITUTE(A61,"NC","") | L61: 0 | N61: =_xlfn.IFNA(VLOOKUP(A61,'Personnel List'!A$1:F$1284,6,FALSE),"")
B62: =_xlfn.IFNA(VLOOKUP(A62,'Personnel List'!A$1:E$1284,5,FALSE),"") | C62: =_xlfn.IFNA(VLOOKUP(A62,'Personnel List'!A$1:E$1284,4,FALSE),"") | D62: =IF(A62<>"",IF(D62<>"",D62,NOW()),"") | E62: =IFERROR(VLOOKUP(A62,G:I,3,FALSE),"Onsite") -> Onsite | I62: =IF(G902<>"",IF(I62<>"",I62,NOW()),"") | J62: =SUBSTITUTE(A62,"NC","") | L62: 0 | N62: =_xlfn.IFNA(VLOOKUP(A62,'Personnel List'!A$1:F$1284,6,FALSE),"")
B63: =_xlfn.IFNA(VLOOKUP(A63,'Personnel List'!A$1:E$1284,5,FALSE),"") | C63: =_xlfn.IFNA(VLOOKUP(A63,'Personnel List'!A$1:E$1284,4,FALSE),"") | D63: =IF(A63<>"",IF(D63<>"",D63,NOW()),"") | E63: =IFERROR(VLOOKUP(A63,G:I,3,FALSE),"Onsite") -> Onsite | I63: =IF(G903<>"",IF(I63<>"",I63,NOW()),"") | J63: =SUBSTITUTE(A63,"NC","") | L63: 0 | N63: =_xlfn.IFNA(VLOOKUP(A63,'Personnel List'!A$1:F$1284,6,FALSE),"")
B64: =_xlfn.IFNA(VLOOKUP(A64,'Personnel List'!A$1:E$1284,5,FALSE),"") | C64: =_xlfn.IFNA(VLOOKUP(A64,'Personnel List'!A$1:E$1284,4,FALSE),"") | D64: =IF(A64<>"",IF(D64<>"",D64,NOW()),"") | E64: =IFERROR(VLOOKUP(A64,G:I,3,FALSE),"Onsite") -> Onsite | I64: =IF(G904<>"",IF(I64<>"",I64,NOW()),"") | J64: =SUBSTITUTE(A64,"NC","") | L64: 0 | N64: =_xlfn.IFNA(VLOOKUP(A64,'Personnel List'!A$1:F$1284,6,FALSE),"")
B65: =_xlfn.IFNA(VLOOKUP(A65,'Personnel List'!A$1:E$1284,5,FALSE),"") | C65: =_xlfn.IFNA(VLOOKUP(A65,'Personnel List'!A$1:E$1284,4,FALSE),"") | D65: =IF(A65<>"",IF(D65<>"",D65,NOW()),"") | E65: =IFERROR(VLOOKUP(A65,G:I,3,FALSE),"Onsite") -> Onsite | I65: =IF(G905<>"",IF(I65<>"",I65,NOW()),"") | J65: =SUBSTITUTE(A65,"NC","") | L65: 0 | N65: =_xlfn.IFNA(VLOOKUP(A65,'Personnel List'!A$1:F$1284,6,FALSE),"")
B66: =_xlfn.IFNA(VLOOKUP(A66,'Personnel List'!A$1:E$1284,5,FALSE),"") | C66: =_xlfn.IFNA(VLOOKUP(A66,'Personnel List'!A$1:E$1284,4,FALSE),"") | D66: =IF(A66<>"",IF(D66<>"",D66,NOW()),"") | E66: =IFERROR(VLOOKUP(A66,G:I,3,FALSE),"Onsite") -> Onsite | I66: =IF(G906<>"",IF(I66<>"",I66,NOW()),"") | J66: =SUBSTITUTE(A66,"NC","") | L66: 0 | N66: =_xlfn.IFNA(VLOOKUP(A66,'Personnel List'!A$1:F$1284,6,FALSE),"")
... B876: =_xlfn.IFNA(VLOOKUP(A876,'Personnel List'!A$1:E$1284,5,FALSE),"") | C876: =_xlfn.IFNA(VLOOKUP(A876,'Personnel List'!A$1:E$1284,4,FALSE),"") | D876: =IF(A876<>"",IF(D876<>"",D876,NOW()),"") | E876: =IFERROR(VLOOKUP(A876,G:I,3,FALSE),"Onsite") -> Onsite | I876: =IF(G1716<>"",IF(I876<>"",I876,NOW()),"") | J876: =SUBSTITUTE(A876,"NC","") | L876: 0 | N876: =_xlfn.IFNA(VLOOKUP(A876,'Personnel List'!A$1:F$1284,6,FALSE),"")
I877: =IF(G1717<>"",IF(I877<>"",I877,NOW()),"") | J877: =SUBSTITUTE(A877,"NC","") | L877: 0
L878: 0
L879: 0
L880: 0
L881: 0
L882: 0
L883: 0
L884: 0
L885: 0
L886: 0
L887: 0
L888: 0
L889: 0
... L1000: 0

Sheet Thu DS
A1: Scan ID | B1: Name | C1: Company Name | D1: Time In | E1: Time Out | G1: Scan Out | I1: Timestamp | J1: SAP Number | L1: Not Scanned Yet | M1: DS | N1: Reverse Name
A2: NC90112534 | B2: =_xlfn.IFNA(VLOOKUP(A2,'Personnel List'!A$1:E$1284,5,FALSE),"") -> Sonia Bott | C2: =_xlfn.IFNA(VLOOKUP(A2,'Personnel List'!A$1:E$1284,4,FALSE),"") -> Coates Pty Ltd | D2: =IF(A2<>"",IF(D2<>"",D2,NOW()),"") -> 45533.218 | E2: =IFERROR(VLOOKUP(A2,G:I,3,FALSE),"Onsite") -> Onsite | G2: NC23410 | I2: =IF(G2<>"",IF(I2<>"",I2,NOW()),"") -> 45533.595 | J2: =SUBSTITUTE(A2,"NC","") -> 90112534 | L2: {=_xlfn._xlws.FILTER(M2:M1000,(ISNA(MATCH(M2:M1000,N2:N1000,0))),"")} -> 0 | M2: {=_xlfn._xlws.FILTER('Thu Data'!E13:E863,ISNUMBER(_xlfn.XMATCH('Thu Data'!D13:D863,M1)))} -> #VALUE! | N2: =_xlfn.IFNA(VLOOKUP(A2,'Personnel List'!A$1:F$1284,6,FALSE),"") -> Bott, Sonia
A3: NC90117684 | B3: =_xlfn.IFNA(VLOOKUP(A3,'Personnel List'!A$1:E$1284,5,FALSE),"") -> Isobel Newman | C3: =_xlfn.IFNA(VLOOKUP(A3,'Personnel List'!A$1:E$1284,4,FALSE),"") -> Hays Personnel Services | D3: =IF(A3<>"",IF(D3<>"",D3,NOW()),"") -> 45533.228 | E3: =IFERROR(VLOOKUP(A3,G:I,3,FALSE),"Onsite") -> 45533.721 | G3: NC90060761 | I3: =IF(G3<>"",IF(I3<>"",I3,NOW()),"") -> 45533.651 | J3: =SUBSTITUTE(A3,"NC","") -> 90117684 | L3: 0 | N3: =_xlfn.IFNA(VLOOKUP(A3,'Personnel List'!A$1:F$1284,6,FALSE),"") -> Newman, Isobel
A4: NC90049722 | B4: =_xlfn.IFNA(VLOOKUP(A4,'Personnel List'!A$1:E$1284,5,FALSE),"") -> Leon Tioke | C4: =_xlfn.IFNA(VLOOKUP(A4,'Personnel List'!A$1:E$1284,4,FALSE),"") -> Technical Maintenance Support (TMS) | D4: =IF(A4<>"",IF(D4<>"",D4,NOW()),"") -> 45533.231 | E4: =IFERROR(VLOOKUP(A4,G:I,3,FALSE),"Onsite") -> Onsite | G4: NC90117684 | I4: =IF(G4<>"",IF(I4<>"",I4,NOW()),"") -> 45533.721 | J4: =SUBSTITUTE(A4,"NC","") -> 90049722 | L4: 0 | N4: =_xlfn.IFNA(VLOOKUP(A4,'Personnel List'!A$1:F$1284,6,FALSE),"") -> Tioke, Leon
A5: NC90070857 | B5: =_xlfn.IFNA(VLOOKUP(A5,'Personnel List'!A$1:E$1284,5,FALSE),"") -> Brodie Eaton | C5: =_xlfn.IFNA(VLOOKUP(A5,'Personnel List'!A$1:E$1284,4,FALSE),"") -> APMS | D5: =IF(A5<>"",IF(D5<>"",D5,NOW()),"") -> 45533.238 | E5: =IFERROR(VLOOKUP(A5,G:I,3,FALSE),"Onsite") -> Onsite | G5: NC3203 | I5: =IF(G5<>"",IF(I5<>"",I5,NOW()),"") -> 45534.21 | J5: =SUBSTITUTE(A5,"NC","") -> 90070857 | L5: 0 | N5: =_xlfn.IFNA(VLOOKUP(A5,'Personnel List'!A$1:F$1284,6,FALSE),"") -> Eaton, Brodie
A6: NC90136780 | B6: =_xlfn.IFNA(VLOOKUP(A6,'Personnel List'!A$1:E$1284,5,FALSE),"") | C6: =_xlfn.IFNA(VLOOKUP(A6,'Personnel List'!A$1:E$1284,4,FALSE),"") | D6: =IF(A6<>"",IF(D6<>"",D6,NOW()),"") -> 45533.238 | E6: =IFERROR(VLOOKUP(A6,G:I,3,FALSE),"Onsite") -> Onsite | I6: =IF(G6<>"",IF(I6<>"",I6,NOW()),"") | J6: =SUBSTITUTE(A6,"NC","") -> 90136780 | L6: 0 | N6: =_xlfn.IFNA(VLOOKUP(A6,'Personnel List'!A$1:F$1284,6,FALSE),"")
A7: NC90109011 | B7: =_xlfn.IFNA(VLOOKUP(A7,'Personnel List'!A$1:E$1284,5,FALSE),"") | C7: =_xlfn.IFNA(VLOOKUP(A7,'Personnel List'!A$1:E$1284,4,FALSE),"") | D7: =IF(A7<>"",IF(D7<>"",D7,NOW()),"") -> 45533.238 | E7: =IFERROR(VLOOKUP(A7,G:I,3,FALSE),"Onsite") -> Onsite | I7: =IF(G7<>"",IF(I7<>"",I7,NOW()),"") | J7: =SUBSTITUTE(A7,"NC","") -> 90109011 | L7: 0 | N7: =_xlfn.IFNA(VLOOKUP(A7,'Personnel List'!A$1:F$1284,6,FALSE),"")
A8: NC90122588 | B8: =_xlfn.IFNA(VLOOKUP(A8,'Personnel List'!A$1:E$1284,5,FALSE),"") -> Dion Pene-Gavin | C8: =_xlfn.IFNA(VLOOKUP(A8,'Personnel List'!A$1:E$1284,4,FALSE),"") -> Global Mill Relines | D8: =IF(A8<>"",IF(D8<>"",D8,NOW()),"") -> 45533.239 | E8: =IFERROR(VLOOKUP(A8,G:I,3,FALSE),"Onsite") -> Onsite | I8: =IF(G8<>"",IF(I8<>"",I8,NOW()),"") | J8: =SUBSTITUTE(A8,"NC","") -> 90122588 | L8: 0 | N8: =_xlfn.IFNA(VLOOKUP(A8,'Personnel List'!A$1:F$1284,6,FALSE),"") -> Pene-Gavin, Dion
A9: NC90135965 | B9: =_xlfn.IFNA(VLOOKUP(A9,'Personnel List'!A$1:E$1284,5,FALSE),"") | C9: =_xlfn.IFNA(VLOOKUP(A9,'Personnel List'!A$1:E$1284,4,FALSE),"") | D9: =IF(A9<>"",IF(D9<>"",D9,NOW()),"") -> 45533.239 | E9: =IFERROR(VLOOKUP(A9,G:I,3,FALSE),"Onsite") -> Onsite | I9: =IF(G9<>"",IF(I9<>"",I9,NOW()),"") | J9: =SUBSTITUTE(A9,"NC","") -> 90135965 | L9: 0 | N9: =_xlfn.IFNA(VLOOKUP(A9,'Personnel List'!A$1:F$1284,6,FALSE),"")
A10: NC90136947 | B10: =_xlfn.IFNA(VLOOKUP(A10,'Personnel List'!A$1:E$1284,5,FALSE),"") | C10: =_xlfn.IFNA(VLOOKUP(A10,'Personnel List'!A$1:E$1284,4,FALSE),"") | D10: =IF(A10<>"",IF(D10<>"",D10,NOW()),"") -> 45533.24 | E10: =IFERROR(VLOOKUP(A10,G:I,3,FALSE),"Onsite") -> Onsite | I10: =IF(G10<>"",IF(I10<>"",I10,NOW()),"") | J10: =SUBSTITUTE(A10,"NC","") -> 90136947 | L10: 0 | N10: =_xlfn.IFNA(VLOOKUP(A10,'Personnel List'!A$1:F$1284,6,FALSE),"")
A11: NC90094440 | B11: =_xlfn.IFNA(VLOOKUP(A11,'Personnel List'!A$1:E$1284,5,FALSE),"") -> Jarred Walker | C11: =_xlfn.IFNA(VLOOKUP(A11,'Personnel List'!A$1:E$1284,4,FALSE),"") -> Minprovise | D11: =IF(A11<>"",IF(D11<>"",D11,NOW()),"") -> 45533.256 | E11: =IFERROR(VLOOKUP(A11,G:I,3,FALSE),"Onsite") -> Onsite | I11: =IF(G11<>"",IF(I11<>"",I11,NOW()),"") | J11: =SUBSTITUTE(A11,"NC","") -> 90094440 | L11: 0 | N11: =_xlfn.IFNA(VLOOKUP(A11,'Personnel List'!A$1:F$1284,6,FALSE),"") -> Walker, Jarred
A12: NC90076757 | B12: =_xlfn.IFNA(VLOOKUP(A12,'Personnel List'!A$1:E$1284,5,FALSE),"") -> Weixin Zhang | C12: =_xlfn.IFNA(VLOOKUP(A12,'Personnel List'!A$1:E$1284,4,FALSE),"") -> Minprovise | D12: =IF(A12<>"",IF(D12<>"",D12,NOW()),"") -> 45533.257 | E12: =IFERROR(VLOOKUP(A12,G:I,3,FALSE),"Onsite") -> Onsite | I12: =IF(G12<>"",IF(I12<>"",I12,NOW()),"") | J12: =SUBSTITUTE(A12,"NC","") -> 90076757 | L12: 0 | N12: =_xlfn.IFNA(VLOOKUP(A12,'Personnel List'!A$1:F$1284,6,FALSE),"") -> Zhang, Weixin
A13: NC90136342 | B13: =_xlfn.IFNA(VLOOKUP(A13,'Personnel List'!A$1:E$1284,5,FALSE),"") -> Sean Gearing | C13: =_xlfn.IFNA(VLOOKUP(A13,'Personnel List'!A$1:E$1284,4,FALSE),"") -> Minprovise | D13: =IF(A13<>"",IF(D13<>"",D13,NOW()),"") -> 45533.257 | E13: =IFERROR(VLOOKUP(A13,G:I,3,FALSE),"Onsite") -> Onsite | I13: =IF(G13<>"",IF(I13<>"",I13,NOW()),"") | J13: =SUBSTITUTE(A13,"NC","") -> 90136342 | L13: 0 | N13: =_xlfn.IFNA(VLOOKUP(A13,'Personnel List'!A$1:F$1284,6,FALSE),"") -> Gearing, Sean
A14: NC90136343 | B14: =_xlfn.IFNA(VLOOKUP(A14,'Personnel List'!A$1:E$1284,5,FALSE),"") -> Thomas Ferrand | C14: =_xlfn.IFNA(VLOOKUP(A14,'Personnel List'!A$1:E$1284,4,FALSE),"") -> Minprovise | D14: =IF(A14<>"",IF(D14<>"",D14,NOW()),"") -> 45533.257 | E14: =IFERROR(VLOOKUP(A14,G:I,3,FALSE),"Onsite") -> Onsite | I14: =IF(G14<>"",IF(I14<>"",I14,NOW()),"") | J14: =SUBSTITUTE(A14,"NC","") -> 90136343 | L14: 0 | N14: =_xlfn.IFNA(VLOOKUP(A14,'Personnel List'!A$1:F$1284,6,FALSE),"") -> Ferrand, Thomas
A15: NC90073280 | B15: =_xlfn.IFNA(VLOOKUP(A15,'Personnel List'!A$1:E$1284,5,FALSE),"") -> Noel Costello | C15: =_xlfn.IFNA(VLOOKUP(A15,'Personnel List'!A$1:E$1284,4,FALSE),"") -> SMS Group Services | D15: =IF(A15<>"",IF(D15<>"",D15,NOW()),"") -> 45533.258 | E15: =IFERROR(VLOOKUP(A15,G:I,3,FALSE),"Onsite") -> Onsite | I15: =IF(G15<>"",IF(I15<>"",I15,NOW()),"") | J15: =SUBSTITUTE(A15,"NC","") -> 90073280 | L15: 0 | N15: =_xlfn.IFNA(VLOOKUP(A15,'Personnel List'!A$1:F$1284,6,FALSE),"") -> Costello, Noel
A16: NC90109838 | B16: =_xlfn.IFNA(VLOOKUP(A16,'Personnel List'!A$1:E$1284,5,FALSE),"") -> Thomas Rogers | C16: =_xlfn.IFNA(VLOOKUP(A16,'Personnel List'!A$1:E$1284,4,FALSE),"") -> SMS Group Services | D16: =IF(A16<>"",IF(D16<>"",D16,NOW()),"") -> 45533.258 | E16: =IFERROR(VLOOKUP(A16,G:I,3,FALSE),"Onsite") -> Onsite | I16: =IF(G16<>"",IF(I16<>"",I16,NOW()),"") | J16: =SUBSTITUTE(A16,"NC","") -> 90109838 | L16: 0 | N16: =_xlfn.IFNA(VLOOKUP(A16,'Personnel List'!A$1:F$1284,6,FALSE),"") -> Rogers, Thomas
A17: NC90135103 | B17: =_xlfn.IFNA(VLOOKUP(A17,'Personnel List'!A$1:E$1284,5,FALSE),"") -> Glenn Holmes | C17: =_xlfn.IFNA(VLOOKUP(A17,'Personnel List'!A$1:E$1284,4,FALSE),"") -> APMS | D17: =IF(A17<>"",IF(D17<>"",D17,NOW()),"") -> 45533.262 | E17: =IFERROR(VLOOKUP(A17,G:I,3,FALSE),"Onsite") -> Onsite | I17: =IF(G17<>"",IF(I17<>"",I17,NOW()),"") | J17: =SUBSTITUTE(A17,"NC","") -> 90135103 | L17: 0 | N17: =_xlfn.IFNA(VLOOKUP(A17,'Personnel List'!A$1:F$1284,6,FALSE),"") -> Holmes, Glenn
... A32: NC90138283 | B32: =_xlfn.IFNA(VLOOKUP(A32,'Personnel List'!A$1:E$1284,5,FALSE),"") | C32: =_xlfn.IFNA(VLOOKUP(A32,'Personnel List'!A$1:E$1284,4,FALSE),"") | D32: =IF(A32<>"",IF(D32<>"",D32,NOW()),"") -> 45533.265 | E32: =IFERROR(VLOOKUP(A32,G:I,3,FALSE),"Onsite") -> Onsite | I32: =IF(G32<>"",IF(I32<>"",I32,NOW()),"") | J32: =SUBSTITUTE(A32,"NC","") -> 90138283 | L32: 0 | N32: =_xlfn.IFNA(VLOOKUP(A32,'Personnel List'!A$1:F$1284,6,FALSE),"")
A33: NC20304 | B33: =_xlfn.IFNA(VLOOKUP(A33,'Personnel List'!A$1:E$1284,5,FALSE),"") -> Alistair Baker | E33: =IFERROR(VLOOKUP(A33,G:I,3,FALSE),"Onsite") -> Onsite | I33: =IF(G33<>"",IF(I33<>"",I33,NOW()),"") | J33: =SUBSTITUTE(A33,"NC","") -> 20304 | L33: 0 | N33: =_xlfn.IFNA(VLOOKUP(A33,'Personnel List'!A$1:F$1284,6,FALSE),"") -> Baker, Alistair
A34: NC90137948 | B34: =_xlfn.IFNA(VLOOKUP(A34,'Personnel List'!A$1:E$1284,5,FALSE),"") | C34: =_xlfn.IFNA(VLOOKUP(A34,'Personnel List'!A$1:E$1284,4,FALSE),"") | D34: =IF(A34<>"",IF(D34<>"",D34,NOW()),"") -> 45533.265 | E34: =IFERROR(VLOOKUP(A34,G:I,3,FALSE),"Onsite") -> Onsite | I34: =IF(G34<>"",IF(I34<>"",I34,NOW()),"") | J34: =SUBSTITUTE(A34,"NC","") -> 90137948 | L34: 0 | N34: =_xlfn.IFNA(VLOOKUP(A34,'Personnel List'!A$1:F$1284,6,FALSE),"")
A35: NC24719 | B35: =_xlfn.IFNA(VLOOKUP(A35,'Personnel List'!A$1:E$1284,5,FALSE),"") -> Emily Lane | C35: =_xlfn.IFNA(VLOOKUP(A35,'Personnel List'!A$1:E$1284,4,FALSE),"") -> Newmont | D35: =IF(A35<>"",IF(D35<>"",D35,NOW()),"") -> 45533.266 | E35: =IFERROR(VLOOKUP(A35,G:I,3,FALSE),"Onsite") -> Onsite | I35: =IF(G35<>"",IF(I35<>"",I35,NOW()),"") | J35: =SUBSTITUTE(A35,"NC","") -> 24719 | L35: 0 | N35: =_xlfn.IFNA(VLOOKUP(A35,'Personnel List'!A$1:F$1284,6,FALSE),"") -> Lane, Emily
A36: NC90130583 | B36: =_xlfn.IFNA(VLOOKUP(A36,'Personnel List'!A$1:E$1284,5,FALSE),"") -> Martin Mulhall | C36: =_xlfn.IFNA(VLOOKUP(A36,'Personnel List'!A$1:E$1284,4,FALSE),"") -> Mader Contracting | D36: =IF(A36<>"",IF(D36<>"",D36,NOW()),"") -> 45533.266 | E36: =IFERROR(VLOOKUP(A36,G:I,3,FALSE),"Onsite") -> Onsite | I36: =IF(G36<>"",IF(I36<>"",I36,NOW()),"") | J36: =SUBSTITUTE(A36,"NC","") -> 90130583 | L36: 0 | N36: =_xlfn.IFNA(VLOOKUP(A36,'Personnel List'!A$1:F$1284,6,FALSE),"") -> Mulhall, Martin
A37: NC90112330 | B37: =_xlfn.IFNA(VLOOKUP(A37,'Personnel List'!A$1:E$1284,5,FALSE),"") -> Shannon McGregor | C37: =_xlfn.IFNA(VLOOKUP(A37,'Personnel List'!A$1:E$1284,4,FALSE),"") -> Boom Cranes | D37: =IF(A37<>"",IF(D37<>"",D37,NOW()),"") -> 45533.266 | E37: =IFERROR(VLOOKUP(A37,G:I,3,FALSE),"Onsite") -> Onsite | I37: =IF(G37<>"",IF(I37<>"",I37,NOW()),"") | J37: =SUBSTITUTE(A37,"NC","") -> 90112330 | L37: 0 | N37: =_xlfn.IFNA(VLOOKUP(A37,'Personnel List'!A$1:F$1284,6,FALSE),"") -> McGregor, Shannon
A38: NC90094237 | B38: =_xlfn.IFNA(VLOOKUP(A38,'Personnel List'!A$1:E$1284,5,FALSE),"") -> Edward Santhanam | C38: =_xlfn.IFNA(VLOOKUP(A38,'Personnel List'!A$1:E$1284,4,FALSE),"") -> Losugen | D38: =IF(A38<>"",IF(D38<>"",D38,NOW()),"") -> 45533.266 | E38: =IFERROR(VLOOKUP(A38,G:I,3,FALSE),"Onsite") -> Onsite | I38: =IF(G38<>"",IF(I38<>"",I38,NOW()),"") | J38: =SUBSTITUTE(A38,"NC","") -> 90094237 | L38: 0 | N38: =_xlfn.IFNA(VLOOKUP(A38,'Personnel List'!A$1:F$1284,6,FALSE),"") -> Santhanam, Edward
A39: NC90040292 | B39: =_xlfn.IFNA(VLOOKUP(A39,'Personnel List'!A$1:E$1284,5,FALSE),"") -> Jerry Taura | C39: =_xlfn.IFNA(VLOOKUP(A39,'Personnel List'!A$1:E$1284,4,FALSE),"") -> SMS Group Services | D39: =IF(A39<>"",IF(D39<>"",D39,NOW()),"") -> 45533.266 | E39: =IFERROR(VLOOKUP(A39,G:I,3,FALSE),"Onsite") -> Onsite | I39: =IF(G39<>"",IF(I39<>"",I39,NOW()),"") | J39: =SUBSTITUTE(A39,"NC","") -> 90040292 | L39: 0 | N39: =_xlfn.IFNA(VLOOKUP(A39,'Personnel List'!A$1:F$1284,6,FALSE),"") -> Taura, Jerry
A40: NC90047222 | B40: =_xlfn.IFNA(VLOOKUP(A40,'Personnel List'!A$1:E$1284,5,FALSE),"") -> Russell-Kingi Tawaka | C40: =_xlfn.IFNA(VLOOKUP(A40,'Personnel List'!A$1:E$1284,4,FALSE),"") -> SMS Group Services | D40: =IF(A40<>"",IF(D40<>"",D40,NOW()),"") -> 45533.266 | E40: =IFERROR(VLOOKUP(A40,G:I,3,FALSE),"Onsite") -> Onsite | I40: =IF(G40<>"",IF(I40<>"",I40,NOW()),"") | J40: =SUBSTITUTE(A40,"NC","") -> 90047222 | L40: 0 | N40: =_xlfn.IFNA(VLOOKUP(A40,'Personnel List'!A$1:F$1284,6,FALSE),"") -> Tawaka, Russell-Kingi
A41: NC18062 | D41: =IF(A41<>"",IF(D41<>"",D41,NOW()),"") -> 45533.266 | E41: =IFERROR(VLOOKUP(A41,G:I,3,FALSE),"Onsite") -> Onsite | I41: =IF(G41<>"",IF(I41<>"",I41,NOW()),"") | J41: =SUBSTITUTE(A41,"NC","") -> 18062 | L41: 0 | N41: =_xlfn.IFNA(VLOOKUP(A41,'Personnel List'!A$1:F$1284,6,FALSE),"") -> Madronero, Angelo
A42: NC90040555 | B42: =_xlfn.IFNA(VLOOKUP(A42,'Personnel List'!A$1:E$1284,5,FALSE),"") -> Bradley Ness | C42: =_xlfn.IFNA(VLOOKUP(A42,'Personnel List'!A$1:E$1284,4,FALSE),"") -> SMS Group Services | D42: =IF(A42<>"",IF(D42<>"",D42,NOW()),"") -> 45533.266 | E42: =IFERROR(VLOOKUP(A42,G:I,3,FALSE),"Onsite") -> Onsite | I42: =IF(G42<>"",IF(I42<>"",I42,NOW()),"") | J42: =SUBSTITUTE(A42,"NC","") -> 90040555 | L42: 0 | N42: =_xlfn.IFNA(VLOOKUP(A42,'Personnel List'!A$1:F$1284,6,FALSE),"") -> Ness, Bradley
A43: NC23783 | B43: =_xlfn.IFNA(VLOOKUP(A43,'Personnel List'!A$1:E$1284,5,FALSE),"") -> Travis Cooper | C43: =_xlfn.IFNA(VLOOKUP(A43,'Personnel List'!A$1:E$1284,4,FALSE),"") -> Newmont | D43: =IF(A43<>"",IF(D43<>"",D43,NOW()),"") -> 45533.266 | E43: =IFERROR(VLOOKUP(A43,G:I,3,FALSE),"Onsite") -> Onsite | I43: =IF(G43<>"",IF(I43<>"",I43,NOW()),"") | J43: =SUBSTITUTE(A43,"NC","") -> 23783 | L43: 0 | N43: =_xlfn.IFNA(VLOOKUP(A43,'Personnel List'!A$1:F$1284,6,FALSE),"") -> Cooper, Travis
A44: NC24490 | B44: =_xlfn.IFNA(VLOOKUP(A44,'Personnel List'!A$1:E$1284,5,FALSE),"") -> Thomas Ryan | C44: =_xlfn.IFNA(VLOOKUP(A44,'Personnel List'!A$1:E$1284,4,FALSE),"") -> Newmont | D44: =IF(A44<>"",IF(D44<>"",D44,NOW()),"") -> 45533.266 | E44: =IFERROR(VLOOKUP(A44,G:I,3,FALSE),"Onsite") -> Onsite | I44: =IF(G44<>"",IF(I44<>"",I44,NOW()),"") | J44: =SUBSTITUTE(A44,"NC","") -> 24490 | L44: 0 | N44: =_xlfn.IFNA(VLOOKUP(A44,'Personnel List'!A$1:F$1284,6,FALSE),"") -> Ryan, Thomas
A45: NC22900 | B45: =_xlfn.IFNA(VLOOKUP(A45,'Personnel List'!A$1:E$1284,5,FALSE),"") -> Dominic Brown | C45: =_xlfn.IFNA(VLOOKUP(A45,'Personnel List'!A$1:E$1284,4,FALSE),"") -> Newmont | D45: =IF(A45<>"",IF(D45<>"",D45,NOW()),"") -> 45533.266 | E45: =IFERROR(VLOOKUP(A45,G:I,3,FALSE),"Onsite") -> Onsite | I45: =IF(G45<>"",IF(I45<>"",I45,NOW()),"") | J45: =SUBSTITUTE(A45,"NC","") -> 22900 | L45: 0 | N45: =_xlfn.IFNA(VLOOKUP(A45,'Personnel List'!A$1:F$1284,6,FALSE),"") -> Brown, Dominic
A46: NC90131908 | B46: =_xlfn.IFNA(VLOOKUP(A46,'Personnel List'!A$1:E$1284,5,FALSE),"") | C46: =_xlfn.IFNA(VLOOKUP(A46,'Personnel List'!A$1:E$1284,4,FALSE),"") | D46: =IF(A46<>"",IF(D46<>"",D46,NOW()),"") -> 45533.266 | E46: =IFERROR(VLOOKUP(A46,G:I,3,FALSE),"Onsite") -> Onsite | I46: =IF(G886<>"",IF(I46<>"",I46,NOW()),"") | J46: =SUBSTITUTE(A46,"NC","") -> 90131908 | L46: 0 | N46: =_xlfn.IFNA(VLOOKUP(A46,'Personnel List'!A$1:F$1284,6,FALSE),"")
A47: NC90118868 | B47: =_xlfn.IFNA(VLOOKUP(A47,'Personnel List'!A$1:E$1284,5,FALSE),"") -> Cameron Jones | C47: =_xlfn.IFNA(VLOOKUP(A47,'Personnel List'!A$1:E$1284,4,FALSE),"") -> Minprovise | D47: =IF(A47<>"",IF(D47<>"",D47,NOW()),"") -> 45533.266 | E47: =IFERROR(VLOOKUP(A47,G:I,3,FALSE),"Onsite") -> Onsite | I47: =IF(G887<>"",IF(I47<>"",I47,NOW()),"") | J47: =SUBSTITUTE(A47,"NC","") -> 90118868 | L47: 0 | N47: =_xlfn.IFNA(VLOOKUP(A47,'Personnel List'!A$1:F$1284,6,FALSE),"") -> Jones, Cameron
A48: NC24687 | B48: =_xlfn.IFNA(VLOOKUP(A48,'Personnel List'!A$1:E$1284,5,FALSE),"") -> Sean Smethurst | C48: =_xlfn.IFNA(VLOOKUP(A48,'Personnel List'!A$1:E$1284,4,FALSE),"") -> Newmont | D48: =IF(A48<>"",IF(D48<>"",D48,NOW()),"") -> 45533.266 | E48: =IFERROR(VLOOKUP(A48,G:I,3,FALSE),"Onsite") -> Onsite | I48: =IF(G888<>"",IF(I48<>"",I48,NOW()),"") | J48: =SUBSTITUTE(A48,"NC","") -> 24687 | L48: 0 | N48: =_xlfn.IFNA(VLOOKUP(A48,'Personnel List'!A$1:F$1284,6,FALSE),"") -> Smethurst, Sean
A49: NC22280 | B49: =_xlfn.IFNA(VLOOKUP(A49,'Personnel List'!A$1:E$1284,5,FALSE),"") -> Lee Coupe | C49: =_xlfn.IFNA(VLOOKUP(A49,'Personnel List'!A$1:E$1284,4,FALSE),"") -> Newmont | D49: =IF(A49<>"",IF(D49<>"",D49,NOW()),"") -> 45533.266 | E49: =IFERROR(VLOOKUP(A49,G:I,3,FALSE),"Onsite") -> Onsite | I49: =IF(G889<>"",IF(I49<>"",I49,NOW()),"") | J49: =SUBSTITUTE(A49,"NC","") -> 22280 | L49: 0 | N49: =_xlfn.IFNA(VLOOKUP(A49,'Personnel List'!A$1:F$1284,6,FALSE),"") -> Coupe, Lee
A50: NC3413 | B50: =_xlfn.IFNA(VLOOKUP(A50,'Personnel List'!A$1:E$1284,5,FALSE),"") -> Darren Lord | C50: =_xlfn.IFNA(VLOOKUP(A50,'Personnel List'!A$1:E$1284,4,FALSE),"") -> Newmont | D50: =IF(A50<>"",IF(D50<>"",D50,NOW()),"") -> 45533.266 | E50: =IFERROR(VLOOKUP(A50,G:I,3,FALSE),"Onsite") -> Onsite | I50: =IF(G890<>"",IF(I50<>"",I50,NOW()),"") | J50: =SUBSTITUTE(A50,"NC","") -> 3413 | L50: 0 | N50: =_xlfn.IFNA(VLOOKUP(A50,'Personnel List'!A$1:F$1284,6,FALSE),"") -> Lord, Darren
A51: NC4953 | B51: =_xlfn.IFNA(VLOOKUP(A51,'Personnel List'!A$1:E$1284,5,FALSE),"") -> Mark Neville | C51: =_xlfn.IFNA(VLOOKUP(A51,'Personnel List'!A$1:E$1284,4,FALSE),"") -> Newmont | D51: =IF(A51<>"",IF(D51<>"",D51,NOW()),"") -> 45533.266 | E51: =IFERROR(VLOOKUP(A51,G:I,3,FALSE),"Onsite") -> Onsite | I51: =IF(G891<>"",IF(I51<>"",I51,NOW()),"") | J51: =SUBSTITUTE(A51,"NC","") -> 4953 | L51: 0 | N51: =_xlfn.IFNA(VLOOKUP(A51,'Personnel List'!A$1:F$1284,6,FALSE),"") -> Neville, Mark
A52: NC3203 | B52: =_xlfn.IFNA(VLOOKUP(A52,'Personnel List'!A$1:E$1284,5,FALSE),"") -> Jason Madden | C52: =_xlfn.IFNA(VLOOKUP(A52,'Personnel List'!A$1:E$1284,4,FALSE),"") -> Newmont | D52: =IF(A52<>"",IF(D52<>"",D52,NOW()),"") -> 45533.266 | E52: =IFERROR(VLOOKUP(A52,G:I,3,FALSE),"Onsite") -> 45534.21 | I52: =IF(G892<>"",IF(I52<>"",I52,NOW()),"") | J52: =SUBSTITUTE(A52,"NC","") -> 3203 | L52: 0 | N52: =_xlfn.IFNA(VLOOKUP(A52,'Personnel List'!A$1:F$1284,6,FALSE),"") -> Madden, Jason
A53: NC19829 | B53: =_xlfn.IFNA(VLOOKUP(A53,'Personnel List'!A$1:E$1284,5,FALSE),"") -> Shaun Smith | D53: =IF(A53<>"",IF(D53<>"",D53,NOW()),"") -> 45533.267 | E53: =IFERROR(VLOOKUP(A53,G:I,3,FALSE),"Onsite") -> Onsite | I53: =IF(G893<>"",IF(I53<>"",I53,NOW()),"") | J53: =SUBSTITUTE(A53,"NC","") -> 19829 | L53: 0 | N53: =_xlfn.IFNA(VLOOKUP(A53,'Personnel List'!A$1:F$1284,6,FALSE),"") -> Smith, Shaun
A54: NC90118509 | B54: =_xlfn.IFNA(VLOOKUP(A54,'Personnel List'!A$1:E$1284,5,FALSE),"") -> Te Raukohe Kingi | D54: =IF(A54<>"",IF(D54<>"",D54,NOW()),"") -> 45533.294 | E54: =IFERROR(VLOOKUP(A54,G:I,3,FALSE),"Onsite") -> Onsite | I54: =IF(G894<>"",IF(I54<>"",I54,NOW()),"") | J54: =SUBSTITUTE(A54,"NC","") -> 90118509 | L54: 0 | N54: =_xlfn.IFNA(VLOOKUP(A54,'Personnel List'!A$1:F$1284,6,FALSE),"") -> Kingi, Te Raukohe
A55: NC90060761 | B55: =_xlfn.IFNA(VLOOKUP(A55,'Personnel List'!A$1:E$1284,5,FALSE),"") -> Troy Van Beek | C55: =_xlfn.IFNA(VLOOKUP(A55,'Personnel List'!A$1:E$1284,4,FALSE),"") -> United Forklift and Access Solution | D55: =IF(A55<>"",IF(D55<>"",D55,NOW()),"") -> 45533.442 | E55: =IFERROR(VLOOKUP(A55,G:I,3,FALSE),"Onsite") -> 45533.651 | I55: =IF(G895<>"",IF(I55<>"",I55,NOW()),"") | J55: =SUBSTITUTE(A55,"NC","") -> 90060761 | L55: 0 | N55: =_xlfn.IFNA(VLOOKUP(A55,'Personnel List'!A$1:F$1284,6,FALSE),"") -> Van Beek, Troy
B56: =_xlfn.IFNA(VLOOKUP(A56,'Personnel List'!A$1:E$1284,5,FALSE),"") | C56: =_xlfn.IFNA(VLOOKUP(A56,'Personnel List'!A$1:E$1284,4,FALSE),"") | D56: =IF(A56<>"",IF(D56<>"",D56,NOW()),"") | E56: =IFERROR(VLOOKUP(A56,G:I,3,FALSE),"Onsite") -> Onsite | I56: =IF(G896<>"",IF(I56<>"",I56,NOW()),"") | J56: =SUBSTITUTE(A56,"NC","") | L56: 0 | N56: =_xlfn.IFNA(VLOOKUP(A56,'Personnel List'!A$1:F$1284,6,FALSE),"")
